MUXR.v
module MUXR(hrdata,hreadyout,hresponse,hrdata_1,hrdata_2,hrdata_3,hreadyout_1,hreadyout_2,hreadyout_3,hresp_1,hresp_2,hresp_3,sel);


input [31:0] hrdata_1;
input [31:0] hrdata_2;
input [31:0] hrdata_3;

input hreadyout_1;
input hreadyout_2;
input hreadyout_3;

input hresp_1;
input hresp_2;
input hresp_3;

input [2:0] sel;

output reg [31:0] hrdata;
output reg hreadyout;
output reg hresponse;


always @(*)
    case (sel)
        3'b000:
            begin

                hrdata = hrdata_1;
                hreadyout = hreadyout_1;
                hresponse = hresp_1;
                  
            end


        3'b001:
            begin

                hrdata = hrdata_2;
                hreadyout = hreadyout_2;
                hresponse = hresp_2;

            end

        3'b010:
            begin

                hrdata = hrdata_3;
                hreadyout = hreadyout_3;
                hresponse = hresp_3;

            end

       default:
            begin

                hrdata = 0;
                hreadyout = 1'b0;
                hresponse = 1'b0;

            end


    endcase


endmodule

MUXR_tb.v
`timescale 1ns/1ns
`include "MUXR.v"  //include other designe files here

module MUXR_tb; //change this 

//define variable
reg [31:0] hrdata_1,hrdata_2,hrdata_3;
reg hreadyout_1, hreadyout_2,hreadyout_3;
reg hresp_1,hresp_2,hresp_3;
reg [2:0] sel;

wire [31:0] hrdata;
wire hreadyout,hresponse;

MUXR uut(hrdata,hreadyout,hresponse,hrdata_1,hrdata_2,hrdata_3,hreadyout_1,hreadyout_2,hreadyout_3,hresp_1,hresp_2,hresp_3,sel);

initial begin

      $dumpfile("MUXR_tb.vcd");
      $dumpvars(0,MUXR_tb);

      //enter the test code here
      #20;
      hrdata_1 = 10;#1;
      hreadyout_1 = 1'b1;#1;
      hresp_1 = 1'b1;#1;
      

      hrdata_2 = 45;#1;
      hreadyout_2 = 1'b0;#1;
      hresp_2 = 1'b0;#1;
      

      hrdata_3 = 55;#1;
      hreadyout_3 = 1'b1;#1;
      hresp_3 = 1'b1;#1;
      

      #20
      sel = 3'b000; #50;
      sel = 3'b001; #50;
      sel = 3'b010; #50;


      $display("End of test!!!");

end

endmodule

MUXR_tb.vcd
$date
	Fri Dec 22 20:46:09 2023
$end
$version
	Icarus Verilog
$end
$timescale
	1ns
$end
$scope module MUXR_tb $end
$var wire 1 ! hresponse $end
$var wire 1 " hreadyout $end
$var wire 32 # hrdata [31:0] $end
$var reg 32 $ hrdata_1 [31:0] $end
$var reg 32 % hrdata_2 [31:0] $end
$var reg 32 & hrdata_3 [31:0] $end
$var reg 1 ' hreadyout_1 $end
$var reg 1 ( hreadyout_2 $end
$var reg 1 ) hreadyout_3 $end
$var reg 1 * hresp_1 $end
$var reg 1 + hresp_2 $end
$var reg 1 , hresp_3 $end
$var reg 3 - sel [2:0] $end
$scope module uut $end
$var wire 32 . hrdata_1 [31:0] $end
$var wire 32 / hrdata_2 [31:0] $end
$var wire 32 0 hrdata_3 [31:0] $end
$var wire 1 ' hreadyout_1 $end
$var wire 1 ( hreadyout_2 $end
$var wire 1 ) hreadyout_3 $end
$var wire 1 * hresp_1 $end
$var wire 1 + hresp_2 $end
$var wire 1 , hresp_3 $end
$var wire 3 1 sel [2:0] $end
$var reg 32 2 hrdata [31:0] $end
$var reg 1 " hreadyout $end
$var reg 1 ! hresponse $end
$upscope $end
$upscope $end
$enddefinitions $end
$comment Show the parameter values. $end
$dumpall
$end
#0
$dumpvars
bx 2
bx 1
bx 0
bx /
bx .
bx -
x,
x+
x*
x)
x(
x'
bx &
bx %
bx $
bx #
x"
x!
$end
#20
0!
0"
b0 #
b0 2
b1010 $
b1010 .
#21
1'
#22
1*
#23
b101101 %
b101101 /
#24
0(
#25
0+
#26
b110111 &
b110111 0
#27
1)
#28
1,
#49
1!
1"
b1010 #
b1010 2
b0 -
b0 1
#99
0!
0"
b101101 #
b101101 2
b1 -
b1 1
#149
1!
1"
b110111 #
b110111 2
b10 -
b10 1
