slave_control.v
module slave_control(slrsp_1, sl_rdy_1,clk,rst,sw1,sa1);

//module control_test_1(sel1,sel2,sel3,sel4,start,done,clk,mux1,mux2);

input clk;
output reg slrsp_1,sl_rdy_1,rst,sw1,sa1;

reg [2:0] state;
parameter s0=3'b000, s1=3'b001, s2=3'b010, s3=3'b011, s4=3'b100;

always @(posedge clk)
    begin
        case (state)
            s0: state <= s1;
            s1: state <= s2;
            s2: state <= s3;
            s3: state <= s4;
            s4: state <= s0;
            
            default: state <= s0;
        endcase
    end

always @(state)
    begin
        case (state)
            s0: begin #1 slrsp_1 = 0; sl_rdy_1 = 0; rst = 0; sw1 = 0; sa1 = 0; end
            s1: begin #1 slrsp_1 = 0; sl_rdy_1 = 1; rst = 0; sw1 = 0; sa1 = 0; end
            s2: begin #1 slrsp_1 = 0; sl_rdy_1 = 0; rst = 0; sw1 = 0; sa1 = 1; end
            s3: begin #1 slrsp_1 = 0; sl_rdy_1 = 0; rst = 0; sw1 = 1; sa1 = 0; end
            s4: begin #1 slrsp_1 = 0; sl_rdy_1 = 0; rst = 0; sw1 = 0; sa1 = 0;  end
            
            default: begin #1 slrsp_1 = 0; sl_rdy_1 = 0; rst = 0; sw1 = 0; sa1 = 0; end
        
        endcase

    end

endmodule

PIPOD.v
module PIPOD(dout,din,ld,clk);
    input [31:0] din;
    input ld,clk;
    output reg [31:0] dout;

    always @(posedge clk)
        if (ld) 
            dout <= din;

endmodule

COMPAR.v
module COMPAR(
  input [15:0] A, B,
  output reg  A_eq_B);
  
  always@(*) 
    begin
        if(A==B)
            A_eq_B = 1'b1;
        else
            A_eq_B = 1'b0;

    end
endmodule

PIPO.v
module PIPO(dout,din,ld,clk);
    input [15:0] din;
    input ld,clk;
    output reg [15:0] dout;

    always @(posedge clk)
        begin
            if (ld) 
                dout <= din;
            else
                dout <= 16'bz; 
        end
endmodule

slave_data_path.v
module slave_data_path(slrsp_1, sl_rdy_1,HADDR1,clk,hsel_1,rst,HWDATA1,sadd,sw1,sa1);

    input hsel_1,rst,sw1,sa1,clk;
    input [15:0] HADDR1,sadd;
    input [31:0] HWDATA1;

    output slrsp_1,sl_rdy_1;
    //output [31:0] hrdata_1;

    wire [15:0] SA;
    wire [31:0] SD,Q;
    wire COMP;

    PIPO SHADDR1 (SA,HADDR1,sa1,clk);
    PIPOD SHWDATA1 (SD,HWDATA1,sw1,clk);

    COMPAR add_compare(HADDR1,sadd,COMP);

    PIPOD SHADDR2 (Q,SD,COMP,clk);

   
    //PIPOD HWDATA2 (q,data_in4,sel4,clk);

endmodule

slave_test_tb.v
`timescale 1ns/1ns
`include "slave_control.v"
`include "slave_data_path.v"
`include "COMPAR.v"
`include "PIPO.v"
`include "PIPOD.v"

module slave_test_tb;

reg [15:0] HADDR1,sadd;
reg [31:0] HWDATA1;

reg clk;

slave_data_path slve_dpt(slrsp_1, sl_rdy_1,HADDR1,clk,hsel_1,rst,HWDATA1,sadd,sw1,sa1);
slave_control slave_cpt(slrsp_1, sl_rdy_1,clk,rst,sw1,sa1);
initial
    begin
        clk = 1'b0;
        #500 $finish;
    end

always #5 clk = ~clk;

initial
    begin

        #1
        HADDR1 = 16'b0000000000001000; #1;
        sadd = 16'b0000000000001000; #1;
        HWDATA1 = 20; #1;

       
    end

initial
    begin
    
        $dumpfile("slave_test_tb.vcd");
        $dumpvars(0,slave_test_tb);
        $display("End of test!!!");

    end

endmodule

slave_test_tb.vcd
$date
	Sat Dec 23 12:02:50 2023
$end
$version
	Icarus Verilog
$end
$timescale
	1ns
$end
$scope module slave_test_tb $end
$var wire 1 ! hsel_1 $end
$var wire 1 " sw1 $end
$var wire 1 # slrsp_1 $end
$var wire 1 $ sl_rdy_1 $end
$var wire 1 % sa1 $end
$var wire 1 & rst $end
$var reg 16 ' HADDR1 [15:0] $end
$var reg 32 ( HWDATA1 [31:0] $end
$var reg 1 ) clk $end
$var reg 16 * sadd [15:0] $end
$scope module slave_cpt $end
$var wire 1 ) clk $end
$var parameter 3 + s0 $end
$var parameter 3 , s1 $end
$var parameter 3 - s2 $end
$var parameter 3 . s3 $end
$var parameter 3 / s4 $end
$var reg 1 & rst $end
$var reg 1 % sa1 $end
$var reg 1 $ sl_rdy_1 $end
$var reg 1 # slrsp_1 $end
$var reg 3 0 state [2:0] $end
$var reg 1 " sw1 $end
$upscope $end
$scope module slve_dpt $end
$var wire 16 1 HADDR1 [15:0] $end
$var wire 32 2 HWDATA1 [31:0] $end
$var wire 1 ) clk $end
$var wire 1 ! hsel_1 $end
$var wire 1 & rst $end
$var wire 1 % sa1 $end
$var wire 16 3 sadd [15:0] $end
$var wire 1 $ sl_rdy_1 $end
$var wire 1 # slrsp_1 $end
$var wire 1 " sw1 $end
$var wire 32 4 SD [31:0] $end
$var wire 16 5 SA [15:0] $end
$var wire 32 6 Q [31:0] $end
$var wire 1 7 COMP $end
$scope module SHADDR1 $end
$var wire 1 ) clk $end
$var wire 16 8 din [15:0] $end
$var wire 1 % ld $end
$var reg 16 9 dout [15:0] $end
$upscope $end
$scope module SHADDR2 $end
$var wire 1 ) clk $end
$var wire 1 7 ld $end
$var wire 32 : din [31:0] $end
$var reg 32 ; dout [31:0] $end
$upscope $end
$scope module SHWDATA1 $end
$var wire 1 ) clk $end
$var wire 32 < din [31:0] $end
$var wire 1 " ld $end
$var reg 32 = dout [31:0] $end
$upscope $end
$scope module add_compare $end
$var wire 16 > A [15:0] $end
$var wire 16 ? B [15:0] $end
$var reg 1 7 A_eq_B $end
$upscope $end
$upscope $end
$upscope $end
$enddefinitions $end
$comment Show the parameter values. $end
$dumpall
b100 /
b11 .
b10 -
b1 ,
b0 +
$end
#0
$dumpvars
bx ?
bx >
bx =
bx <
bx ;
bx :
bx 9
bx 8
x7
bx 6
bx 5
bx 4
bx 3
bx 2
bx 1
bx 0
bx *
0)
bx (
bx '
x&
x%
x$
x#
x"
z!
$end
#1
07
b1000 '
b1000 1
b1000 8
b1000 >
#2
17
b1000 *
b1000 3
b1000 ?
#3
b10100 (
b10100 2
b10100 <
#5
b0 0
1)
#6
0%
0"
0&
0$
0#
#10
0)
#15
b1 0
1)
#16
1$
#20
0)
#25
b10 0
1)
#26
1%
0$
#30
0)
#35
b11 0
b1000 5
b1000 9
1)
#36
0%
1"
#40
0)
#45
b10100 4
b10100 :
b10100 =
b100 0
1)
#46
0"
#50
0)
#55
b0 0
b10100 6
b10100 ;
1)
#60
0)
#65
b1 0
1)
#66
1$
#70
0)
#75
b10 0
1)
#76
1%
0$
#80
0)
#85
b11 0
1)
#86
0%
1"
#90
0)
#95
b100 0
1)
#96
0"
#100
0)
#105
b0 0
1)
#110
0)
#115
b1 0
1)
#116
1$
#120
0)
#125
b10 0
1)
#126
1%
0$
#130
0)
#135
b11 0
1)
#136
0%
1"
#140
0)
#145
b100 0
1)
#146
0"
#150
0)
#155
b0 0
1)
#160
0)
#165
b1 0
1)
#166
1$
#170
0)
#175
b10 0
1)
#176
1%
0$
#180
0)
#185
b11 0
1)
#186
0%
1"
#190
0)
#195
b100 0
1)
#196
0"
#200
0)
#205
b0 0
1)
#210
0)
#215
b1 0
1)
#216
1$
#220
0)
#225
b10 0
1)
#226
1%
0$
#230
0)
#235
b11 0
1)
#236
0%
1"
#240
0)
#245
b100 0
1)
#246
0"
#250
0)
#255
b0 0
1)
#260
0)
#265
b1 0
1)
#266
1$
#270
0)
#275
b10 0
1)
#276
1%
0$
#280
0)
#285
b11 0
1)
#286
0%
1"
#290
0)
#295
b100 0
1)
#296
0"
#300
0)
#305
b0 0
1)
#310
0)
#315
b1 0
1)
#316
1$
#320
0)
#325
b10 0
1)
#326
1%
0$
#330
0)
#335
b11 0
1)
#336
0%
1"
#340
0)
#345
b100 0
1)
#346
0"
#350
0)
#355
b0 0
1)
#360
0)
#365
b1 0
1)
#366
1$
#370
0)
#375
b10 0
1)
#376
1%
0$
#380
0)
#385
b11 0
1)
#386
0%
1"
#390
0)
#395
b100 0
1)
#396
0"
#400
0)
#405
b0 0
1)
#410
0)
#415
b1 0
1)
#416
1$
#420
0)
#425
b10 0
1)
#426
1%
0$
#430
0)
#435
b11 0
1)
#436
0%
1"
#440
0)
#445
b100 0
1)
#446
0"
#450
0)
#455
b0 0
1)
#460
0)
#465
b1 0
1)
#466
1$
#470
0)
#475
b10 0
1)
#476
1%
0$
#480
0)
#485
b11 0
1)
#486
0%
1"
#490
0)
#495
b100 0
1)
#496
0"
