control_test_1.v
module control_test_1(sel1,sel2,start,done,clk,mux1);
input clk,start;
output reg sel1,sel2,mux1,done;

reg [2:0] state;
parameter s0=3'b000, s1=3'b001, s2=3'b010, s3=3'b011, s4=3'b100;

always @(posedge clk)
    begin
        case (state)
            s0: if (start) state <= s1;
            s1: state <= s2;
            s2: state <= s3;
            s3: state <= s4;
            s4: state <= s0;
            default: state <= s0;
        endcase
    end

always @(state)
    begin
        case (state)
            s0: begin #1 sel1=0; sel2 = 0; mux1 = 0; done=0; end
            s1: begin #1 sel1=1; sel2 = 0; mux1 = 0; done=0; end
            s2: begin #1 sel2=1; sel1 = 0; mux1 = 0; done=0;end
            s3: begin #1 mux1=1; sel2 = 0; sel1 = 0; done=0;end
            s4: begin #1 done=1; sel1 = 0; sel2 = 0; mux1=0; end
            default: begin #1 sel1=0; sel2 = 0; mux1 = 0; end
        
        endcase

    end

endmodule

MUXR.v
module MUXR(

hrdata_1,
hrdata_2,
hrdata_3,

hreadyout_1,
hreadyout_2,
hreadyout_3,

hresp_1,
hresp_2,
hresp_3,

sel,

hrdata,
hreadyout,
hresponse

);


input [31:0] hrdata_1;
input [31:0] hrdata_2;
input [31:0] hrdata_3;

input hreadyout_1;
input hreadyout_2;
input hreadyout_3;

input hresp_1;
input hresp_2;
input hresp_3;

input [1:0] sel

output reg [31:0] hrdata;
output reg hrdata;
output reg hresponse;


always @(*)
    case (sel)
        2'b00:
            begin

                hrdata = hrdata_1;
                hreadyout = hreadyout_1;
                hresponse = hresp_1;
                  
            end


        2'b01:
            begin

                hrdata = hrdata_2;
                hreadyout = hreadyout_2;
                hresponse = hresp_2;

            end

        2'b10:
            begin

                hrdata = hrdata_3;
                hreadyout = hreadyout_3;
                hresponse = hresp_3;

            end

       default:
            begin

                hrdata = hrdata_2;
                hreadyout = hreadyout_2;
                hresponse = hresp_2;

            end


    endcase


endmodule

decoder.v
module decoder(

hsel_0,// hSelect  slave0  
hsel_1,//hSelect  slave1  
hsel_2,//hSelect  slave2  
haddr,// Input address from the Address mux

//sel_slave//To read data response MUX

);

 input [15:0] haddr;
 output hsel_0;
 output hsel_1;
 output hsel_2;
 
 always @(*)
    case (haddr[15:14])
        2'b00:
            begin
              hsel_0 = 1'b1;
              hsel_1 = 1'b0;
              hsel_2 = 1'b0;
            end

        2'b01:
            begin
              hsel_0 = 1'b0;
              hsel_1 = 1'b1;
              hsel_2 = 1'b0;
            end

        2'b10:
            begin
              hsel_0 = 1'b0;
              hsel_1 = 1'b0;
              hsel_2 = 1'b1;
            end
        default:
            begin
              hsel_0 = 1'b0;
              hsel_1 = 1'b0;
              hsel_2 = 1'b0;
            end

    endcase
    


endmodule

MUXD.v
module MUXD(out, in0, in1, sel);

input sel;
input [31:0]in0, in1;
output [31:0]out;

assign out = sel ? in1 : in0;

endmodule

MUX.v
module MUX(out, in0, in1, sel);

input sel;
input [15:0]in0, in1;
output [15:0]out;

assign out = sel ? in1 : in0;

endmodule

PIPOD.v
module PIPOD(dout,din,ld,clk);
    input [31:0] din;
    input ld,clk;
    output reg [31:0] dout;

    always @(posedge clk)
        if (ld) 
            dout <= din;

endmodule

PIPO.v
module PIPO(dout,din,ld,clk);
    input [15:0] din;
    input ld,clk;
    output reg [15:0] dout;

    always @(posedge clk)
        begin
            if (ld) 
                dout <= din;
            else
                dout <= 16'bz; 
        end
endmodule

data_path_test_1.v
module data_path_test_1(sel1,sel2,sel3,sel4,mux1,mux2,data_in1,data_in2,data_in3,data_in4,clk,hsel_1,hsel_2,hsel_3,
                                hrdata,hreadyout,hresponse,hrdata_1,hrdata_2,hrdata_3,hreadyout_1,hreadyout_2,hreadyout_3,hresp_1,hresp_2,hresp_3,sel);

    input sel1,sel2,sel3,sel4,mux1,mux2,clk;
    input [15:0] data_in1, data_in2;
    input [31:0] data_in3, data_in4;


    input [31:0] hrdata_1,hrdata_2,hrdata_3;
    input hreadyout_1,hreadyout_2,hreadyout_3,hresp_1,hresp_2,hresp_3;
    input [2:0] sel;

    output [31:0] hrdata;
    output hreadyout,hresponse;


    output hsel_1,hsel_2,hsel_3;
    
    

    wire [15:0] z,x,y;
    wire [31:0] p,q,r;
    
//This part has some errors
    assign sel[0] = test1_dec(hsel_1);
    assign sel[1] = hsel_2;
    assign sel[2] = hsel_3;
   

    PIPO HADDR1 (x,data_in1,sel1,clk);
    PIPO HADDR2 (y,data_in2,sel2,clk);

    PIPOD HWDATA1 (p,data_in3,sel3,clk);
    PIPOD HWDATA2 (q,data_in4,sel4,clk);

    MUX addressmux (z,x,y,mux1);
    MUXD datamux (r,p,q,mux2);
    decoder test1_dec (hsel_1,hsel_2,hsel_3,z);

    MUXR readmux (hrdata,hreadyout,hresponse,hrdata_1,hrdata_2,hrdata_3,hreadyout_1,hreadyout_2,hreadyout_3,hresp_1,hresp_2,hresp_3,sel);

    
endmodule

test1_tb.v
`timescale 1ns/1ns
`include "control_test_1.v"
`include "data_path_test_1.v"
`include "MUX.v"
`include "PIPO.v"
`include "decoder.v"

module test1_tb;

reg [15:0] data_in1,data_in2;
reg clk, start;
wire done;

data_path_test_1 dpt1 (sel1,sel2,mux1,data_in1,data_in2,clk,hsel_1,hsel_2,hsel_3);
control_test_1 cpt1(sel1,sel2,start,done,clk,mux1);

initial
    begin
        clk = 1'b0;
        #3 start = 1'b1;
        #500 $finish;
    end

always #5 clk = ~clk;

initial
    begin

        #1
        data_in1 = 16'b0000000000001000; #1;
        data_in2 = 16'b0100000000001000; #1;
        //data_in2 = 16'b1000000000001000; #50;
        //data_in1 = 16'b0000000000001000; #1;

       
    end

initial
    begin
    
        $dumpfile("test1_tb.vcd");
        $dumpvars(0,test1_tb);
        $display("End of test!!!");

    end

endmodule

test1_tb.vcd
$date
	Fri Dec 22 16:28:47 2023
$end
$version
	Icarus Verilog
$end
$timescale
	1ns
$end
$scope module test1_tb $end
$var wire 1 ! sel2 $end
$var wire 1 " sel1 $end
$var wire 1 # mux1 $end
$var wire 1 $ hsel_3 $end
$var wire 1 % hsel_2 $end
$var wire 1 & hsel_1 $end
$var wire 1 ' done $end
$var reg 1 ( clk $end
$var reg 16 ) data_in1 [15:0] $end
$var reg 16 * data_in2 [15:0] $end
$var reg 1 + start $end
$scope module cpt1 $end
$var wire 1 ( clk $end
$var wire 1 + start $end
$var parameter 3 , s0 $end
$var parameter 3 - s1 $end
$var parameter 3 . s2 $end
$var parameter 3 / s3 $end
$var parameter 3 0 s4 $end
$var reg 1 ' done $end
$var reg 1 # mux1 $end
$var reg 1 " sel1 $end
$var reg 1 ! sel2 $end
$var reg 3 1 state [2:0] $end
$upscope $end
$scope module dpt1 $end
$var wire 1 ( clk $end
$var wire 16 2 data_in1 [15:0] $end
$var wire 16 3 data_in2 [15:0] $end
$var wire 1 # mux1 $end
$var wire 1 " sel1 $end
$var wire 1 ! sel2 $end
$var wire 16 4 z [15:0] $end
$var wire 16 5 y [15:0] $end
$var wire 16 6 x [15:0] $end
$var wire 1 $ hsel_3 $end
$var wire 1 % hsel_2 $end
$var wire 1 & hsel_1 $end
$scope module HADDR1 $end
$var wire 1 ( clk $end
$var wire 16 7 din [15:0] $end
$var wire 1 " ld $end
$var reg 16 8 dout [15:0] $end
$upscope $end
$scope module HADDR2 $end
$var wire 1 ( clk $end
$var wire 16 9 din [15:0] $end
$var wire 1 ! ld $end
$var reg 16 : dout [15:0] $end
$upscope $end
$scope module addressmux $end
$var wire 16 ; in0 [15:0] $end
$var wire 16 < in1 [15:0] $end
$var wire 1 # sel $end
$var wire 16 = out [15:0] $end
$upscope $end
$scope module test1_dec $end
$var wire 16 > haddr [15:0] $end
$var reg 1 & hsel_0 $end
$var reg 1 % hsel_1 $end
$var reg 1 $ hsel_2 $end
$upscope $end
$upscope $end
$upscope $end
$enddefinitions $end
$comment Show the parameter values. $end
$dumpall
b100 0
b11 /
b10 .
b1 -
b0 ,
$end
#0
$dumpvars
bx >
bx =
bx <
bx ;
bx :
bx 9
bx 8
bx 7
bx 6
bx 5
bx 4
bx 3
bx 2
bx 1
x+
bx *
bx )
0(
x'
x&
x%
x$
x#
x"
x!
$end
#1
b1000 )
b1000 2
b1000 7
#2
b100000000001000 *
b100000000001000 3
b100000000001000 9
#3
1+
#5
b0 1
1(
#6
0'
0#
0!
0"
#10
0(
#15
b1 1
1(
#16
1"
#20
0(
#25
0$
0%
1&
b1000 4
b1000 =
b1000 >
b1000 6
b1000 8
b1000 ;
b10 1
1(
#26
0"
1!
#30
0(
#35
b11 1
b100000000001000 5
b100000000001000 :
b100000000001000 <
1(
#36
1%
0&
b100000000001000 4
b100000000001000 =
b100000000001000 >
0!
1#
#40
0(
#45
b100 1
1(
#46
0%
1&
b1000 4
b1000 =
b1000 >
0#
1'
#50
0(
#55
b0 1
1(
#56
0'
#60
0(
#65
b1 1
1(
#66
1"
#70
0(
#75
b10 1
1(
#76
0"
1!
#80
0(
#85
b11 1
1(
#86
1%
0&
b100000000001000 4
b100000000001000 =
b100000000001000 >
0!
1#
#90
0(
#95
b100 1
1(
#96
0%
1&
b1000 4
b1000 =
b1000 >
0#
1'
#100
0(
#105
b0 1
1(
#106
0'
#110
0(
#115
b1 1
1(
#116
1"
#120
0(
#125
b10 1
1(
#126
0"
1!
#130
0(
#135
b11 1
1(
#136
1%
0&
b100000000001000 4
b100000000001000 =
b100000000001000 >
0!
1#
#140
0(
#145
b100 1
1(
#146
0%
1&
b1000 4
b1000 =
b1000 >
0#
1'
#150
0(
#155
b0 1
1(
#156
0'
#160
0(
#165
b1 1
1(
#166
1"
#170
0(
#175
b10 1
1(
#176
0"
1!
#180
0(
#185
b11 1
1(
#186
1%
0&
b100000000001000 4
b100000000001000 =
b100000000001000 >
0!
1#
#190
0(
#195
b100 1
1(
#196
0%
1&
b1000 4
b1000 =
b1000 >
0#
1'
#200
0(
#205
b0 1
1(
#206
0'
#210
0(
#215
b1 1
1(
#216
1"
#220
0(
#225
b10 1
1(
#226
0"
1!
#230
0(
#235
b11 1
1(
#236
1%
0&
b100000000001000 4
b100000000001000 =
b100000000001000 >
0!
1#
#240
0(
#245
b100 1
1(
#246
0%
1&
b1000 4
b1000 =
b1000 >
0#
1'
#250
0(
#255
b0 1
1(
#256
0'
#260
0(
#265
b1 1
1(
#266
1"
#270
0(
#275
b10 1
1(
#276
0"
1!
#280
0(
#285
b11 1
1(
#286
1%
0&
b100000000001000 4
b100000000001000 =
b100000000001000 >
0!
1#
#290
0(
#295
b100 1
1(
#296
0%
1&
b1000 4
b1000 =
b1000 >
0#
1'
#300
0(
#305
b0 1
1(
#306
0'
#310
0(
#315
b1 1
1(
#316
1"
#320
0(
#325
b10 1
1(
#326
0"
1!
#330
0(
#335
b11 1
1(
#336
1%
0&
b100000000001000 4
b100000000001000 =
b100000000001000 >
0!
1#
#340
0(
#345
b100 1
1(
#346
0%
1&
b1000 4
b1000 =
b1000 >
0#
1'
#350
0(
#355
b0 1
1(
#356
0'
#360
0(
#365
b1 1
1(
#366
1"
#370
0(
#375
b10 1
1(
#376
0"
1!
#380
0(
#385
b11 1
1(
#386
1%
0&
b100000000001000 4
b100000000001000 =
b100000000001000 >
0!
1#
#390
0(
#395
b100 1
1(
#396
0%
1&
b1000 4
b1000 =
b1000 >
0#
1'
#400
0(
#405
b0 1
1(
#406
0'
#410
0(
#415
b1 1
1(
#416
1"
#420
0(
#425
b10 1
1(
#426
0"
1!
#430
0(
#435
b11 1
1(
#436
1%
0&
b100000000001000 4
b100000000001000 =
b100000000001000 >
0!
1#
#440
0(
#445
b100 1
1(
#446
0%
1&
b1000 4
b1000 =
b1000 >
0#
1'
#450
0(
#455
b0 1
1(
#456
0'
#460
0(
#465
b1 1
1(
#466
1"
#470
0(
#475
b10 1
1(
#476
0"
1!
#480
0(
#485
b11 1
1(
#486
1%
0&
b100000000001000 4
b100000000001000 =
b100000000001000 >
0!
1#
#490
0(
#495
b100 1
1(
#496
0%
1&
b1000 4
b1000 =
b1000 >
0#
1'
