control_states.v
module control_states(sel1,sel2,sel3,sel4,mux2,clk,mux1,rst,Aout,Dout,
                            busreq_1,busreq_2,grant_1,grant_2,split,response,ready,read_write);

input clk,rst,busreq_1,busreq_2,split,ready,read_write;
input [1:0] response;
output reg sel1,sel2,mux1,sel3,sel4,mux2,Aout,Dout,grant_1,grant_2;

wire [1:0] REQ;
assign REQ[0] = busreq_1;
assign REQ[1] = busreq_2;

parameter M1 = 2'b01, M2 = 2'b10, MB = 2'b11;

reg [2:0] state;
parameter s0=3'b000, s1=3'b001, s2=3'b010, s3=3'b011, s4=3'b100;

always @(posedge clk)
    begin
        case (state)
            s0: if (~rst) begin
                    case (REQ)
                        M1: begin
                                if(ready==1 && split ==0 && response == 2'b00 && read_write == 1) //1 - write / 0 - read
                                    begin
                                        grant_1 = 1;
                                        grant_2 = 0;
                                        state <= s1;
                                    end

                                else if (ready==1 && split ==0 && response == 2'b00 && read_write == 0)
                                    begin
                                        grant_1 = 1;
                                        grant_2 = 0;
                                        state <= s2;
                                    end
                                else
                                    state <= s0;
                            end

                        M2: begin
                            if(ready==1 && split ==0 && response == 2'b00 && read_write == 1) //1 - write / 0 - read
                                    begin
                                        grant_1 = 0;
                                        grant_2 = 1;
                                        state <= s3;
                                    end

                                else if (ready==1 && split ==0 && response == 2'b00 && read_write == 0)
                                    begin
                                        grant_1 = 0;
                                        grant_2 = 1;
                                        state <= s4;
                                    end
                                else
                                    state <= s0;
                            end
                        MB: begin
                            if(ready==1 && split ==0 && response == 2'b00 && read_write == 1) //1 - write / 0 - read
                                    begin
                                        grant_1 = 1;
                                        grant_2 = 0;
                                        state <= s1;
                                    end

                                else if (ready==1 && split ==0 && response == 2'b00 && read_write == 0)
                                    begin
                                        grant_1 = 1;
                                        grant_2 = 0;
                                        state <= s2;
                                    end
                                else
                                    state <= s0;
                            end
                        default: state <= s0;
                       endcase
                    end

                    else state <= s0;
                

            s1: state <= s2; //slave 1 write state

            s2: state <= s3; //slave 1 read state
            s3: state <= s4; //slave 2 write state
            s4: state <= s0; //slave 2 read state
            default: state <= s0;
        endcase
    end

always @(state)
    begin
        case (state)
            s0: begin #10 sel1=0; sel2 = 0; mux1 = 0; Aout = 0; sel3=0; sel4 = 0; mux2 = 0; Dout = 0; end
            s1: begin #10 sel1=1; sel2 = 0;#2; mux1 = 0; Aout = 1; sel3=1; sel4 = 0;#2; mux2 = 0; Dout = 1; end //data write to slave1
            s2: begin #10 sel1=1; sel2 = 0;#2; mux1 = 0; Aout = 1; sel3=0; sel4 = 0; mux2 = 0; Dout = 0;  end //data read from slave 1
            s3: begin #10 mux1=1; sel2 = 1; sel1 = 0; Aout = 0; sel3=0; sel4 = 0; mux2 = 1; Dout = 1;  end//data write to slave2
            s4: begin #10 sel1 = 0; sel2 = 1; mux1=1; Aout = 0; sel3=0; sel4 = 0; mux2 = 0; Dout = 0;  end //data read from slave 1
            default: begin #10 sel1=0; sel2 = 0; mux1 = 0; Aout = 0; sel3=0; sel4 = 0; mux2 = 0; Dout = 0;  end
        
        endcase

    end

endmodule

MUXR.v
module MUXR(hrdata,hreadyout,hresponse, hrdata_1, hrdata_2,hrdata_3,hreadyout_1,hreadyout_2,hreadyout_3,
                hresp_1,hresp_2,hresp_3,sel);


input [31:0] hrdata_1;
input [31:0] hrdata_2;
input [31:0] hrdata_3;

input hreadyout_1;
input hreadyout_2;
input hreadyout_3;

input [1:0] hresp_1;
input [1:0] hresp_2;
input [1:0] hresp_3;

input [2:0] sel;

output reg [31:0] hrdata;
output reg hreadyout;
output reg [1:0] hresponse;


always @(*)
    case (sel)

        3'b000:
            begin

                hrdata = 32'b0;
                hreadyout = 0;
                hresponse = 2'b0;
                  
            end

        3'b001:
            begin

                hrdata = hrdata_1;
                hreadyout = hreadyout_1;
                hresponse = hresp_1;
                  
            end


        3'b010:
            begin

                hrdata = hrdata_2;
                hreadyout = hreadyout_2;
                hresponse = hresp_2;

            end

        3'b011:
            begin

                hrdata = hrdata_3;
                hreadyout = hreadyout_3;
                hresponse = hresp_3;

            end

       default:
            begin

                hrdata = 32'bz;
                hreadyout = hreadyout;
                hresponse = 2'bz;

            end


    endcase


endmodule

BUFFER.v
module BUFFER(out, in);
input in;
output out;

assign out = in;
endmodule

decoder.v
module decoder( hsel_0, hsel_1, hsel_2, haddr,rst);

 input [15:0] haddr;  // Input address from the Address mux
 input rst;
 output reg hsel_0; // hSelect  slave0
 output reg hsel_1; //hSelect  slave1 
 output reg hsel_2; //hSelect  slave2 
 
  
 always @(*)
  if(rst)
    begin
        hsel_0 = 1'b0;
        hsel_1 = 1'b0;
        hsel_2 = 1'b0;
    end
  else
    begin
    case (haddr[15:13])
        3'b001:
            begin
              hsel_0 = 1'b1;
              hsel_1 = 1'b0;
              hsel_2 = 1'b0;
            end

        3'b010:
            begin
              hsel_0 = 1'b0;
              hsel_1 = 1'b1;
              hsel_2 = 1'b0;
            end

        3'b011:
            begin
              hsel_0 = 1'b0;
              hsel_1 = 1'b0;
              hsel_2 = 1'b1;
            end
        default:
            begin
              hsel_0 = 1'b0;
              hsel_1 = 1'b0;
              hsel_2 = 1'b0;
            end

    endcase
    end


endmodule

TRI_BUFF_D.v
module TRI_BUFF_D(out, en, in);
input en;
input [31:0] in;
output [31:0] out;

assign out = en ? in : 32'b0;
endmodule

TRI_BUFF.v
module TRI_BUFF(out, en, in);
input en;
input [15:0] in;
output [15:0] out;

assign out = en ? in : 16'b0;
endmodule

MUXD.v
module MUXD(out, in0, in1, sel);

input sel;
input [31:0]in0, in1;
output [31:0]out;

assign out = sel ? in1 : in0;

endmodule

PIPOD.v
module PIPOD(dout,din,ld,clk);
    input [31:0] din;
    input ld,clk;
    output reg [31:0] dout;

    always @(posedge clk)
        if (ld) 
            dout <= din;

endmodule

MUX.v
module MUX(out, in0, in1, sel);

input sel;
input [15:0]in0, in1;
output [15:0]out;

assign out = sel ? in1 : in0;

endmodule

PIPO.v
module PIPO(dout,din,ld,clk);
    input [15:0] din;
    input ld,clk;
    output reg [15:0] dout;

    always @(posedge clk)
        begin
            if (ld) 
                dout <= din;
            else
                dout <= 16'bz; 
        end
endmodule

data_path.v
module data_path(slave_0,slave_1,slave_2,address,Aout,sel1,sel2,mux1,rst,data_in1,data_in2,clk,
                                sel3,sel4,mux2,data_in3,data_in4,
                                rdin1,rdin2,rdin3,resp1,resp2,resp3,rdy1,rdy2,rdy3,dout,rdyout,respout,
                                dataout, Dout);

    input sel1,sel2,mux1,sel3,sel4,mux2,clk,rst,Aout,Dout;
    input [15:0] data_in1, data_in2;
    input [31:0] data_in3,data_in4;

    //read data mux
    input [31:0] rdin1,rdin2,rdin3;
    input [1:0] resp1,resp2,resp3;
    input rdy1,rdy2,rdy3;

    output [31:0] dout;
    output rdyout;
    output [1:0] respout;

//.......................
    output [15:0] address;
    output [31:0] dataout;
//.........................


    wire hsel_0,hsel_1,hsel_2;

    wire [15:0] x,y,z; //for address values passing
    wire [31:0] p,q,r; // for data values

    output slave_0,slave_1,slave_2; //buffer outputs

//making control inputs for the data out register

    wire [2:0] seld;
    assign seld[0] = hsel_0;
    assign seld[1] = hsel_1;
    assign seld[2] = hsel_2;


   
 //address muxes   
    PIPO HADDR1 (x,data_in1,sel1,clk);
    PIPO HADDR2 (y,data_in2,sel2,clk);
    MUX addressmux (z,x,y,mux1);

//data muxes
    PIPOD HWDATA1 (p,data_in3,sel3,clk);
    PIPOD HWDATA2 (q,data_in4,sel4,clk);
    MUXD datamux (r,p,q,mux2);

   
    TRI_BUFF add_buff(address,Aout,z); // pssing address from the master
    TRI_BUFF_D data_buff(dataout,Dout,r); //passing data from the master

    decoder dec1 (hsel_0,hsel_1,hsel_2,z,rst);

    BUFFER out1(slave_0,hsel_0);
    BUFFER out2(slave_1,hsel_1);
    BUFFER out3(slave_2,hsel_2);

// read data mux

    MUXR readMUX(dout,rdyout,respout,rdin1,rdin2,rdin3,rdy1,rdy2,rdy3,resp1,resp2,resp3,seld);





    
endmodule

test1_tb.v
`timescale 1ns/1ns
`include "control_states.v"
`include "data_path.v"
`include "MUX.v"
`include "PIPO.v"
`include "decoder.v"
`include "BUFFER.v"
`include "PIPOD.v"
`include "MUXD.v"
`include "MUXR.v"
`include "TRI_BUFF.v"
`include "TRI_BUFF_D.v"


module test1_tb;

reg [15:0] data_in1,data_in2;
reg [31:0] data_in3,data_in4;

reg clk,rst;
wire [15:0] address; //for address out

//for data put register from slaves
reg [31:0] rdin1,rdin2,rdin3;
reg [1:0] resp1,resp2,resp3;
reg rdy1,rdy2,rdy3;

//output data from slaves
wire [31:0] dout;
wire [1:0] respout;

//output data from master to slave
wire [31:0] dataout;

//for the arbiter part

reg [1:0] response;
reg split,ready,busreq_1,busreq_2,read_write;
   // reg ready,grant_1,grant_2;

                
//data_path dpt1 (hsel_0,hsel_1,hsel_2,address,Aout,sel1,sel2,mux1,rst,data_in1,data_in2,clk);

data_path dpt(slave_0,slave_1,slave_2,address,Aout,sel1,sel2,mux1,rst,data_in1,data_in2,clk,
                                sel3,sel4,mux2,data_in3,data_in4,
                                rdin1,rdin2,rdin3,resp1,resp2,resp3,rdy1,rdy2,rdy3,dout,rdyout,respout,
                                dataout, Dout);
                                
                               

control_states cpt1(sel1,sel2,sel3,sel4,mux2,clk,mux1,rst,Aout,Dout,
                            busreq_1,busreq_2,grant_1,grant_2,split,response,ready,read_write);

initial
    begin
        clk = 1'b0;
        #1000 $finish;
    end

always #5 clk = ~clk;

initial
    begin
   
        rst = 1'b1; #1;

        data_in1 = 16'b0010000000001000; #1;
        data_in2 = 16'b0100000000001000; #1;

        data_in3 = 567; #1;
        data_in4 = 434; #1;

        rdin1 = 50;#1;
        rdin2 = 0;#1;
        rdin3 = 0;#1;

        resp1 = 2'b01;#1;
        resp2 = 2'b11;#1;
        resp1 = 2'b10;#1;

        rdy1 = 1;#1;
        rdy2 = 0;#1;
        rdy3 = 1;#1;

        //for arbiter read_write: 1 - write / 0 - read

        //writing to slave1 by the master1 from idle state
     /*   busreq_1 = 1;#1;
        busreq_2 = 0;#1;
        ready = 1;#1;
        split = 0;#1;
        response = 2'b00;#1;
        read_write = 1; */

      //reading from slave1 by the master1 from idle state
    /*    busreq_1 = 1;#1;
        busreq_2 = 0;#1;
        ready = 1;#1;
        split = 0;#1;
        response = 2'b00;#1;
        read_write = 0; */

    //reading from slave1 by the master 2 from idle state
     /*   busreq_1 = 0;#1;
        busreq_2 = 1;#1;
        ready = 1;#1;
        split = 0;#1;
        response = 2'b00;#1;
        read_write = 0;*/

    //both masters are requesting the buss address from idle state. Master1 was assigned highest priority
        busreq_1 = 1;#1;
        busreq_2 = 1;#1;
        ready = 1;#1;
        split = 0;#1;
        response = 2'b00;#1;
        read_write = 0;

        

       // data_in1 = 16'b0110000000001000; #1;

        rst = 1'b0; #500;

        rst = 1'b1;

       // #200;
        //rst = 1'b1;
        //data_in2 = 16'b1000000000001000; #50;
        //data_in1 = 16'b0000000000001000; #1;

       
    end

initial
    begin
    
        $dumpfile("test1_tb.vcd");
        $dumpvars(0,test1_tb);
        $display("End of test!!!");

    end

endmodule

test1_tb.vcd
$date
	Sun Dec 24 22:56:39 2023
$end
$version
	Icarus Verilog
$end
$timescale
	1ns
$end
$scope module test1_tb $end
$var wire 1 ! slave_2 $end
$var wire 1 " slave_1 $end
$var wire 1 # slave_0 $end
$var wire 1 $ sel4 $end
$var wire 1 % sel3 $end
$var wire 1 & sel2 $end
$var wire 1 ' sel1 $end
$var wire 2 ( respout [1:0] $end
$var wire 1 ) rdyout $end
$var wire 1 * mux2 $end
$var wire 1 + mux1 $end
$var wire 1 , grant_2 $end
$var wire 1 - grant_1 $end
$var wire 32 . dout [31:0] $end
$var wire 32 / dataout [31:0] $end
$var wire 16 0 address [15:0] $end
$var wire 1 1 Dout $end
$var wire 1 2 Aout $end
$var reg 1 3 busreq_1 $end
$var reg 1 4 busreq_2 $end
$var reg 1 5 clk $end
$var reg 16 6 data_in1 [15:0] $end
$var reg 16 7 data_in2 [15:0] $end
$var reg 32 8 data_in3 [31:0] $end
$var reg 32 9 data_in4 [31:0] $end
$var reg 32 : rdin1 [31:0] $end
$var reg 32 ; rdin2 [31:0] $end
$var reg 32 < rdin3 [31:0] $end
$var reg 1 = rdy1 $end
$var reg 1 > rdy2 $end
$var reg 1 ? rdy3 $end
$var reg 1 @ read_write $end
$var reg 1 A ready $end
$var reg 2 B resp1 [1:0] $end
$var reg 2 C resp2 [1:0] $end
$var reg 2 D resp3 [1:0] $end
$var reg 2 E response [1:0] $end
$var reg 1 F rst $end
$var reg 1 G split $end
$scope module cpt1 $end
$var wire 1 3 busreq_1 $end
$var wire 1 4 busreq_2 $end
$var wire 1 5 clk $end
$var wire 1 @ read_write $end
$var wire 1 A ready $end
$var wire 2 H response [1:0] $end
$var wire 1 F rst $end
$var wire 1 G split $end
$var wire 2 I REQ [1:0] $end
$var parameter 2 J M1 $end
$var parameter 2 K M2 $end
$var parameter 2 L MB $end
$var parameter 3 M s0 $end
$var parameter 3 N s1 $end
$var parameter 3 O s2 $end
$var parameter 3 P s3 $end
$var parameter 3 Q s4 $end
$var reg 1 2 Aout $end
$var reg 1 1 Dout $end
$var reg 1 - grant_1 $end
$var reg 1 , grant_2 $end
$var reg 1 + mux1 $end
$var reg 1 * mux2 $end
$var reg 1 ' sel1 $end
$var reg 1 & sel2 $end
$var reg 1 % sel3 $end
$var reg 1 $ sel4 $end
$var reg 3 R state [2:0] $end
$upscope $end
$scope module dpt $end
$var wire 1 2 Aout $end
$var wire 1 1 Dout $end
$var wire 1 5 clk $end
$var wire 16 S data_in1 [15:0] $end
$var wire 16 T data_in2 [15:0] $end
$var wire 32 U data_in3 [31:0] $end
$var wire 32 V data_in4 [31:0] $end
$var wire 1 + mux1 $end
$var wire 1 * mux2 $end
$var wire 32 W rdin1 [31:0] $end
$var wire 32 X rdin2 [31:0] $end
$var wire 32 Y rdin3 [31:0] $end
$var wire 1 = rdy1 $end
$var wire 1 > rdy2 $end
$var wire 1 ? rdy3 $end
$var wire 2 Z resp1 [1:0] $end
$var wire 2 [ resp2 [1:0] $end
$var wire 2 \ resp3 [1:0] $end
$var wire 1 F rst $end
$var wire 1 ' sel1 $end
$var wire 1 & sel2 $end
$var wire 1 % sel3 $end
$var wire 1 $ sel4 $end
$var wire 16 ] z [15:0] $end
$var wire 16 ^ y [15:0] $end
$var wire 16 _ x [15:0] $end
$var wire 1 ! slave_2 $end
$var wire 1 " slave_1 $end
$var wire 1 # slave_0 $end
$var wire 3 ` seld [2:0] $end
$var wire 2 a respout [1:0] $end
$var wire 1 ) rdyout $end
$var wire 32 b r [31:0] $end
$var wire 32 c q [31:0] $end
$var wire 32 d p [31:0] $end
$var wire 1 e hsel_2 $end
$var wire 1 f hsel_1 $end
$var wire 1 g hsel_0 $end
$var wire 32 h dout [31:0] $end
$var wire 32 i dataout [31:0] $end
$var wire 16 j address [15:0] $end
$scope module HADDR1 $end
$var wire 1 5 clk $end
$var wire 16 k din [15:0] $end
$var wire 1 ' ld $end
$var reg 16 l dout [15:0] $end
$upscope $end
$scope module HADDR2 $end
$var wire 1 5 clk $end
$var wire 16 m din [15:0] $end
$var wire 1 & ld $end
$var reg 16 n dout [15:0] $end
$upscope $end
$scope module HWDATA1 $end
$var wire 1 5 clk $end
$var wire 32 o din [31:0] $end
$var wire 1 % ld $end
$var reg 32 p dout [31:0] $end
$upscope $end
$scope module HWDATA2 $end
$var wire 1 5 clk $end
$var wire 32 q din [31:0] $end
$var wire 1 $ ld $end
$var reg 32 r dout [31:0] $end
$upscope $end
$scope module add_buff $end
$var wire 1 2 en $end
$var wire 16 s out [15:0] $end
$var wire 16 t in [15:0] $end
$upscope $end
$scope module addressmux $end
$var wire 16 u in0 [15:0] $end
$var wire 16 v in1 [15:0] $end
$var wire 1 + sel $end
$var wire 16 w out [15:0] $end
$upscope $end
$scope module data_buff $end
$var wire 1 1 en $end
$var wire 32 x out [31:0] $end
$var wire 32 y in [31:0] $end
$upscope $end
$scope module datamux $end
$var wire 32 z in0 [31:0] $end
$var wire 32 { in1 [31:0] $end
$var wire 1 * sel $end
$var wire 32 | out [31:0] $end
$upscope $end
$scope module dec1 $end
$var wire 16 } haddr [15:0] $end
$var wire 1 F rst $end
$var reg 1 g hsel_0 $end
$var reg 1 f hsel_1 $end
$var reg 1 e hsel_2 $end
$upscope $end
$scope module out1 $end
$var wire 1 g in $end
$var wire 1 # out $end
$upscope $end
$scope module out2 $end
$var wire 1 f in $end
$var wire 1 " out $end
$upscope $end
$scope module out3 $end
$var wire 1 e in $end
$var wire 1 ! out $end
$upscope $end
$scope module readMUX $end
$var wire 32 ~ hrdata_1 [31:0] $end
$var wire 32 !" hrdata_2 [31:0] $end
$var wire 32 "" hrdata_3 [31:0] $end
$var wire 1 = hreadyout_1 $end
$var wire 1 > hreadyout_2 $end
$var wire 1 ? hreadyout_3 $end
$var wire 2 #" hresp_1 [1:0] $end
$var wire 2 $" hresp_2 [1:0] $end
$var wire 2 %" hresp_3 [1:0] $end
$var wire 3 &" sel [2:0] $end
$var reg 32 '" hrdata [31:0] $end
$var reg 1 ) hreadyout $end
$var reg 2 (" hresponse [1:0] $end
$upscope $end
$upscope $end
$upscope $end
$enddefinitions $end
$comment Show the parameter values. $end
$dumpall
b100 Q
b11 P
b10 O
b1 N
b0 M
b11 L
b10 K
b1 J
$end
#0
$dumpvars
bz ("
bz '"
b0 &"
bx %"
bx $"
bx #"
bx ""
bx !"
bx ~
bx }
bx |
bx {
bx z
bx y
bx x
bx w
bx v
bx u
bx t
bx s
bx r
bx q
bx p
bx o
bx n
bx m
bx l
bx k
bx j
bx i
bz h
0g
0f
0e
bx d
bx c
bx b
bz a
b0 `
bx _
bx ^
bx ]
bx \
bx [
bx Z
bx Y
bx X
bx W
bx V
bx U
bx T
bx S
bx R
bx I
bx H
xG
1F
bx E
bx D
bx C
bx B
xA
x@
x?
x>
x=
bx <
bx ;
bx :
bx 9
bx 8
bx 7
bx 6
05
x4
x3
x2
x1
bx 0
bx /
bz .
x-
x,
x+
x*
x)
bz (
x'
x&
x%
x$
0#
0"
0!
$end
#1
b10000000001000 6
b10000000001000 S
b10000000001000 k
#2
b100000000001000 7
b100000000001000 T
b100000000001000 m
#3
b1000110111 8
b1000110111 U
b1000110111 o
#4
b110110010 9
b110110010 V
b110110010 q
#5
bz ]
bz t
bz w
bz }
bz b
bz y
bz |
bz _
bz l
bz u
bz ^
bz n
bz v
bz d
bz p
bz z
bz c
bz r
bz {
b0 R
b110010 :
b110010 W
b110010 ~
15
#6
b0 ;
b0 X
b0 !"
#7
b0 <
b0 Y
b0 ""
#8
b1 B
b1 Z
b1 #"
#9
b11 C
b11 [
b11 $"
#10
b10 B
b10 Z
b10 #"
05
#11
1=
#12
0>
#13
1?
#14
bx1 I
13
#15
b0 /
b0 i
b0 x
b0 0
b0 j
b0 s
b11 I
14
15
01
0*
0$
0%
02
0+
0&
0'
#16
1A
#17
0G
#18
b0 E
b0 H
#19
0F
0@
#20
05
#25
b10 R
0,
1-
15
#30
05
#35
b10 (
b10 a
b10 ("
1)
b110010 .
b110010 h
b110010 '"
1#
b1 `
b1 &"
1g
b10000000001000 ]
b10000000001000 t
b10000000001000 w
b10000000001000 }
b11 R
b10000000001000 _
b10000000001000 l
b10000000001000 u
15
1'
#37
b10000000001000 0
b10000000001000 j
b10000000001000 s
12
#40
05
#45
b100 R
15
#50
05
#55
0)
1"
1f
b0 R
b100000000001000 ^
b100000000001000 n
b100000000001000 v
bz _
bz l
bz u
b11 (
b11 a
b11 ("
b0 .
b0 h
b0 '"
0#
b10 `
b10 &"
0g
b0 0
b0 j
b0 s
b100000000001000 ]
b100000000001000 t
b100000000001000 w
b100000000001000 }
15
02
1+
1&
0'
#60
05
#65
bz ^
bz n
bz v
b10 R
bz (
bz a
bz ("
bz .
bz h
bz '"
0"
b0 `
b0 &"
0f
bz ]
bz t
bz w
bz }
15
0+
0&
#70
05
#75
b10 (
b10 a
b10 ("
1)
b110010 .
b110010 h
b110010 '"
1#
b1 `
b1 &"
1g
b10000000001000 ]
b10000000001000 t
b10000000001000 w
b10000000001000 }
b11 R
b10000000001000 _
b10000000001000 l
b10000000001000 u
15
1'
#77
b10000000001000 0
b10000000001000 j
b10000000001000 s
12
#80
05
#85
b100 R
15
#90
05
#95
0)
1"
1f
b0 R
b100000000001000 ^
b100000000001000 n
b100000000001000 v
bz _
bz l
bz u
b11 (
b11 a
b11 ("
b0 .
b0 h
b0 '"
0#
b10 `
b10 &"
0g
b0 0
b0 j
b0 s
b100000000001000 ]
b100000000001000 t
b100000000001000 w
b100000000001000 }
15
02
1+
1&
0'
#100
05
#105
bz ^
bz n
bz v
b10 R
bz (
bz a
bz ("
bz .
bz h
bz '"
0"
b0 `
b0 &"
0f
bz ]
bz t
bz w
bz }
15
0+
0&
#110
05
#115
b10 (
b10 a
b10 ("
1)
b110010 .
b110010 h
b110010 '"
1#
b1 `
b1 &"
1g
b10000000001000 ]
b10000000001000 t
b10000000001000 w
b10000000001000 }
b11 R
b10000000001000 _
b10000000001000 l
b10000000001000 u
15
1'
#117
b10000000001000 0
b10000000001000 j
b10000000001000 s
12
#120
05
#125
b100 R
15
#130
05
#135
0)
1"
1f
b0 R
b100000000001000 ^
b100000000001000 n
b100000000001000 v
bz _
bz l
bz u
b11 (
b11 a
b11 ("
b0 .
b0 h
b0 '"
0#
b10 `
b10 &"
0g
b0 0
b0 j
b0 s
b100000000001000 ]
b100000000001000 t
b100000000001000 w
b100000000001000 }
15
02
1+
1&
0'
#140
05
#145
bz ^
bz n
bz v
b10 R
bz (
bz a
bz ("
bz .
bz h
bz '"
0"
b0 `
b0 &"
0f
bz ]
bz t
bz w
bz }
15
0+
0&
#150
05
#155
b10 (
b10 a
b10 ("
1)
b110010 .
b110010 h
b110010 '"
1#
b1 `
b1 &"
1g
b10000000001000 ]
b10000000001000 t
b10000000001000 w
b10000000001000 }
b11 R
b10000000001000 _
b10000000001000 l
b10000000001000 u
15
1'
#157
b10000000001000 0
b10000000001000 j
b10000000001000 s
12
#160
05
#165
b100 R
15
#170
05
#175
0)
1"
1f
b0 R
b100000000001000 ^
b100000000001000 n
b100000000001000 v
bz _
bz l
bz u
b11 (
b11 a
b11 ("
b0 .
b0 h
b0 '"
0#
b10 `
b10 &"
0g
b0 0
b0 j
b0 s
b100000000001000 ]
b100000000001000 t
b100000000001000 w
b100000000001000 }
15
02
1+
1&
0'
#180
05
#185
bz ^
bz n
bz v
b10 R
bz (
bz a
bz ("
bz .
bz h
bz '"
0"
b0 `
b0 &"
0f
bz ]
bz t
bz w
bz }
15
0+
0&
#190
05
#195
b10 (
b10 a
b10 ("
1)
b110010 .
b110010 h
b110010 '"
1#
b1 `
b1 &"
1g
b10000000001000 ]
b10000000001000 t
b10000000001000 w
b10000000001000 }
b11 R
b10000000001000 _
b10000000001000 l
b10000000001000 u
15
1'
#197
b10000000001000 0
b10000000001000 j
b10000000001000 s
12
#200
05
#205
b100 R
15
#210
05
#215
0)
1"
1f
b0 R
b100000000001000 ^
b100000000001000 n
b100000000001000 v
bz _
bz l
bz u
b11 (
b11 a
b11 ("
b0 .
b0 h
b0 '"
0#
b10 `
b10 &"
0g
b0 0
b0 j
b0 s
b100000000001000 ]
b100000000001000 t
b100000000001000 w
b100000000001000 }
15
02
1+
1&
0'
#220
05
#225
bz ^
bz n
bz v
b10 R
bz (
bz a
bz ("
bz .
bz h
bz '"
0"
b0 `
b0 &"
0f
bz ]
bz t
bz w
bz }
15
0+
0&
#230
05
#235
b10 (
b10 a
b10 ("
1)
b110010 .
b110010 h
b110010 '"
1#
b1 `
b1 &"
1g
b10000000001000 ]
b10000000001000 t
b10000000001000 w
b10000000001000 }
b11 R
b10000000001000 _
b10000000001000 l
b10000000001000 u
15
1'
#237
b10000000001000 0
b10000000001000 j
b10000000001000 s
12
#240
05
#245
b100 R
15
#250
05
#255
0)
1"
1f
b0 R
b100000000001000 ^
b100000000001000 n
b100000000001000 v
bz _
bz l
bz u
b11 (
b11 a
b11 ("
b0 .
b0 h
b0 '"
0#
b10 `
b10 &"
0g
b0 0
b0 j
b0 s
b100000000001000 ]
b100000000001000 t
b100000000001000 w
b100000000001000 }
15
02
1+
1&
0'
#260
05
#265
bz ^
bz n
bz v
b10 R
bz (
bz a
bz ("
bz .
bz h
bz '"
0"
b0 `
b0 &"
0f
bz ]
bz t
bz w
bz }
15
0+
0&
#270
05
#275
b10 (
b10 a
b10 ("
1)
b110010 .
b110010 h
b110010 '"
1#
b1 `
b1 &"
1g
b10000000001000 ]
b10000000001000 t
b10000000001000 w
b10000000001000 }
b11 R
b10000000001000 _
b10000000001000 l
b10000000001000 u
15
1'
#277
b10000000001000 0
b10000000001000 j
b10000000001000 s
12
#280
05
#285
b100 R
15
#290
05
#295
0)
1"
1f
b0 R
b100000000001000 ^
b100000000001000 n
b100000000001000 v
bz _
bz l
bz u
b11 (
b11 a
b11 ("
b0 .
b0 h
b0 '"
0#
b10 `
b10 &"
0g
b0 0
b0 j
b0 s
b100000000001000 ]
b100000000001000 t
b100000000001000 w
b100000000001000 }
15
02
1+
1&
0'
#300
05
#305
bz ^
bz n
bz v
b10 R
bz (
bz a
bz ("
bz .
bz h
bz '"
0"
b0 `
b0 &"
0f
bz ]
bz t
bz w
bz }
15
0+
0&
#310
05
#315
b10 (
b10 a
b10 ("
1)
b110010 .
b110010 h
b110010 '"
1#
b1 `
b1 &"
1g
b10000000001000 ]
b10000000001000 t
b10000000001000 w
b10000000001000 }
b11 R
b10000000001000 _
b10000000001000 l
b10000000001000 u
15
1'
#317
b10000000001000 0
b10000000001000 j
b10000000001000 s
12
#320
05
#325
b100 R
15
#330
05
#335
0)
1"
1f
b0 R
b100000000001000 ^
b100000000001000 n
b100000000001000 v
bz _
bz l
bz u
b11 (
b11 a
b11 ("
b0 .
b0 h
b0 '"
0#
b10 `
b10 &"
0g
b0 0
b0 j
b0 s
b100000000001000 ]
b100000000001000 t
b100000000001000 w
b100000000001000 }
15
02
1+
1&
0'
#340
05
#345
bz ^
bz n
bz v
b10 R
bz (
bz a
bz ("
bz .
bz h
bz '"
0"
b0 `
b0 &"
0f
bz ]
bz t
bz w
bz }
15
0+
0&
#350
05
#355
b10 (
b10 a
b10 ("
1)
b110010 .
b110010 h
b110010 '"
1#
b1 `
b1 &"
1g
b10000000001000 ]
b10000000001000 t
b10000000001000 w
b10000000001000 }
b11 R
b10000000001000 _
b10000000001000 l
b10000000001000 u
15
1'
#357
b10000000001000 0
b10000000001000 j
b10000000001000 s
12
#360
05
#365
b100 R
15
#370
05
#375
0)
1"
1f
b0 R
b100000000001000 ^
b100000000001000 n
b100000000001000 v
bz _
bz l
bz u
b11 (
b11 a
b11 ("
b0 .
b0 h
b0 '"
0#
b10 `
b10 &"
0g
b0 0
b0 j
b0 s
b100000000001000 ]
b100000000001000 t
b100000000001000 w
b100000000001000 }
15
02
1+
1&
0'
#380
05
#385
bz ^
bz n
bz v
b10 R
bz (
bz a
bz ("
bz .
bz h
bz '"
0"
b0 `
b0 &"
0f
bz ]
bz t
bz w
bz }
15
0+
0&
#390
05
#395
b10 (
b10 a
b10 ("
1)
b110010 .
b110010 h
b110010 '"
1#
b1 `
b1 &"
1g
b10000000001000 ]
b10000000001000 t
b10000000001000 w
b10000000001000 }
b11 R
b10000000001000 _
b10000000001000 l
b10000000001000 u
15
1'
#397
b10000000001000 0
b10000000001000 j
b10000000001000 s
12
#400
05
#405
b100 R
15
#410
05
#415
0)
1"
1f
b0 R
b100000000001000 ^
b100000000001000 n
b100000000001000 v
bz _
bz l
bz u
b11 (
b11 a
b11 ("
b0 .
b0 h
b0 '"
0#
b10 `
b10 &"
0g
b0 0
b0 j
b0 s
b100000000001000 ]
b100000000001000 t
b100000000001000 w
b100000000001000 }
15
02
1+
1&
0'
#420
05
#425
bz ^
bz n
bz v
b10 R
bz (
bz a
bz ("
bz .
bz h
bz '"
0"
b0 `
b0 &"
0f
bz ]
bz t
bz w
bz }
15
0+
0&
#430
05
#435
b10 (
b10 a
b10 ("
1)
b110010 .
b110010 h
b110010 '"
1#
b1 `
b1 &"
1g
b10000000001000 ]
b10000000001000 t
b10000000001000 w
b10000000001000 }
b11 R
b10000000001000 _
b10000000001000 l
b10000000001000 u
15
1'
#437
b10000000001000 0
b10000000001000 j
b10000000001000 s
12
#440
05
#445
b100 R
15
#450
05
#455
0)
1"
1f
b0 R
b100000000001000 ^
b100000000001000 n
b100000000001000 v
bz _
bz l
bz u
b11 (
b11 a
b11 ("
b0 .
b0 h
b0 '"
0#
b10 `
b10 &"
0g
b0 0
b0 j
b0 s
b100000000001000 ]
b100000000001000 t
b100000000001000 w
b100000000001000 }
15
02
1+
1&
0'
#460
05
#465
bz ^
bz n
bz v
b10 R
bz (
bz a
bz ("
bz .
bz h
bz '"
0"
b0 `
b0 &"
0f
bz ]
bz t
bz w
bz }
15
0+
0&
#470
05
#475
b10 (
b10 a
b10 ("
1)
b110010 .
b110010 h
b110010 '"
1#
b1 `
b1 &"
1g
b10000000001000 ]
b10000000001000 t
b10000000001000 w
b10000000001000 }
b11 R
b10000000001000 _
b10000000001000 l
b10000000001000 u
15
1'
#477
b10000000001000 0
b10000000001000 j
b10000000001000 s
12
#480
05
#485
b100 R
15
#490
05
#495
0)
1"
1f
b0 R
b100000000001000 ^
b100000000001000 n
b100000000001000 v
bz _
bz l
bz u
b11 (
b11 a
b11 ("
b0 .
b0 h
b0 '"
0#
b10 `
b10 &"
0g
b0 0
b0 j
b0 s
b100000000001000 ]
b100000000001000 t
b100000000001000 w
b100000000001000 }
15
02
1+
1&
0'
#500
05
