control_states.v
module control_states(sel1,sel2,sel3,sel4,mux2,clk,mux1,rst,Aout,Dout,
                            busreq_1,busreq_2,grant_1,grant_2,split,response,ready,read_write,error);

input clk,rst,busreq_1,busreq_2,split,ready,read_write;
input [1:0] response;
output reg sel1,sel2,mux1,sel3,sel4,mux2,Aout,Dout,grant_1,grant_2,error;



wire [1:0] REQ;
assign REQ[0] = busreq_1;
assign REQ[1] = busreq_2;

parameter M1 = 2'b01, M2 = 2'b10, MB = 2'b11;

reg [2:0] state;
parameter s0=3'b000, s1=3'b001, s2=3'b010, s3=3'b011, s4=3'b100;

always @(posedge clk)
     begin
        case (state)
            s0: if (~rst) begin
                    case (REQ)
                        M1: begin
                                if(ready==1 && split ==0 && response == 2'b00 && read_write == 1) //1 - write / 0 - read
                                    begin
                                        grant_1 = 1;
                                        grant_2 = 0;
                                        state <= s1;
                                    end

                                else if (ready==1 && split ==0 && response == 2'b00 && read_write == 0)
                                    begin
                                        grant_1 = 1;
                                        grant_2 = 0;
                                        state <= s2;
                                    end
                                else
                                    state <= s0;
                            end

                        M2: begin
                            if(ready==1 && split ==0 && response == 2'b00 && read_write == 1) //1 - write / 0 - read
                                    begin
                                        grant_1 = 0;
                                        grant_2 = 1;
                                        state <= s3;
                                    end

                                else if (ready==1 && split ==0 && response == 2'b00 && read_write == 0)
                                    begin
                                        grant_1 = 0;
                                        grant_2 = 1;
                                        state <= s4;
                                    end
                                else
                                    state <= s0;
                            end
                        MB: begin
                            if(ready==1 && split ==0 && response == 2'b00 && read_write == 1) //1 - write / 0 - read
                                    begin
                                        grant_1 = 1;
                                        grant_2 = 0;
                                        state <= s1;
                                    end

                                else if (ready==1 && split ==0 && response == 2'b00 && read_write == 0)
                                    begin
                                        grant_1 = 1;
                                        grant_2 = 0;
                                        state <= s2;
                                    end
                                else
                                    state <= s0;
                            end
                        default: state <= s0;
                       endcase
                    end

                        else begin
                    grant_1 = 0;
                    grant_2 = 0;
                    end       

            s1: if (~rst) 
                    begin
                        case(response)
                            00: 
                                if(ready)
                                    begin
                                        state <= s0;
                                    end
                            01: 
                                begin
                                    error = 1;
                                    state <= s0;
                                end

                            10: 
                                state <= s1;

                            11:
                                state <= s1;
                            
                            default: state <= s0;
                        endcase
                    end
                
               else begin
                    grant_1 = 0;
                    grant_2 = 0;
                    end
           // s1: state <= s2; //slave 1 write state

            s2:  //slave 1 read state
                if (~rst) begin
                    case(response)
                        00: 
                            if(ready)
                                begin
                                    state <= s0;
                                end
                        01: 
                            begin
                                error = 1;
                                state <= s0;
                            end

                        10: 
                            state <= s2;

                        11:
                            state <= s2;
                          
                        default: state <= s0;
                    endcase
                end
                else begin
                    grant_1 = 0;
                    grant_2 = 0;
                    end
                
            s3: //slave 2 write state
                if (~rst) 
                    begin
                        case(response)
                            00: 
                                if(ready)
                                    begin
                                        state <= s0;
                                    end
                            01: 
                                begin
                                    error = 1;
                                    state <= s0;
                                end

                            10: 
                                state <= s3;

                            11:
                                state <= s3;
                            
                            default: state <= s0;
                        endcase
                end
                
               else begin
                    grant_1 = 0;
                    grant_2 = 0;
                    end


            s4:  //slave 2 read state
                        if (~rst) begin
                            case(response)
                                00: 
                                    if(ready)
                                        begin
                                            state <= s0;
                                        end
                                01: 
                                    begin
                                        error = 1;
                                        state <= s0;
                                    end

                                10: 
                                    state <= s4;

                                11:
                                    state <= s4;
                                
                                default: state <= s0;
                            endcase
                        end
                        
                     else begin
                    grant_1 = 0;
                    grant_2 = 0;
                    end   

                    default: state <= s0;
                endcase
            end

always @(state)
    begin
        case (state)
            s0: begin  sel1=0; sel2 = 0; mux1 = 0; Aout = 0; sel3=0; sel4 = 0; mux2 = 0; Dout = 0;grant_1=0;grant_2=0;error =0; #20; end
            s1: begin  sel1=1; sel2 = 0; mux1 = 0; Aout = 1; sel3=1; sel4 = 0; mux2 = 0; Dout = 1; #20; end //data write to slave1
            s2: begin  sel1=1; sel2 = 0; mux1 = 0; Aout = 1; sel3=0; sel4 = 0; mux2 = 0; Dout = 0; #20;  end //data read from slave 1
            s3: begin  mux1=1; sel2 = 1; sel1 = 0; Aout = 0; sel3=0; sel4 = 0; mux2 = 1; Dout = 1; #20;  end//data write to slave2
            s4: begin  sel1 = 0; sel2 = 1; mux1=1; Aout = 0; sel3=0; sel4 = 0; mux2 = 0; Dout = 0; #20;  end //data read from slave 1
            default: begin sel1=0; sel2 = 0; mux1 = 0; Aout = 0; sel3=0; sel4 = 0; mux2 = 0; Dout = 0;grant_1=0;grant_2=0;error =0; #20;end
        
        endcase

    end

endmodule

MUXR.v
module MUXR(hrdata,hreadyout,hresponse, hrdata_1, hrdata_2,hrdata_3,hreadyout_1,hreadyout_2,hreadyout_3,
                hresp_1,hresp_2,hresp_3,sel);


input [31:0] hrdata_1;
input [31:0] hrdata_2;
input [31:0] hrdata_3;

input hreadyout_1;
input hreadyout_2;
input hreadyout_3;

input [1:0] hresp_1;
input [1:0] hresp_2;
input [1:0] hresp_3;

input [2:0] sel;

output reg [31:0] hrdata;
output reg hreadyout;
output reg [1:0] hresponse;


always @(*)
    case (sel)

        3'b000:
            begin

                hrdata = 32'b0;
                hreadyout = 0;
                hresponse = 2'b0;
                  
            end

        3'b001:
            begin

                hrdata = hrdata_1;
                hreadyout = hreadyout_1;
                hresponse = hresp_1;
                  
            end


        3'b010:
            begin

                hrdata = hrdata_2;
                hreadyout = hreadyout_2;
                hresponse = hresp_2;

            end

        3'b011:
            begin

                hrdata = hrdata_3;
                hreadyout = hreadyout_3;
                hresponse = hresp_3;

            end

       default:
            begin

                hrdata = 32'bz;
                hreadyout = hreadyout;
                hresponse = 2'bz;

            end


    endcase


endmodule

BUFFER.v
module BUFFER(out, in);
input in;
output out;

assign out = in;
endmodule

decoder.v
module decoder( hsel_0, hsel_1, hsel_2, haddr,rst);

 input [15:0] haddr;  // Input address from the Address mux
 input rst;
 output reg hsel_0; // hSelect  slave0
 output reg hsel_1; //hSelect  slave1 
 output reg hsel_2; //hSelect  slave2 
 
  
 always @(*)
  if(rst)
    begin
        hsel_0 = 1'b0;
        hsel_1 = 1'b0;
        hsel_2 = 1'b0;
    end
  else
    begin
    case (haddr[15:13])
        3'b001:
            begin
              hsel_0 = 1'b1;
              hsel_1 = 1'b0;
              hsel_2 = 1'b0;
            end

        3'b010:
            begin
              hsel_0 = 1'b0;
              hsel_1 = 1'b1;
              hsel_2 = 1'b0;
            end

        3'b011:
            begin
              hsel_0 = 1'b0;
              hsel_1 = 1'b0;
              hsel_2 = 1'b1;
            end
        default:
            begin
              hsel_0 = 1'b0;
              hsel_1 = 1'b0;
              hsel_2 = 1'b0;
            end

    endcase
    end


endmodule

TRI_BUFF_D.v
module TRI_BUFF_D(out, en, in,rst);
input en,rst;
input [31:0] in;
output reg [31:0] out;

always @(*)
  if(rst)
    begin
        out = 32'b0;
    end
    else
    out = in;
endmodule

TRI_BUFF.v
module TRI_BUFF(out, en, in,rst);
input en,rst;
input [15:0] in;
output reg [15:0] out;

always @(*)
  if(rst)
    begin
        out = 16'b0;
    end
    else
    out = in;
endmodule

MUXD.v
module MUXD(out, in0, in1, sel);

input sel;
input [31:0]in0, in1;
output [31:0]out;

assign out = sel ? in1 : in0;

endmodule

PIPOD.v
module PIPOD(dout,din,ld,clk);
    input [31:0] din;
    input ld,clk;
    output reg [31:0] dout;

    always @(posedge clk)
        begin
            if (ld) 
                dout <= din;
       else
                dout <= 32'bz; 
        end 
endmodule

MUX.v
module MUX(out, in0, in1, sel);

input sel;
input [15:0]in0, in1;
output [15:0]out;

assign out = sel ? in1 : in0;

endmodule

PIPO.v
module PIPO(dout,din,ld,clk);
    input [15:0] din;
    input ld,clk;
    output reg [15:0] dout;

    always @(posedge clk)
        begin
            if (ld) 
                dout <= din;
            else
                dout <= 16'bz; 
        end
endmodule

data_path.v
module data_path(slave_0,slave_1,slave_2,address,Aout,sel1,sel2,mux1,rst,data_in1,data_in2,clk,
                                sel3,sel4,mux2,data_in3,data_in4,
                                rdin1,rdin2,rdin3,resp1,resp2,resp3,rdy1,rdy2,rdy3,dout,rdyout,respout,
                                dataout, Dout);

    input sel1,sel2,mux1,sel3,sel4,mux2,clk,rst,Aout,Dout;
    input [15:0] data_in1, data_in2;
    input [31:0] data_in3,data_in4;

    //read data mux
    input [31:0] rdin1,rdin2,rdin3;
    input [1:0] resp1,resp2,resp3;
    input rdy1,rdy2,rdy3;

    output [31:0] dout;
    output rdyout;
    output [1:0] respout;

//.......................
    output [15:0] address;
    output [31:0] dataout;
//.........................


    wire hsel_0,hsel_1,hsel_2;

    wire [15:0] x,y,z; //for address values passing
    wire [31:0] p,q,r; // for data values

    output slave_0,slave_1,slave_2; //buffer outputs

//making control inputs for the data out register

    wire [2:0] seld;
    assign seld[0] = hsel_0;
    assign seld[1] = hsel_1;
    assign seld[2] = hsel_2;


   
 //address muxes   
    PIPO HADDR1 (x,data_in1,sel1,clk);
    PIPO HADDR2 (y,data_in2,sel2,clk);
    MUX addressmux (z,x,y,mux1);

//data muxes
    PIPOD HWDATA1 (p,data_in3,sel3,clk);
    PIPOD HWDATA2 (q,data_in4,sel4,clk);
    MUXD datamux (r,p,q,mux2);

   
    TRI_BUFF add_buff(address,Aout,z,rst); // pssing address from the master
    TRI_BUFF_D data_buff(dataout,Dout,r,rst); //passing data from the master

    decoder dec1 (hsel_0,hsel_1,hsel_2,z,rst);

    BUFFER out1(slave_0,hsel_0);
    BUFFER out2(slave_1,hsel_1);
    BUFFER out3(slave_2,hsel_2);

// read data mux

    MUXR readMUX(dout,rdyout,respout,rdin1,rdin2,rdin3,rdy1,rdy2,rdy3,resp1,resp2,resp3,seld);





    
endmodule

test1_tb.v
`timescale 1ns/1ns
`include "control_states.v"
`include "data_path.v"
`include "MUX.v"
`include "PIPO.v"
`include "decoder.v"
`include "BUFFER.v"
`include "PIPOD.v"
`include "MUXD.v"
`include "MUXR.v"
`include "TRI_BUFF.v"
`include "TRI_BUFF_D.v"


module test1_tb;

reg [15:0] data_in1,data_in2;
reg [31:0] data_in3,data_in4;

reg clk,rst;
wire [15:0] address; //for address out

//for data put register from slaves
reg [31:0] rdin1,rdin2,rdin3;
reg [1:0] resp1,resp2,resp3;
reg rdy1,rdy2,rdy3;

//output data from slaves
wire [31:0] dout;
wire [1:0] respout;

//output data from master to slave
wire [31:0] dataout;

//for the arbiter part

reg [1:0] response;
reg split,ready,busreq_1,busreq_2,read_write;
   // reg ready,grant_1,grant_2;

                
//data_path dpt1 (hsel_0,hsel_1,hsel_2,address,Aout,sel1,sel2,mux1,rst,data_in1,data_in2,clk);

data_path dpt(slave_0,slave_1,slave_2,address,Aout,sel1,sel2,mux1,rst,data_in1,data_in2,clk,
                                sel3,sel4,mux2,data_in3,data_in4,
                                rdin1,rdin2,rdin3,resp1,resp2,resp3,rdy1,rdy2,rdy3,dout,rdyout,respout,
                                dataout, Dout);
                                
                               

control_states cpt1(sel1,sel2,sel3,sel4,mux2,clk,mux1,rst,Aout,Dout,
                            busreq_1,busreq_2,grant_1,grant_2,split,response,ready,read_write,error);

initial
    begin
        clk = 1'b0;
        #1000 $finish;
    end

always #5 clk = ~clk;

initial
    begin
   
     //   rst = 1'b1; #1;

        data_in1 = 16'b0010000000001000;  //slave one select h2008
      //  data_in2 = 16'b0100000000001000; #1; //slave 2 select h4008

        data_in3 = 567; #20;
        data_in4 = 434; #20;

        rdin1 = 50;#1;
        rdin2 = 0;#1;
        rdin3 = 0;#1;

        resp1 = 2'b01;#1;
        resp2 = 2'b11;#1;
        resp1 = 2'b10;#1;

        rdy1 = 1;#1;
        rdy2 = 0;#1;
        rdy3 = 1;#1;

        //for arbiter read_write: 1 - write / 0 - read

        
    // Testing the idle condition
   /*     rst = 1'b0;
        busreq_1 = 1;
        read_write =1'bx; #10;
        busreq_2= 0;
        read_write =1'bx; #10;
        read_write =1'b0;
        split = 1'bx; #10;
        ready = 1;#10;
        ready = 0;
     

        response = 2'b00;*/
/*...............................................................................................................
    //writing to slave1 by the master1 from idle state
        rst = 0;#1;
        busreq_1 = 1;#1; // master 1 requesting the bus
        busreq_2 = 0;#1;
        ready = 1; #1;//slave ready
        split = 0;#1;  //no split transfers
        response = 2'b00;#1; //response is in complete state
        read_write = 1;#100;  // write request

        rst = 1; #20;
       
        rst = 0;#1;
        busreq_1 = 1;#1; // master 1 requesting the bus
        busreq_2 = 0;#1;
        ready = 1; #1;//slave ready
        split = 0;#1;  //no split transfers
        response = 2'b00;#1; //response is in complete state
        read_write = 1;#200;  // write request

        busreq_1 = 1;#1; // master 1 requesting the bus
        busreq_2 = 1;#1;
        ready = 1; #1;//slave ready
        split = 0;#1;  //no split transfers
        response = 2'b00;#1; //response is in complete state
        read_write = 1;#200;  // write request

       ............................................................................................ */

       //reading from slave 1 by master1
    /*    rst = 0;#1;
        busreq_1 = 1;#1; // master 1 requesting the bus
        busreq_2 = 0;#1;
        ready = 1; #1;//slave ready
        split = 0;#1;  //no split transfers
        response = 2'b00;#1; //response is in complete state
        read_write = 0;#100;  // write request

        rst = 1; #20;
       
        rst = 0;#1;
        busreq_1 = 1;#1; // master 1 requesting the bus
        busreq_2 = 0;#1;
        ready = 1; #1;//slave ready
        split = 0;#1;  //no split transfers
        response = 2'b00;#1; //response is in complete state
        read_write = 0;#200;  // write request

        busreq_1 = 1;#1; // master 1 requesting the bus
        busreq_2 = 0;#1;
        ready = 1; #1;//slave ready
        split = 0;#1;  //no split transfers
        response = 2'b00;#1; //response is in complete state
        read_write = 0;#200;  //  */
//..........................................................................................................
    //when both masters got accessed

    /*    rst = 0;#1;
        busreq_1 = 1;#1; // master 1 requesting the bus
        busreq_2 = 1;#1;
        ready = 1; #1;//slave ready
        split = 0;#1;  //no split transfers
        response = 2'b00;#1; //response is in complete state
        read_write = 0;#100;  // write request

        rst = 1; #20;
       
        rst = 0;#1;
        busreq_1 = 1;#1; // master 1 requesting the bus
        busreq_2 = 1;#1;
        ready = 1; #1;//slave ready
        split = 0;#1;  //no split transfers
        response = 2'b00;#1; //response is in complete state
        read_write = 0;#200;  // write request

    */
    //...........................................................................................

        rst = 0;#20;
        busreq_1 = 1;#1; // master 1 requesting the bus
        busreq_2 = 0;#1;
        ready = 1; #1;//slave ready
        split = 0;#1;  //no split transfers
        response = 2'b00;#1; //response is in complete state
        read_write = 0;#100;  // write request

        rst = 1;#20;

        response = 2'b01; #10;

        rst = 1'b0;



       /*   
        busreq_1 = 1;#1; // master 1 requesting the bus
        busreq_2 = 0;#1;
        ready = 1; #1;//slave ready
        split = 0;#1;  //no split transfers
        response = 2'b00;#1; //response is in complete state
        read_write = 0;#200;  // write request
        */



      //reading from slave1 by the master1 from idle state
    /*    busreq_1 = 1;#1;
        busreq_2 = 0;#1;
        ready = 1;#1;
        split = 0;#1;
        response = 2'b00;#1;
        read_write = 0; */

    //reading from slave1 by the master 2 from idle state
     /*   busreq_1 = 0;#1;
        busreq_2 = 1;#1;
        ready = 1;#1;
        split = 0;#1;
        response = 2'b00;#1;
        read_write = 0;*/

    //both masters are requesting the buss address from idle state. Master1 was assigned highest priority
   /*     busreq_1 = 1;#1;
        busreq_2 = 1;#1;
        ready = 1;#1;
        split = 0;#1;
        response = 2'b00;#1;
        read_write = 0;
*/
        

       // data_in1 = 16'b0110000000001000; #1;

       // rst = 1'b0; #500;

       // rst = 1'b1;

       // #200;
        //rst = 1'b1;
        //data_in2 = 16'b1000000000001000; #50;
        //data_in1 = 16'b0000000000001000; #1;

       
    end

initial
    begin
    
        $dumpfile("test1_tb.vcd");
        $dumpvars(0,test1_tb);
        $display("End of test!!!");

    end

endmodule

test1_tb.vcd
$date
	Mon Dec 25 13:33:12 2023
$end
$version
	Icarus Verilog
$end
$timescale
	1ns
$end
$scope module test1_tb $end
$var wire 1 ! slave_2 $end
$var wire 1 " slave_1 $end
$var wire 1 # slave_0 $end
$var wire 1 $ sel4 $end
$var wire 1 % sel3 $end
$var wire 1 & sel2 $end
$var wire 1 ' sel1 $end
$var wire 2 ( respout [1:0] $end
$var wire 1 ) rdyout $end
$var wire 1 * mux2 $end
$var wire 1 + mux1 $end
$var wire 1 , grant_2 $end
$var wire 1 - grant_1 $end
$var wire 1 . error $end
$var wire 32 / dout [31:0] $end
$var wire 32 0 dataout [31:0] $end
$var wire 16 1 address [15:0] $end
$var wire 1 2 Dout $end
$var wire 1 3 Aout $end
$var reg 1 4 busreq_1 $end
$var reg 1 5 busreq_2 $end
$var reg 1 6 clk $end
$var reg 16 7 data_in1 [15:0] $end
$var reg 16 8 data_in2 [15:0] $end
$var reg 32 9 data_in3 [31:0] $end
$var reg 32 : data_in4 [31:0] $end
$var reg 32 ; rdin1 [31:0] $end
$var reg 32 < rdin2 [31:0] $end
$var reg 32 = rdin3 [31:0] $end
$var reg 1 > rdy1 $end
$var reg 1 ? rdy2 $end
$var reg 1 @ rdy3 $end
$var reg 1 A read_write $end
$var reg 1 B ready $end
$var reg 2 C resp1 [1:0] $end
$var reg 2 D resp2 [1:0] $end
$var reg 2 E resp3 [1:0] $end
$var reg 2 F response [1:0] $end
$var reg 1 G rst $end
$var reg 1 H split $end
$scope module cpt1 $end
$var wire 1 4 busreq_1 $end
$var wire 1 5 busreq_2 $end
$var wire 1 6 clk $end
$var wire 1 A read_write $end
$var wire 1 B ready $end
$var wire 2 I response [1:0] $end
$var wire 1 G rst $end
$var wire 1 H split $end
$var wire 2 J REQ [1:0] $end
$var parameter 2 K M1 $end
$var parameter 2 L M2 $end
$var parameter 2 M MB $end
$var parameter 3 N s0 $end
$var parameter 3 O s1 $end
$var parameter 3 P s2 $end
$var parameter 3 Q s3 $end
$var parameter 3 R s4 $end
$var reg 1 3 Aout $end
$var reg 1 2 Dout $end
$var reg 1 . error $end
$var reg 1 - grant_1 $end
$var reg 1 , grant_2 $end
$var reg 1 + mux1 $end
$var reg 1 * mux2 $end
$var reg 1 ' sel1 $end
$var reg 1 & sel2 $end
$var reg 1 % sel3 $end
$var reg 1 $ sel4 $end
$var reg 3 S state [2:0] $end
$upscope $end
$scope module dpt $end
$var wire 1 3 Aout $end
$var wire 1 2 Dout $end
$var wire 1 6 clk $end
$var wire 16 T data_in1 [15:0] $end
$var wire 16 U data_in2 [15:0] $end
$var wire 32 V data_in3 [31:0] $end
$var wire 32 W data_in4 [31:0] $end
$var wire 1 + mux1 $end
$var wire 1 * mux2 $end
$var wire 32 X rdin1 [31:0] $end
$var wire 32 Y rdin2 [31:0] $end
$var wire 32 Z rdin3 [31:0] $end
$var wire 1 > rdy1 $end
$var wire 1 ? rdy2 $end
$var wire 1 @ rdy3 $end
$var wire 2 [ resp1 [1:0] $end
$var wire 2 \ resp2 [1:0] $end
$var wire 2 ] resp3 [1:0] $end
$var wire 1 G rst $end
$var wire 1 ' sel1 $end
$var wire 1 & sel2 $end
$var wire 1 % sel3 $end
$var wire 1 $ sel4 $end
$var wire 16 ^ z [15:0] $end
$var wire 16 _ y [15:0] $end
$var wire 16 ` x [15:0] $end
$var wire 1 ! slave_2 $end
$var wire 1 " slave_1 $end
$var wire 1 # slave_0 $end
$var wire 3 a seld [2:0] $end
$var wire 2 b respout [1:0] $end
$var wire 1 ) rdyout $end
$var wire 32 c r [31:0] $end
$var wire 32 d q [31:0] $end
$var wire 32 e p [31:0] $end
$var wire 1 f hsel_2 $end
$var wire 1 g hsel_1 $end
$var wire 1 h hsel_0 $end
$var wire 32 i dout [31:0] $end
$var wire 32 j dataout [31:0] $end
$var wire 16 k address [15:0] $end
$scope module HADDR1 $end
$var wire 1 6 clk $end
$var wire 16 l din [15:0] $end
$var wire 1 ' ld $end
$var reg 16 m dout [15:0] $end
$upscope $end
$scope module HADDR2 $end
$var wire 1 6 clk $end
$var wire 16 n din [15:0] $end
$var wire 1 & ld $end
$var reg 16 o dout [15:0] $end
$upscope $end
$scope module HWDATA1 $end
$var wire 1 6 clk $end
$var wire 32 p din [31:0] $end
$var wire 1 % ld $end
$var reg 32 q dout [31:0] $end
$upscope $end
$scope module HWDATA2 $end
$var wire 1 6 clk $end
$var wire 32 r din [31:0] $end
$var wire 1 $ ld $end
$var reg 32 s dout [31:0] $end
$upscope $end
$scope module add_buff $end
$var wire 1 3 en $end
$var wire 1 G rst $end
$var wire 16 t in [15:0] $end
$var reg 16 u out [15:0] $end
$upscope $end
$scope module addressmux $end
$var wire 16 v in0 [15:0] $end
$var wire 16 w in1 [15:0] $end
$var wire 1 + sel $end
$var wire 16 x out [15:0] $end
$upscope $end
$scope module data_buff $end
$var wire 1 2 en $end
$var wire 1 G rst $end
$var wire 32 y in [31:0] $end
$var reg 32 z out [31:0] $end
$upscope $end
$scope module datamux $end
$var wire 32 { in0 [31:0] $end
$var wire 32 | in1 [31:0] $end
$var wire 1 * sel $end
$var wire 32 } out [31:0] $end
$upscope $end
$scope module dec1 $end
$var wire 16 ~ haddr [15:0] $end
$var wire 1 G rst $end
$var reg 1 h hsel_0 $end
$var reg 1 g hsel_1 $end
$var reg 1 f hsel_2 $end
$upscope $end
$scope module out1 $end
$var wire 1 h in $end
$var wire 1 # out $end
$upscope $end
$scope module out2 $end
$var wire 1 g in $end
$var wire 1 " out $end
$upscope $end
$scope module out3 $end
$var wire 1 f in $end
$var wire 1 ! out $end
$upscope $end
$scope module readMUX $end
$var wire 32 !" hrdata_1 [31:0] $end
$var wire 32 "" hrdata_2 [31:0] $end
$var wire 32 #" hrdata_3 [31:0] $end
$var wire 1 > hreadyout_1 $end
$var wire 1 ? hreadyout_2 $end
$var wire 1 @ hreadyout_3 $end
$var wire 2 $" hresp_1 [1:0] $end
$var wire 2 %" hresp_2 [1:0] $end
$var wire 2 &" hresp_3 [1:0] $end
$var wire 3 '" sel [2:0] $end
$var reg 32 (" hrdata [31:0] $end
$var reg 1 ) hreadyout $end
$var reg 2 )" hresponse [1:0] $end
$upscope $end
$upscope $end
$upscope $end
$enddefinitions $end
$comment Show the parameter values. $end
$dumpall
b100 R
b11 Q
b10 P
b1 O
b0 N
b11 M
b10 L
b1 K
$end
#0
$dumpvars
bx )"
bx ("
bx '"
bx &"
bx %"
bx $"
bx #"
bx ""
bx !"
bx ~
bx }
bx |
bx {
bx z
bx y
bx x
bx w
bx v
bx u
bx t
bx s
bx r
bx q
b1000110111 p
bx o
bx n
bx m
b10000000001000 l
bx k
bx j
bx i
xh
xg
xf
bx e
bx d
bx c
bx b
bx a
bx `
bx _
bx ^
bx ]
bx \
bx [
bx Z
bx Y
bx X
bx W
b1000110111 V
bx U
b10000000001000 T
bx S
bx J
bx I
xH
xG
bx F
bx E
bx D
bx C
xB
xA
x@
x?
x>
bx =
bx <
bx ;
bx :
b1000110111 9
bx 8
b10000000001000 7
06
x5
x4
x3
x2
bx 1
bx 0
bx /
x.
x-
x,
x+
x*
x)
bx (
x'
x&
x%
x$
x#
x"
x!
$end
#5
bz (
bz b
bz )"
bz /
bz i
bz ("
0!
0f
0"
0g
0#
b0 a
b0 '"
0h
bz 1
bz k
bz u
bz 0
bz j
bz z
bz ^
bz t
bz x
bz ~
bz c
bz y
bz }
0.
0,
0-
02
0*
0$
0%
03
0+
0&
0'
bz `
bz m
bz v
bz _
bz o
bz w
bz e
bz q
bz {
bz d
bz s
bz |
b0 S
16
#10
06
#15
16
#20
06
b110110010 :
b110110010 W
b110110010 r
#25
16
#30
06
#35
16
#40
06
b110010 ;
b110010 X
b110010 !"
#41
b0 <
b0 Y
b0 ""
#42
b0 =
b0 Z
b0 #"
#43
b1 C
b1 [
b1 $"
#44
b11 D
b11 \
b11 %"
#45
b10 C
b10 [
b10 $"
16
#46
1>
#47
0?
#48
1@
#49
0G
#50
06
#55
16
#60
06
#65
16
#69
bx1 J
14
#70
b1 J
05
06
#71
1B
#72
0H
#73
b0 F
b0 I
#74
0A
#75
13
1'
b10 S
1-
16
#80
06
#85
b10 (
b10 b
b10 )"
1)
b110010 /
b110010 i
b110010 ("
1#
b1 a
b1 '"
1h
b10000000001000 1
b10000000001000 k
b10000000001000 u
b10000000001000 ^
b10000000001000 t
b10000000001000 x
b10000000001000 ~
b10000000001000 `
b10000000001000 m
b10000000001000 v
b0 S
16
#90
06
#95
b10 S
16
#100
06
#105
b0 S
16
#110
06
#115
b10 S
16
#120
06
#125
b0 S
16
#130
06
#135
b10 S
16
#140
06
#145
b0 S
16
#150
06
#155
b10 S
16
#160
06
#165
b0 S
16
#170
06
#174
bz (
bz b
bz )"
bz /
bz i
bz ("
b0 1
b0 k
b0 u
0#
b0 a
b0 '"
0h
b0 0
b0 j
b0 z
1G
#175
0-
16
#180
06
#185
16
#190
06
#194
b1 F
b1 I
#195
16
#200
06
#204
b10 (
b10 b
b10 )"
b110010 /
b110010 i
b110010 ("
1#
b1 a
b1 '"
1h
b10000000001000 1
b10000000001000 k
b10000000001000 u
bz 0
bz j
bz z
0G
