control_states.v
module control_states(sel1,sel2,sel3,sel4,mux2,clk,mux1,rst,Aout);
input clk,rst;
output reg sel1,sel2,mux1,sel3,sel4,mux2,Aout;

reg [2:0] state;
parameter s0=3'b000, s1=3'b001, s2=3'b010, s3=3'b011, s4=3'b100;

always @(posedge clk)
    begin
        case (state)
            s0: if (~rst) state <= s1;
            s1: state <= s2;
            s2: state <= s3;
            s3: state <= s4;
            s4: state <= s0;
            default: state <= s0;
        endcase
    end

always @(state)
    begin
        case (state)
            s0: begin #10 sel1=0; sel2 = 0; mux1 = 0; Aout = 0; sel3=0; sel4 = 0; mux2 = 0; end
            s1: begin #10 sel1=1; sel2 = 0; mux1 = 0; Aout = 0; sel3=1; sel4 = 0; mux2 = 0; end
            s2: begin #10 sel1=0; sel2 = 1; mux1 = 0; Aout = 0; sel3=0; sel4 = 1; mux2 = 0;  end
            s3: begin #10 mux1=1; sel2 = 1; sel1 = 0; Aout = 0; sel3=0; sel4 = 1; mux2 = 1;  end
            s4: begin #10 sel1 = 0; sel2 = 0; mux1=0; Aout = 0; sel3=0; sel4 = 0; mux2 = 0;  end
            default: begin #10 sel1=0; sel2 = 0; mux1 = 0; Aout = 0; sel3=0; sel4 = 0; mux2 = 0;  end
        
        endcase

    end

endmodule

BUFFER.v
module BUFFER(out, in);
input in;
output out;

assign out = in;
endmodule

decoder.v
module decoder( hsel_0, hsel_1, hsel_2, haddr,rst);

 input [15:0] haddr;  // Input address from the Address mux
 input rst;
 output reg hsel_0; // hSelect  slave0
 output reg hsel_1; //hSelect  slave1 
 output reg hsel_2; //hSelect  slave2 
 
  
 always @(*)
  if(rst)
    begin
        hsel_0 = 1'b0;
        hsel_1 = 1'b0;
        hsel_2 = 1'b0;
    end
  else
    begin
    case (haddr[15:13])
        3'b001:
            begin
              hsel_0 = 1'b1;
              hsel_1 = 1'b0;
              hsel_2 = 1'b0;
            end

        3'b010:
            begin
              hsel_0 = 1'b0;
              hsel_1 = 1'b1;
              hsel_2 = 1'b0;
            end

        3'b011:
            begin
              hsel_0 = 1'b0;
              hsel_1 = 1'b0;
              hsel_2 = 1'b1;
            end
        default:
            begin
              hsel_0 = 1'b0;
              hsel_1 = 1'b0;
              hsel_2 = 1'b0;
            end

    endcase
    end


endmodule

PIPO.v
module PIPO(dout,din,ld,clk);
    input [15:0] din;
    input ld,clk;
    output reg [15:0] dout;

    always @(posedge clk)
        begin
            if (ld) 
                dout <= din;
            else
                dout <= 16'bz; 
        end
endmodule

MUXD.v
module MUXD(out, in0, in1, sel);

input sel;
input [31:0]in0, in1;
output [31:0]out;

assign out = sel ? in1 : in0;

endmodule

PIPOD.v
module PIPOD(dout,din,ld,clk);
    input [31:0] din;
    input ld,clk;
    output reg [31:0] dout;

    always @(posedge clk)
        begin
            if (ld) 
                dout <= din;
            else
                dout <= 32'bz;
        end
endmodule

MUX.v
module MUX(out, in0, in1, sel);

input sel;
input [15:0]in0, in1;
output [15:0]out;

assign out = sel ? in1 : in0;

endmodule

data_path.v
module data_path(slave_0,slave_1,slave_2,address,Aout,sel1,sel2,mux1,rst,data_in1,data_in2,clk,
                                sel3,sel4,mux2,data_in3,data_in4);

    input sel1,sel2,mux1,sel3,sel4,mux2,clk,rst,Aout;
    input [15:0] data_in1, data_in2;
    input [31:0] data_in3,data_in4;

//.......................
    output [15:0] address;
//.........................


    wire hsel_0,hsel_1,hsel_2;

    wire [15:0] x,y,z; //for address values passing
    wire [31:0] p,q,r; // for data values

    output slave_0,slave_1,slave_2; //buffer outputs

   
 //address muxes   
    PIPO HADDR1 (x,data_in1,sel1,clk);
    PIPO HADDR2 (y,data_in2,sel2,clk);
    MUX addressmux (z,x,y,mux1);

//data muxes
    PIPOD HWDATA1 (p,data_in3,sel3,clk);
    PIPOD HWDATA2 (q,data_in4,sel4,clk);
    MUXD datamux (r,p,q,mux2);

   
    PIPO AOUT (address,z,Aout,clk);

    decoder dec1 (hsel_0,hsel_1,hsel_2,z,rst);

    BUFFER out1(slave_0,hsel_0);
    BUFFER out2(slave_1,hsel_1);
    BUFFER out3(slave_2,hsel_2);

// read data mux

    MUXR 





    
endmodule

test1_tb.v
`timescale 1ns/1ns
`include "control_states.v"
`include "data_path.v"
`include "MUX.v"
`include "PIPO.v"
`include "decoder.v"
`include "BUFFER.v"
`include "PIPOD.v"
`include "MUXD.v"




module test1_tb;

reg [15:0] data_in1,data_in2;
reg [31:0] data_in3,data_in4;

reg clk,rst;
wire [15:0] address;


                
//data_path dpt1 (hsel_0,hsel_1,hsel_2,address,Aout,sel1,sel2,mux1,rst,data_in1,data_in2,clk);

data_path dpt1 (slave_0,slave_1,slave_2,address,Aout,sel1,sel2,mux1,rst,data_in1,data_in2,clk,
                                sel3,sel4,mux2,data_in3,data_in4);

control_states cpt1(sel1,sel2,sel3,sel4,mux2,clk,mux1,rst,Aout);

initial
    begin
        clk = 1'b0;
        #1000 $finish;
    end

always #5 clk = ~clk;

initial
    begin

    
        rst = 1'b1; #1;

       

        data_in1 = 16'b0010000000001000; #1;
        data_in2 = 16'b0100000000001000; #1;

        data_in3 = 567; #1;
        data_in4 = 434; #1;



       // data_in1 = 16'b0110000000001000; #1;

        rst = 1'b0; #500;

        rst = 1'b1;

       // #200;
        //rst = 1'b1;
        //data_in2 = 16'b1000000000001000; #50;
        //data_in1 = 16'b0000000000001000; #1;

       
    end

initial
    begin
    
        $dumpfile("test1_tb.vcd");
        $dumpvars(0,test1_tb);
        $display("End of test!!!");

    end

endmodule

test1_tb.vcd
$date
	Sun Dec 24 12:36:26 2023
$end
$version
	Icarus Verilog
$end
$timescale
	1ns
$end
$scope module test1_tb $end
$var wire 1 ! slave_2 $end
$var wire 1 " slave_1 $end
$var wire 1 # slave_0 $end
$var wire 1 $ sel4 $end
$var wire 1 % sel3 $end
$var wire 1 & sel2 $end
$var wire 1 ' sel1 $end
$var wire 1 ( mux2 $end
$var wire 1 ) mux1 $end
$var wire 16 * address [15:0] $end
$var wire 1 + Aout $end
$var reg 1 , clk $end
$var reg 16 - data_in1 [15:0] $end
$var reg 16 . data_in2 [15:0] $end
$var reg 32 / data_in3 [31:0] $end
$var reg 32 0 data_in4 [31:0] $end
$var reg 1 1 rst $end
$scope module cpt1 $end
$var wire 1 , clk $end
$var wire 1 1 rst $end
$var parameter 3 2 s0 $end
$var parameter 3 3 s1 $end
$var parameter 3 4 s2 $end
$var parameter 3 5 s3 $end
$var parameter 3 6 s4 $end
$var reg 1 + Aout $end
$var reg 1 ) mux1 $end
$var reg 1 ( mux2 $end
$var reg 1 ' sel1 $end
$var reg 1 & sel2 $end
$var reg 1 % sel3 $end
$var reg 1 $ sel4 $end
$var reg 3 7 state [2:0] $end
$upscope $end
$scope module dpt1 $end
$var wire 1 + Aout $end
$var wire 1 , clk $end
$var wire 16 8 data_in1 [15:0] $end
$var wire 16 9 data_in2 [15:0] $end
$var wire 32 : data_in3 [31:0] $end
$var wire 32 ; data_in4 [31:0] $end
$var wire 1 ) mux1 $end
$var wire 1 ( mux2 $end
$var wire 1 1 rst $end
$var wire 1 ' sel1 $end
$var wire 1 & sel2 $end
$var wire 1 % sel3 $end
$var wire 1 $ sel4 $end
$var wire 16 < z [15:0] $end
$var wire 16 = y [15:0] $end
$var wire 16 > x [15:0] $end
$var wire 1 ! slave_2 $end
$var wire 1 " slave_1 $end
$var wire 1 # slave_0 $end
$var wire 32 ? r [31:0] $end
$var wire 32 @ q [31:0] $end
$var wire 32 A p [31:0] $end
$var wire 1 B hsel_2 $end
$var wire 1 C hsel_1 $end
$var wire 1 D hsel_0 $end
$var wire 16 E address [15:0] $end
$scope module AOUT $end
$var wire 1 , clk $end
$var wire 1 + ld $end
$var wire 16 F din [15:0] $end
$var reg 16 G dout [15:0] $end
$upscope $end
$scope module HADDR1 $end
$var wire 1 , clk $end
$var wire 16 H din [15:0] $end
$var wire 1 ' ld $end
$var reg 16 I dout [15:0] $end
$upscope $end
$scope module HADDR2 $end
$var wire 1 , clk $end
$var wire 16 J din [15:0] $end
$var wire 1 & ld $end
$var reg 16 K dout [15:0] $end
$upscope $end
$scope module HWDATA1 $end
$var wire 1 , clk $end
$var wire 32 L din [31:0] $end
$var wire 1 % ld $end
$var reg 32 M dout [31:0] $end
$upscope $end
$scope module HWDATA2 $end
$var wire 1 , clk $end
$var wire 32 N din [31:0] $end
$var wire 1 $ ld $end
$var reg 32 O dout [31:0] $end
$upscope $end
$scope module addressmux $end
$var wire 16 P in0 [15:0] $end
$var wire 16 Q in1 [15:0] $end
$var wire 1 ) sel $end
$var wire 16 R out [15:0] $end
$upscope $end
$scope module datamux $end
$var wire 32 S in0 [31:0] $end
$var wire 32 T in1 [31:0] $end
$var wire 1 ( sel $end
$var wire 32 U out [31:0] $end
$upscope $end
$scope module dec1 $end
$var wire 16 V haddr [15:0] $end
$var wire 1 1 rst $end
$var reg 1 D hsel_0 $end
$var reg 1 C hsel_1 $end
$var reg 1 B hsel_2 $end
$upscope $end
$scope module out1 $end
$var wire 1 D in $end
$var wire 1 # out $end
$upscope $end
$scope module out2 $end
$var wire 1 C in $end
$var wire 1 " out $end
$upscope $end
$scope module out3 $end
$var wire 1 B in $end
$var wire 1 ! out $end
$upscope $end
$upscope $end
$upscope $end
$enddefinitions $end
$comment Show the parameter values. $end
$dumpall
b100 6
b11 5
b10 4
b1 3
b0 2
$end
#0
$dumpvars
bx V
bx U
bx T
bx S
bx R
bx Q
bx P
bx O
bx N
bx M
bx L
bx K
bx J
bx I
bx H
bx G
bx F
bx E
0D
0C
0B
bx A
bx @
bx ?
bx >
bx =
bx <
bx ;
bx :
bx 9
bx 8
bx 7
11
bx 0
bx /
bx .
bx -
0,
x+
bx *
x)
x(
x'
x&
x%
x$
0#
0"
0!
$end
#1
b10000000001000 -
b10000000001000 8
b10000000001000 H
#2
b100000000001000 .
b100000000001000 9
b100000000001000 J
#3
b1000110111 /
b1000110111 :
b1000110111 L
#4
b110110010 0
b110110010 ;
b110110010 N
#5
bz <
bz F
bz R
bz V
bz ?
bz U
bz >
bz I
bz P
bz =
bz K
bz Q
bz A
bz M
bz S
bz @
bz O
bz T
bz *
bz E
bz G
b0 7
01
1,
#10
0,
#15
b1 7
1,
0(
0$
0%
0+
0)
0&
0'
#20
0,
#25
1#
1D
b10000000001000 <
b10000000001000 F
b10000000001000 R
b10000000001000 V
b1000110111 ?
b1000110111 U
b10000000001000 >
b10000000001000 I
b10000000001000 P
b1000110111 A
b1000110111 M
b1000110111 S
b10 7
1,
1%
1'
#30
0,
#35
0#
0D
bz ?
bz U
bz <
bz F
bz R
bz V
b11 7
b110110010 @
b110110010 O
b110110010 T
bz A
bz M
bz S
b100000000001000 =
b100000000001000 K
b100000000001000 Q
bz >
bz I
bz P
1,
1$
0%
1&
0'
#40
0,
#45
b100 7
1"
1C
b110110010 ?
b110110010 U
b100000000001000 <
b100000000001000 F
b100000000001000 R
b100000000001000 V
1,
1(
1)
#50
0,
#55
b0 7
bz @
bz O
bz T
bz =
bz K
bz Q
0"
0C
bz ?
bz U
bz <
bz F
bz R
bz V
1,
0(
0$
0)
0&
#60
0,
#65
b1 7
1,
#70
0,
#75
1#
1D
b1000110111 ?
b1000110111 U
b10000000001000 <
b10000000001000 F
b10000000001000 R
b10000000001000 V
b10 7
b1000110111 A
b1000110111 M
b1000110111 S
b10000000001000 >
b10000000001000 I
b10000000001000 P
1,
1%
1'
#80
0,
#85
0#
0D
bz <
bz F
bz R
bz V
bz ?
bz U
bz >
bz I
bz P
b100000000001000 =
b100000000001000 K
b100000000001000 Q
bz A
bz M
bz S
b110110010 @
b110110010 O
b110110010 T
b11 7
1,
1$
0%
1&
0'
#90
0,
#95
b100 7
1"
1C
b110110010 ?
b110110010 U
b100000000001000 <
b100000000001000 F
b100000000001000 R
b100000000001000 V
1,
1(
1)
#100
0,
#105
bz =
bz K
bz Q
bz @
bz O
bz T
b0 7
0"
0C
bz ?
bz U
bz <
bz F
bz R
bz V
1,
0(
0$
0)
0&
#110
0,
#115
b1 7
1,
#120
0,
#125
1#
1D
b10000000001000 <
b10000000001000 F
b10000000001000 R
b10000000001000 V
b1000110111 ?
b1000110111 U
b10000000001000 >
b10000000001000 I
b10000000001000 P
b1000110111 A
b1000110111 M
b1000110111 S
b10 7
1,
1%
1'
#130
0,
#135
0#
0D
bz ?
bz U
bz <
bz F
bz R
bz V
b11 7
b110110010 @
b110110010 O
b110110010 T
bz A
bz M
bz S
b100000000001000 =
b100000000001000 K
b100000000001000 Q
bz >
bz I
bz P
1,
1$
0%
1&
0'
#140
0,
#145
b100 7
1"
1C
b110110010 ?
b110110010 U
b100000000001000 <
b100000000001000 F
b100000000001000 R
b100000000001000 V
1,
1(
1)
#150
0,
#155
b0 7
bz @
bz O
bz T
bz =
bz K
bz Q
0"
0C
bz ?
bz U
bz <
bz F
bz R
bz V
1,
0(
0$
0)
0&
#160
0,
#165
b1 7
1,
#170
0,
#175
1#
1D
b1000110111 ?
b1000110111 U
b10000000001000 <
b10000000001000 F
b10000000001000 R
b10000000001000 V
b10 7
b1000110111 A
b1000110111 M
b1000110111 S
b10000000001000 >
b10000000001000 I
b10000000001000 P
1,
1%
1'
#180
0,
#185
0#
0D
bz <
bz F
bz R
bz V
bz ?
bz U
bz >
bz I
bz P
b100000000001000 =
b100000000001000 K
b100000000001000 Q
bz A
bz M
bz S
b110110010 @
b110110010 O
b110110010 T
b11 7
1,
1$
0%
1&
0'
#190
0,
#195
b100 7
1"
1C
b110110010 ?
b110110010 U
b100000000001000 <
b100000000001000 F
b100000000001000 R
b100000000001000 V
1,
1(
1)
#200
0,
#205
bz =
bz K
bz Q
bz @
bz O
bz T
b0 7
0"
0C
bz ?
bz U
bz <
bz F
bz R
bz V
1,
0(
0$
0)
0&
#210
0,
#215
b1 7
1,
#220
0,
#225
1#
1D
b10000000001000 <
b10000000001000 F
b10000000001000 R
b10000000001000 V
b1000110111 ?
b1000110111 U
b10000000001000 >
b10000000001000 I
b10000000001000 P
b1000110111 A
b1000110111 M
b1000110111 S
b10 7
1,
1%
1'
#230
0,
#235
0#
0D
bz ?
bz U
bz <
bz F
bz R
bz V
b11 7
b110110010 @
b110110010 O
b110110010 T
bz A
bz M
bz S
b100000000001000 =
b100000000001000 K
b100000000001000 Q
bz >
bz I
bz P
1,
1$
0%
1&
0'
#240
0,
#245
b100 7
1"
1C
b110110010 ?
b110110010 U
b100000000001000 <
b100000000001000 F
b100000000001000 R
b100000000001000 V
1,
1(
1)
#250
0,
#255
b0 7
bz @
bz O
bz T
bz =
bz K
bz Q
0"
0C
bz ?
bz U
bz <
bz F
bz R
bz V
1,
0(
0$
0)
0&
#260
0,
#265
b1 7
1,
#270
0,
#275
1#
1D
b1000110111 ?
b1000110111 U
b10000000001000 <
b10000000001000 F
b10000000001000 R
b10000000001000 V
b10 7
b1000110111 A
b1000110111 M
b1000110111 S
b10000000001000 >
b10000000001000 I
b10000000001000 P
1,
1%
1'
#280
0,
#285
0#
0D
bz <
bz F
bz R
bz V
bz ?
bz U
bz >
bz I
bz P
b100000000001000 =
b100000000001000 K
b100000000001000 Q
bz A
bz M
bz S
b110110010 @
b110110010 O
b110110010 T
b11 7
1,
1$
0%
1&
0'
#290
0,
#295
b100 7
1"
1C
b110110010 ?
b110110010 U
b100000000001000 <
b100000000001000 F
b100000000001000 R
b100000000001000 V
1,
1(
1)
#300
0,
#305
bz =
bz K
bz Q
bz @
bz O
bz T
b0 7
0"
0C
bz ?
bz U
bz <
bz F
bz R
bz V
1,
0(
0$
0)
0&
#310
0,
#315
b1 7
1,
#320
0,
#325
1#
1D
b10000000001000 <
b10000000001000 F
b10000000001000 R
b10000000001000 V
b1000110111 ?
b1000110111 U
b10000000001000 >
b10000000001000 I
b10000000001000 P
b1000110111 A
b1000110111 M
b1000110111 S
b10 7
1,
1%
1'
#330
0,
#335
0#
0D
bz ?
bz U
bz <
bz F
bz R
bz V
b11 7
b110110010 @
b110110010 O
b110110010 T
bz A
bz M
bz S
b100000000001000 =
b100000000001000 K
b100000000001000 Q
bz >
bz I
bz P
1,
1$
0%
1&
0'
#340
0,
#345
b100 7
1"
1C
b110110010 ?
b110110010 U
b100000000001000 <
b100000000001000 F
b100000000001000 R
b100000000001000 V
1,
1(
1)
#350
0,
#355
b0 7
bz @
bz O
bz T
bz =
bz K
bz Q
0"
0C
bz ?
bz U
bz <
bz F
bz R
bz V
1,
0(
0$
0)
0&
#360
0,
#365
b1 7
1,
#370
0,
#375
1#
1D
b1000110111 ?
b1000110111 U
b10000000001000 <
b10000000001000 F
b10000000001000 R
b10000000001000 V
b10 7
b1000110111 A
b1000110111 M
b1000110111 S
b10000000001000 >
b10000000001000 I
b10000000001000 P
1,
1%
1'
#380
0,
#385
0#
0D
bz <
bz F
bz R
bz V
bz ?
bz U
bz >
bz I
bz P
b100000000001000 =
b100000000001000 K
b100000000001000 Q
bz A
bz M
bz S
b110110010 @
b110110010 O
b110110010 T
b11 7
1,
1$
0%
1&
0'
#390
0,
#395
b100 7
1"
1C
b110110010 ?
b110110010 U
b100000000001000 <
b100000000001000 F
b100000000001000 R
b100000000001000 V
1,
1(
1)
#400
0,
#405
bz =
bz K
bz Q
bz @
bz O
bz T
b0 7
0"
0C
bz ?
bz U
bz <
bz F
bz R
bz V
1,
0(
0$
0)
0&
#410
0,
#415
b1 7
1,
#420
0,
#425
1#
1D
b10000000001000 <
b10000000001000 F
b10000000001000 R
b10000000001000 V
b1000110111 ?
b1000110111 U
b10000000001000 >
b10000000001000 I
b10000000001000 P
b1000110111 A
b1000110111 M
b1000110111 S
b10 7
1,
1%
1'
#430
0,
#435
0#
0D
bz ?
bz U
bz <
bz F
bz R
bz V
b11 7
b110110010 @
b110110010 O
b110110010 T
bz A
bz M
bz S
b100000000001000 =
b100000000001000 K
b100000000001000 Q
bz >
bz I
bz P
1,
1$
0%
1&
0'
#440
0,
#445
b100 7
1"
1C
b110110010 ?
b110110010 U
b100000000001000 <
b100000000001000 F
b100000000001000 R
b100000000001000 V
1,
1(
1)
#450
0,
#455
b0 7
bz @
bz O
bz T
bz =
bz K
bz Q
0"
0C
bz ?
bz U
bz <
bz F
bz R
bz V
1,
0(
0$
0)
0&
#460
0,
#465
b1 7
1,
#470
0,
#475
1#
1D
b1000110111 ?
b1000110111 U
b10000000001000 <
b10000000001000 F
b10000000001000 R
b10000000001000 V
b10 7
b1000110111 A
b1000110111 M
b1000110111 S
b10000000001000 >
b10000000001000 I
b10000000001000 P
1,
1%
1'
#480
0,
#485
0#
0D
bz <
bz F
bz R
bz V
bz ?
bz U
bz >
bz I
bz P
b100000000001000 =
b100000000001000 K
b100000000001000 Q
bz A
bz M
bz S
b110110010 @
b110110010 O
b110110010 T
b11 7
1,
1$
0%
1&
0'
#490
0,
#495
b100 7
1"
1C
b110110010 ?
b110110010 U
b100000000001000 <
b100000000001000 F
b100000000001000 R
b100000000001000 V
1,
1(
1)
#500
0,
#505
bz =
bz K
bz Q
bz @
bz O
bz T
b0 7
bz ?
bz U
bz <
bz F
bz R
bz V
0"
0C
1,
0(
0$
0)
0&
11
