control_states.v
module control_states(sel1,sel2,sel3,sel4,mux2,clk,mux1,rst,Aout,Dout);
input clk,rst;
output reg sel1,sel2,mux1,sel3,sel4,mux2,Aout,Dout;

reg [2:0] state;
parameter s0=3'b000, s1=3'b001, s2=3'b010, s3=3'b011, s4=3'b100;

always @(posedge clk)
    begin
        case (state)
            s0: if (~rst) state <= s1;
            s1: state <= s2;
            s2: state <= s3;
            s3: state <= s4;
            s4: state <= s0;
            default: state <= s0;
        endcase
    end

always @(state)
    begin
        case (state)
            s0: begin #10 sel1=0; sel2 = 0; mux1 = 0; Aout = 0; sel3=0; sel4 = 0; mux2 = 0; Dout = 0;  end
            s1: begin #10 sel1=1; sel2 = 0; mux1 = 0; Aout = 1; sel3=1; sel4 = 0; mux2 = 0; Dout = 1; end
            s2: begin #10 sel1=0; sel2 = 1; mux1 = 0; Aout = 0; sel3=0; sel4 = 1; mux2 = 0; Dout = 0;  end
            s3: begin #10 mux1=1; sel2 = 1; sel1 = 0; Aout = 1; sel3=0; sel4 = 1; mux2 = 1; Dout = 1;  end
            s4: begin #10 sel1 = 0; sel2 = 0; mux1=0; Aout = 0; sel3=0; sel4 = 0; mux2 = 0; Dout = 0;  end
            default: begin #10 sel1=0; sel2 = 0; mux1 = 0; Aout = 0; sel3=0; sel4 = 0; mux2 = 0; Dout = 0;  end
        
        endcase

    end

endmodule

MUXR.v
module MUXR(hrdata,hreadyout,hresponse, hrdata_1, hrdata_2,hrdata_3,hreadyout_1,hreadyout_2,hreadyout_3,
                hresp_1,hresp_2,hresp_3,sel);


input [31:0] hrdata_1;
input [31:0] hrdata_2;
input [31:0] hrdata_3;

input hreadyout_1;
input hreadyout_2;
input hreadyout_3;

input [1:0] hresp_1;
input [1:0] hresp_2;
input [1:0] hresp_3;

input [2:0] sel;

output reg [31:0] hrdata;
output reg hreadyout;
output reg [1:0] hresponse;


always @(*)
    case (sel)

        3'b000:
            begin

                hrdata = 32'bz;
                hreadyout = hreadyout;
                hresponse = 2'bz;
                  
            end

        3'b001:
            begin

                hrdata = hrdata_1;
                hreadyout = hreadyout_1;
                hresponse = hresp_1;
                  
            end


        3'b010:
            begin

                hrdata = hrdata_2;
                hreadyout = hreadyout_2;
                hresponse = hresp_2;

            end

        3'b011:
            begin

                hrdata = hrdata_3;
                hreadyout = hreadyout_3;
                hresponse = hresp_3;

            end

       default:
            begin

                hrdata = 32'bz;
                hreadyout = hreadyout;
                hresponse = 2'bz;

            end


    endcase


endmodule

BUFFER.v
module BUFFER(out, in);
input in;
output out;

assign out = in;
endmodule

decoder.v
module decoder( hsel_0, hsel_1, hsel_2, haddr,rst);

 input [15:0] haddr;  // Input address from the Address mux
 input rst;
 output reg hsel_0; // hSelect  slave0
 output reg hsel_1; //hSelect  slave1 
 output reg hsel_2; //hSelect  slave2 
 
  
 always @(*)
  if(rst)
    begin
        hsel_0 = 1'b0;
        hsel_1 = 1'b0;
        hsel_2 = 1'b0;
    end
  else
    begin
    case (haddr[15:13])
        3'b001:
            begin
              hsel_0 = 1'b1;
              hsel_1 = 1'b0;
              hsel_2 = 1'b0;
            end

        3'b010:
            begin
              hsel_0 = 1'b0;
              hsel_1 = 1'b1;
              hsel_2 = 1'b0;
            end

        3'b011:
            begin
              hsel_0 = 1'b0;
              hsel_1 = 1'b0;
              hsel_2 = 1'b1;
            end
        default:
            begin
              hsel_0 = 1'b0;
              hsel_1 = 1'b0;
              hsel_2 = 1'b0;
            end

    endcase
    end


endmodule

TRI_BUFF_D.v
module TRI_BUFF_D(out, en, in);
input en;
input [31:0] in;
output [31:0] out;

assign out = en ? in : 32'b0;
endmodule

TRI_BUFF.v
module TRI_BUFF(out, en, in);
input en;
input [15:0] in;
output [15:0] out;

assign out = en ? in : 16'b0;
endmodule

MUXD.v
module MUXD(out, in0, in1, sel);

input sel;
input [31:0]in0, in1;
output [31:0]out;

assign out = sel ? in1 : in0;

endmodule

PIPOD.v
module PIPOD(dout,din,ld,clk);
    input [31:0] din;
    input ld,clk;
    output reg [31:0] dout;

    always @(posedge clk)
        if (ld) 
            dout <= din;

endmodule

MUX.v
module MUX(out, in0, in1, sel);

input sel;
input [15:0]in0, in1;
output [15:0]out;

assign out = sel ? in1 : in0;

endmodule

PIPO.v
module PIPO(dout,din,ld,clk);
    input [15:0] din;
    input ld,clk;
    output reg [15:0] dout;

    always @(posedge clk)
        begin
            if (ld) 
                dout <= din;
            else
                dout <= 16'bz; 
        end
endmodule

data_path.v
module data_path(slave_0,slave_1,slave_2,address,Aout,sel1,sel2,mux1,rst,data_in1,data_in2,clk,
                                sel3,sel4,mux2,data_in3,data_in4,
                                rdin1,rdin2,rdin3,resp1,resp2,resp3,rdy1,rdy2,rdy3,dout,rdyout,respout,
                                dataout, Dout);

    input sel1,sel2,mux1,sel3,sel4,mux2,clk,rst,Aout,Dout;
    input [15:0] data_in1, data_in2;
    input [31:0] data_in3,data_in4;

    //read data mux
    input [31:0] rdin1,rdin2,rdin3;
    input [1:0] resp1,resp2,resp3;
    input rdy1,rdy2,rdy3;

    output [31:0] dout;
    output rdyout;
    output [1:0] respout;

//.......................
    output [15:0] address;
    output [31:0] dataout;
//.........................


    wire hsel_0,hsel_1,hsel_2;

    wire [15:0] x,y,z; //for address values passing
    wire [31:0] p,q,r; // for data values

    output slave_0,slave_1,slave_2; //buffer outputs

//making control inputs for the data out register

    wire [2:0] seld;
    assign seld[0] = hsel_0;
    assign seld[1] = hsel_1;
    assign seld[2] = hsel_2;


   
 //address muxes   
    PIPO HADDR1 (x,data_in1,sel1,clk);
    PIPO HADDR2 (y,data_in2,sel2,clk);
    MUX addressmux (z,x,y,mux1);

//data muxes
    PIPOD HWDATA1 (p,data_in3,sel3,clk);
    PIPOD HWDATA2 (q,data_in4,sel4,clk);
    MUXD datamux (r,p,q,mux2);

   
    TRI_BUFF add_buff(address,Aout,z);
    TRI_BUFF_D data_buff(dataout,Dout,r);

    decoder dec1 (hsel_0,hsel_1,hsel_2,z,rst);

    BUFFER out1(slave_0,hsel_0);
    BUFFER out2(slave_1,hsel_1);
    BUFFER out3(slave_2,hsel_2);

// read data mux

    MUXR readMUX(dout,rdyout,respout,rdin1,rdin2,rdin3,rdy1,rdy2,rdy3,resp1,resp2,resp3,seld);





    
endmodule

test1_tb.v
`timescale 1ns/1ns
`include "control_states.v"
`include "data_path.v"
`include "MUX.v"
`include "PIPO.v"
`include "decoder.v"
`include "BUFFER.v"
`include "PIPOD.v"
`include "MUXD.v"
`include "MUXR.v"
`include "TRI_BUFF.v"
`include "TRI_BUFF_D.v"






module test1_tb;

reg [15:0] data_in1,data_in2;
reg [31:0] data_in3,data_in4;

reg clk,rst;
wire [15:0] address; //for address out

//for data put register from slaves
reg [31:0] rdin1,rdin2,rdin3;
reg [1:0] resp1,resp2,resp3;
reg rdy1,rdy2,rdy3;

//output data from slaves
wire [31:0] dout;
wire [1:0] respout;

//output data from master to slave
wire [31:0] dataout;


                
//data_path dpt1 (hsel_0,hsel_1,hsel_2,address,Aout,sel1,sel2,mux1,rst,data_in1,data_in2,clk);

data_path dpt(slave_0,slave_1,slave_2,address,Aout,sel1,sel2,mux1,rst,data_in1,data_in2,clk,
                                sel3,sel4,mux2,data_in3,data_in4,
                                rdin1,rdin2,rdin3,resp1,resp2,resp3,rdy1,rdy2,rdy3,dout,rdyout,respout,
                                dataout, Dout);
                                
                               

control_states cpt1(sel1,sel2,sel3,sel4,mux2,clk,mux1,rst,Aout,Dout);

initial
    begin
        clk = 1'b0;
        #1000 $finish;
    end

always #5 clk = ~clk;

initial
    begin
   
        rst = 1'b1; #1;

        data_in1 = 16'b0010000000001000; #1;
        data_in2 = 16'b0100000000001000; #1;

        data_in3 = 567; #1;
        data_in4 = 434; #1;

        rdin1 = 50;#1;
        rdin2 = 0;#1;
        rdin3 = 0;#1;

        resp1 = 2'b01;#1;
        resp2 = 2'b11;#1;
        resp1 = 2'b10;#1;

        rdy1 = 1;
        rdy2 = 0;
        rdy3 = 1;

       // data_in1 = 16'b0110000000001000; #1;

        rst = 1'b0; #500;

        rst = 1'b1;

       // #200;
        //rst = 1'b1;
        //data_in2 = 16'b1000000000001000; #50;
        //data_in1 = 16'b0000000000001000; #1;

       
    end

initial
    begin
    
        $dumpfile("test1_tb.vcd");
        $dumpvars(0,test1_tb);
        $display("End of test!!!");

    end

endmodule

test1_tb.vcd
$date
	Sun Dec 24 15:44:45 2023
$end
$version
	Icarus Verilog
$end
$timescale
	1ns
$end
$scope module test1_tb $end
$var wire 1 ! slave_2 $end
$var wire 1 " slave_1 $end
$var wire 1 # slave_0 $end
$var wire 1 $ sel4 $end
$var wire 1 % sel3 $end
$var wire 1 & sel2 $end
$var wire 1 ' sel1 $end
$var wire 2 ( respout [1:0] $end
$var wire 1 ) rdyout $end
$var wire 1 * mux2 $end
$var wire 1 + mux1 $end
$var wire 32 , dout [31:0] $end
$var wire 32 - dataout [31:0] $end
$var wire 16 . address [15:0] $end
$var wire 1 / Dout $end
$var wire 1 0 Aout $end
$var reg 1 1 clk $end
$var reg 16 2 data_in1 [15:0] $end
$var reg 16 3 data_in2 [15:0] $end
$var reg 32 4 data_in3 [31:0] $end
$var reg 32 5 data_in4 [31:0] $end
$var reg 32 6 rdin1 [31:0] $end
$var reg 32 7 rdin2 [31:0] $end
$var reg 32 8 rdin3 [31:0] $end
$var reg 1 9 rdy1 $end
$var reg 1 : rdy2 $end
$var reg 1 ; rdy3 $end
$var reg 2 < resp1 [1:0] $end
$var reg 2 = resp2 [1:0] $end
$var reg 2 > resp3 [1:0] $end
$var reg 1 ? rst $end
$scope module cpt1 $end
$var wire 1 1 clk $end
$var wire 1 ? rst $end
$var parameter 3 @ s0 $end
$var parameter 3 A s1 $end
$var parameter 3 B s2 $end
$var parameter 3 C s3 $end
$var parameter 3 D s4 $end
$var reg 1 0 Aout $end
$var reg 1 / Dout $end
$var reg 1 + mux1 $end
$var reg 1 * mux2 $end
$var reg 1 ' sel1 $end
$var reg 1 & sel2 $end
$var reg 1 % sel3 $end
$var reg 1 $ sel4 $end
$var reg 3 E state [2:0] $end
$upscope $end
$scope module dpt $end
$var wire 1 0 Aout $end
$var wire 1 / Dout $end
$var wire 1 1 clk $end
$var wire 16 F data_in1 [15:0] $end
$var wire 16 G data_in2 [15:0] $end
$var wire 32 H data_in3 [31:0] $end
$var wire 32 I data_in4 [31:0] $end
$var wire 1 + mux1 $end
$var wire 1 * mux2 $end
$var wire 32 J rdin1 [31:0] $end
$var wire 32 K rdin2 [31:0] $end
$var wire 32 L rdin3 [31:0] $end
$var wire 1 9 rdy1 $end
$var wire 1 : rdy2 $end
$var wire 1 ; rdy3 $end
$var wire 2 M resp1 [1:0] $end
$var wire 2 N resp2 [1:0] $end
$var wire 2 O resp3 [1:0] $end
$var wire 1 ? rst $end
$var wire 1 ' sel1 $end
$var wire 1 & sel2 $end
$var wire 1 % sel3 $end
$var wire 1 $ sel4 $end
$var wire 16 P z [15:0] $end
$var wire 16 Q y [15:0] $end
$var wire 16 R x [15:0] $end
$var wire 1 ! slave_2 $end
$var wire 1 " slave_1 $end
$var wire 1 # slave_0 $end
$var wire 3 S seld [2:0] $end
$var wire 2 T respout [1:0] $end
$var wire 1 ) rdyout $end
$var wire 32 U r [31:0] $end
$var wire 32 V q [31:0] $end
$var wire 32 W p [31:0] $end
$var wire 1 X hsel_2 $end
$var wire 1 Y hsel_1 $end
$var wire 1 Z hsel_0 $end
$var wire 32 [ dout [31:0] $end
$var wire 32 \ dataout [31:0] $end
$var wire 16 ] address [15:0] $end
$scope module HADDR1 $end
$var wire 1 1 clk $end
$var wire 16 ^ din [15:0] $end
$var wire 1 ' ld $end
$var reg 16 _ dout [15:0] $end
$upscope $end
$scope module HADDR2 $end
$var wire 1 1 clk $end
$var wire 16 ` din [15:0] $end
$var wire 1 & ld $end
$var reg 16 a dout [15:0] $end
$upscope $end
$scope module HWDATA1 $end
$var wire 1 1 clk $end
$var wire 32 b din [31:0] $end
$var wire 1 % ld $end
$var reg 32 c dout [31:0] $end
$upscope $end
$scope module HWDATA2 $end
$var wire 1 1 clk $end
$var wire 32 d din [31:0] $end
$var wire 1 $ ld $end
$var reg 32 e dout [31:0] $end
$upscope $end
$scope module add_buff $end
$var wire 1 0 en $end
$var wire 16 f out [15:0] $end
$var wire 16 g in [15:0] $end
$upscope $end
$scope module addressmux $end
$var wire 16 h in0 [15:0] $end
$var wire 16 i in1 [15:0] $end
$var wire 1 + sel $end
$var wire 16 j out [15:0] $end
$upscope $end
$scope module data_buff $end
$var wire 1 / en $end
$var wire 32 k out [31:0] $end
$var wire 32 l in [31:0] $end
$upscope $end
$scope module datamux $end
$var wire 32 m in0 [31:0] $end
$var wire 32 n in1 [31:0] $end
$var wire 1 * sel $end
$var wire 32 o out [31:0] $end
$upscope $end
$scope module dec1 $end
$var wire 16 p haddr [15:0] $end
$var wire 1 ? rst $end
$var reg 1 Z hsel_0 $end
$var reg 1 Y hsel_1 $end
$var reg 1 X hsel_2 $end
$upscope $end
$scope module out1 $end
$var wire 1 Z in $end
$var wire 1 # out $end
$upscope $end
$scope module out2 $end
$var wire 1 Y in $end
$var wire 1 " out $end
$upscope $end
$scope module out3 $end
$var wire 1 X in $end
$var wire 1 ! out $end
$upscope $end
$scope module readMUX $end
$var wire 32 q hrdata_1 [31:0] $end
$var wire 32 r hrdata_2 [31:0] $end
$var wire 32 s hrdata_3 [31:0] $end
$var wire 1 9 hreadyout_1 $end
$var wire 1 : hreadyout_2 $end
$var wire 1 ; hreadyout_3 $end
$var wire 2 t hresp_1 [1:0] $end
$var wire 2 u hresp_2 [1:0] $end
$var wire 2 v hresp_3 [1:0] $end
$var wire 3 w sel [2:0] $end
$var reg 32 x hrdata [31:0] $end
$var reg 1 ) hreadyout $end
$var reg 2 y hresponse [1:0] $end
$upscope $end
$upscope $end
$upscope $end
$enddefinitions $end
$comment Show the parameter values. $end
$dumpall
b100 D
b11 C
b10 B
b1 A
b0 @
$end
#0
$dumpvars
bz y
bz x
b0 w
bx v
bx u
bx t
bx s
bx r
bx q
bx p
bx o
bx n
bx m
bx l
bx k
bx j
bx i
bx h
bx g
bx f
bx e
bx d
bx c
bx b
bx a
bx `
bx _
bx ^
bx ]
bx \
bz [
0Z
0Y
0X
bx W
bx V
bx U
bz T
b0 S
bx R
bx Q
bx P
bx O
bx N
bx M
bx L
bx K
bx J
bx I
bx H
bx G
bx F
bx E
1?
bx >
bx =
bx <
x;
x:
x9
bx 8
bx 7
bx 6
bx 5
bx 4
bx 3
bx 2
01
x0
x/
bx .
bx -
bz ,
x+
x*
x)
bz (
x'
x&
x%
x$
0#
0"
0!
$end
#1
b10000000001000 2
b10000000001000 F
b10000000001000 ^
#2
b100000000001000 3
b100000000001000 G
b100000000001000 `
#3
b1000110111 4
b1000110111 H
b1000110111 b
#4
b110110010 5
b110110010 I
b110110010 d
#5
bz P
bz g
bz j
bz p
bz U
bz l
bz o
bz R
bz _
bz h
bz Q
bz a
bz i
bz W
bz c
bz m
bz V
bz e
bz n
b0 E
b110010 6
b110010 J
b110010 q
11
#6
b0 7
b0 K
b0 r
#7
b0 8
b0 L
b0 s
#8
b1 <
b1 M
b1 t
#9
b11 =
b11 N
b11 u
#10
b10 <
b10 M
b10 t
01
#11
0?
1;
0:
19
#15
b1 E
b0 -
b0 \
b0 k
b0 .
b0 ]
b0 f
11
0/
0*
0$
0%
00
0+
0&
0'
#20
01
#25
b10 (
b10 T
b10 y
1)
b110010 ,
b110010 [
b110010 x
1#
b1 S
b1 w
1Z
b10000000001000 P
b10000000001000 g
b10000000001000 j
b10000000001000 p
b1000110111 U
b1000110111 l
b1000110111 o
b10000000001000 R
b10000000001000 _
b10000000001000 h
b1000110111 W
b1000110111 c
b1000110111 m
b10 E
b1000110111 -
b1000110111 \
b1000110111 k
b10000000001000 .
b10000000001000 ]
b10000000001000 f
11
1/
1%
10
1'
#30
01
#35
bz (
bz T
bz y
bz ,
bz [
bz x
0#
b0 S
b0 w
0Z
bz U
bz l
bz o
bz P
bz g
bz j
bz p
b11 E
b110110010 V
b110110010 e
b110110010 n
bz W
bz c
bz m
b100000000001000 Q
b100000000001000 a
b100000000001000 i
bz R
bz _
bz h
b0 -
b0 \
b0 k
b0 .
b0 ]
b0 f
11
0/
1$
0%
00
1&
0'
#40
01
#45
b100 E
b11 (
b11 T
b11 y
0)
b0 ,
b0 [
b0 x
1"
b10 S
b10 w
1Y
b110110010 -
b110110010 \
b110110010 k
b110110010 U
b110110010 l
b110110010 o
b100000000001000 .
b100000000001000 ]
b100000000001000 f
b100000000001000 P
b100000000001000 g
b100000000001000 j
b100000000001000 p
11
1/
1*
10
1+
#50
01
#55
b0 E
bz V
bz e
bz n
bz Q
bz a
bz i
bz (
bz T
bz y
bz ,
bz [
bz x
0"
b0 S
b0 w
0Y
b0 -
b0 \
b0 k
bz U
bz l
bz o
b0 .
b0 ]
b0 f
bz P
bz g
bz j
bz p
11
0/
0*
0$
00
0+
0&
#60
01
#65
b1 E
11
#70
01
#75
b10 (
b10 T
b10 y
1)
b110010 ,
b110010 [
b110010 x
1#
b1 S
b1 w
1Z
b1000110111 U
b1000110111 l
b1000110111 o
b10000000001000 P
b10000000001000 g
b10000000001000 j
b10000000001000 p
b10 E
b1000110111 W
b1000110111 c
b1000110111 m
b10000000001000 R
b10000000001000 _
b10000000001000 h
b1000110111 -
b1000110111 \
b1000110111 k
b10000000001000 .
b10000000001000 ]
b10000000001000 f
11
1/
1%
10
1'
#80
01
#85
bz (
bz T
bz y
bz ,
bz [
bz x
0#
b0 S
b0 w
0Z
bz P
bz g
bz j
bz p
bz U
bz l
bz o
bz R
bz _
bz h
b100000000001000 Q
b100000000001000 a
b100000000001000 i
bz W
bz c
bz m
b110110010 V
b110110010 e
b110110010 n
b11 E
b0 -
b0 \
b0 k
b0 .
b0 ]
b0 f
11
0/
1$
0%
00
1&
0'
#90
01
#95
b100 E
b11 (
b11 T
b11 y
0)
b0 ,
b0 [
b0 x
1"
b10 S
b10 w
1Y
b110110010 -
b110110010 \
b110110010 k
b110110010 U
b110110010 l
b110110010 o
b100000000001000 .
b100000000001000 ]
b100000000001000 f
b100000000001000 P
b100000000001000 g
b100000000001000 j
b100000000001000 p
11
1/
1*
10
1+
#100
01
#105
bz Q
bz a
bz i
bz V
bz e
bz n
b0 E
bz (
bz T
bz y
bz ,
bz [
bz x
0"
b0 S
b0 w
0Y
b0 -
b0 \
b0 k
bz U
bz l
bz o
b0 .
b0 ]
b0 f
bz P
bz g
bz j
bz p
11
0/
0*
0$
00
0+
0&
#110
01
#115
b1 E
11
#120
01
#125
b10 (
b10 T
b10 y
1)
b110010 ,
b110010 [
b110010 x
1#
b1 S
b1 w
1Z
b10000000001000 P
b10000000001000 g
b10000000001000 j
b10000000001000 p
b1000110111 U
b1000110111 l
b1000110111 o
b10000000001000 R
b10000000001000 _
b10000000001000 h
b1000110111 W
b1000110111 c
b1000110111 m
b10 E
b1000110111 -
b1000110111 \
b1000110111 k
b10000000001000 .
b10000000001000 ]
b10000000001000 f
11
1/
1%
10
1'
#130
01
#135
bz (
bz T
bz y
bz ,
bz [
bz x
0#
b0 S
b0 w
0Z
bz U
bz l
bz o
bz P
bz g
bz j
bz p
b11 E
b110110010 V
b110110010 e
b110110010 n
bz W
bz c
bz m
b100000000001000 Q
b100000000001000 a
b100000000001000 i
bz R
bz _
bz h
b0 -
b0 \
b0 k
b0 .
b0 ]
b0 f
11
0/
1$
0%
00
1&
0'
#140
01
#145
b100 E
b11 (
b11 T
b11 y
0)
b0 ,
b0 [
b0 x
1"
b10 S
b10 w
1Y
b110110010 -
b110110010 \
b110110010 k
b110110010 U
b110110010 l
b110110010 o
b100000000001000 .
b100000000001000 ]
b100000000001000 f
b100000000001000 P
b100000000001000 g
b100000000001000 j
b100000000001000 p
11
1/
1*
10
1+
#150
01
#155
b0 E
bz V
bz e
bz n
bz Q
bz a
bz i
bz (
bz T
bz y
bz ,
bz [
bz x
0"
b0 S
b0 w
0Y
b0 -
b0 \
b0 k
bz U
bz l
bz o
b0 .
b0 ]
b0 f
bz P
bz g
bz j
bz p
11
0/
0*
0$
00
0+
0&
#160
01
#165
b1 E
11
#170
01
#175
b10 (
b10 T
b10 y
1)
b110010 ,
b110010 [
b110010 x
1#
b1 S
b1 w
1Z
b1000110111 U
b1000110111 l
b1000110111 o
b10000000001000 P
b10000000001000 g
b10000000001000 j
b10000000001000 p
b10 E
b1000110111 W
b1000110111 c
b1000110111 m
b10000000001000 R
b10000000001000 _
b10000000001000 h
b1000110111 -
b1000110111 \
b1000110111 k
b10000000001000 .
b10000000001000 ]
b10000000001000 f
11
1/
1%
10
1'
#180
01
#185
bz (
bz T
bz y
bz ,
bz [
bz x
0#
b0 S
b0 w
0Z
bz P
bz g
bz j
bz p
bz U
bz l
bz o
bz R
bz _
bz h
b100000000001000 Q
b100000000001000 a
b100000000001000 i
bz W
bz c
bz m
b110110010 V
b110110010 e
b110110010 n
b11 E
b0 -
b0 \
b0 k
b0 .
b0 ]
b0 f
11
0/
1$
0%
00
1&
0'
#190
01
#195
b100 E
b11 (
b11 T
b11 y
0)
b0 ,
b0 [
b0 x
1"
b10 S
b10 w
1Y
b110110010 -
b110110010 \
b110110010 k
b110110010 U
b110110010 l
b110110010 o
b100000000001000 .
b100000000001000 ]
b100000000001000 f
b100000000001000 P
b100000000001000 g
b100000000001000 j
b100000000001000 p
11
1/
1*
10
1+
#200
01
#205
bz Q
bz a
bz i
bz V
bz e
bz n
b0 E
bz (
bz T
bz y
bz ,
bz [
bz x
0"
b0 S
b0 w
0Y
b0 -
b0 \
b0 k
bz U
bz l
bz o
b0 .
b0 ]
b0 f
bz P
bz g
bz j
bz p
11
0/
0*
0$
00
0+
0&
#210
01
#215
b1 E
11
#220
01
#225
b10 (
b10 T
b10 y
1)
b110010 ,
b110010 [
b110010 x
1#
b1 S
b1 w
1Z
b10000000001000 P
b10000000001000 g
b10000000001000 j
b10000000001000 p
b1000110111 U
b1000110111 l
b1000110111 o
b10000000001000 R
b10000000001000 _
b10000000001000 h
b1000110111 W
b1000110111 c
b1000110111 m
b10 E
b1000110111 -
b1000110111 \
b1000110111 k
b10000000001000 .
b10000000001000 ]
b10000000001000 f
11
1/
1%
10
1'
#230
01
#235
bz (
bz T
bz y
bz ,
bz [
bz x
0#
b0 S
b0 w
0Z
bz U
bz l
bz o
bz P
bz g
bz j
bz p
b11 E
b110110010 V
b110110010 e
b110110010 n
bz W
bz c
bz m
b100000000001000 Q
b100000000001000 a
b100000000001000 i
bz R
bz _
bz h
b0 -
b0 \
b0 k
b0 .
b0 ]
b0 f
11
0/
1$
0%
00
1&
0'
#240
01
#245
b100 E
b11 (
b11 T
b11 y
0)
b0 ,
b0 [
b0 x
1"
b10 S
b10 w
1Y
b110110010 -
b110110010 \
b110110010 k
b110110010 U
b110110010 l
b110110010 o
b100000000001000 .
b100000000001000 ]
b100000000001000 f
b100000000001000 P
b100000000001000 g
b100000000001000 j
b100000000001000 p
11
1/
1*
10
1+
#250
01
#255
b0 E
bz V
bz e
bz n
bz Q
bz a
bz i
bz (
bz T
bz y
bz ,
bz [
bz x
0"
b0 S
b0 w
0Y
b0 -
b0 \
b0 k
bz U
bz l
bz o
b0 .
b0 ]
b0 f
bz P
bz g
bz j
bz p
11
0/
0*
0$
00
0+
0&
#260
01
#265
b1 E
11
#270
01
#275
b10 (
b10 T
b10 y
1)
b110010 ,
b110010 [
b110010 x
1#
b1 S
b1 w
1Z
b1000110111 U
b1000110111 l
b1000110111 o
b10000000001000 P
b10000000001000 g
b10000000001000 j
b10000000001000 p
b10 E
b1000110111 W
b1000110111 c
b1000110111 m
b10000000001000 R
b10000000001000 _
b10000000001000 h
b1000110111 -
b1000110111 \
b1000110111 k
b10000000001000 .
b10000000001000 ]
b10000000001000 f
11
1/
1%
10
1'
#280
01
#285
bz (
bz T
bz y
bz ,
bz [
bz x
0#
b0 S
b0 w
0Z
bz P
bz g
bz j
bz p
bz U
bz l
bz o
bz R
bz _
bz h
b100000000001000 Q
b100000000001000 a
b100000000001000 i
bz W
bz c
bz m
b110110010 V
b110110010 e
b110110010 n
b11 E
b0 -
b0 \
b0 k
b0 .
b0 ]
b0 f
11
0/
1$
0%
00
1&
0'
#290
01
#295
b100 E
b11 (
b11 T
b11 y
0)
b0 ,
b0 [
b0 x
1"
b10 S
b10 w
1Y
b110110010 -
b110110010 \
b110110010 k
b110110010 U
b110110010 l
b110110010 o
b100000000001000 .
b100000000001000 ]
b100000000001000 f
b100000000001000 P
b100000000001000 g
b100000000001000 j
b100000000001000 p
11
1/
1*
10
1+
#300
01
#305
bz Q
bz a
bz i
bz V
bz e
bz n
b0 E
bz (
bz T
bz y
bz ,
bz [
bz x
0"
b0 S
b0 w
0Y
b0 -
b0 \
b0 k
bz U
bz l
bz o
b0 .
b0 ]
b0 f
bz P
bz g
bz j
bz p
11
0/
0*
0$
00
0+
0&
#310
01
#315
b1 E
11
#320
01
#325
b10 (
b10 T
b10 y
1)
b110010 ,
b110010 [
b110010 x
1#
b1 S
b1 w
1Z
b10000000001000 P
b10000000001000 g
b10000000001000 j
b10000000001000 p
b1000110111 U
b1000110111 l
b1000110111 o
b10000000001000 R
b10000000001000 _
b10000000001000 h
b1000110111 W
b1000110111 c
b1000110111 m
b10 E
b1000110111 -
b1000110111 \
b1000110111 k
b10000000001000 .
b10000000001000 ]
b10000000001000 f
11
1/
1%
10
1'
#330
01
#335
bz (
bz T
bz y
bz ,
bz [
bz x
0#
b0 S
b0 w
0Z
bz U
bz l
bz o
bz P
bz g
bz j
bz p
b11 E
b110110010 V
b110110010 e
b110110010 n
bz W
bz c
bz m
b100000000001000 Q
b100000000001000 a
b100000000001000 i
bz R
bz _
bz h
b0 -
b0 \
b0 k
b0 .
b0 ]
b0 f
11
0/
1$
0%
00
1&
0'
#340
01
#345
b100 E
b11 (
b11 T
b11 y
0)
b0 ,
b0 [
b0 x
1"
b10 S
b10 w
1Y
b110110010 -
b110110010 \
b110110010 k
b110110010 U
b110110010 l
b110110010 o
b100000000001000 .
b100000000001000 ]
b100000000001000 f
b100000000001000 P
b100000000001000 g
b100000000001000 j
b100000000001000 p
11
1/
1*
10
1+
#350
01
#355
b0 E
bz V
bz e
bz n
bz Q
bz a
bz i
bz (
bz T
bz y
bz ,
bz [
bz x
0"
b0 S
b0 w
0Y
b0 -
b0 \
b0 k
bz U
bz l
bz o
b0 .
b0 ]
b0 f
bz P
bz g
bz j
bz p
11
0/
0*
0$
00
0+
0&
#360
01
#365
b1 E
11
#370
01
#375
b10 (
b10 T
b10 y
1)
b110010 ,
b110010 [
b110010 x
1#
b1 S
b1 w
1Z
b1000110111 U
b1000110111 l
b1000110111 o
b10000000001000 P
b10000000001000 g
b10000000001000 j
b10000000001000 p
b10 E
b1000110111 W
b1000110111 c
b1000110111 m
b10000000001000 R
b10000000001000 _
b10000000001000 h
b1000110111 -
b1000110111 \
b1000110111 k
b10000000001000 .
b10000000001000 ]
b10000000001000 f
11
1/
1%
10
1'
#380
01
#385
bz (
bz T
bz y
bz ,
bz [
bz x
0#
b0 S
b0 w
0Z
bz P
bz g
bz j
bz p
bz U
bz l
bz o
bz R
bz _
bz h
b100000000001000 Q
b100000000001000 a
b100000000001000 i
bz W
bz c
bz m
b110110010 V
b110110010 e
b110110010 n
b11 E
b0 -
b0 \
b0 k
b0 .
b0 ]
b0 f
11
0/
1$
0%
00
1&
0'
#390
01
#395
b100 E
b11 (
b11 T
b11 y
0)
b0 ,
b0 [
b0 x
1"
b10 S
b10 w
1Y
b110110010 -
b110110010 \
b110110010 k
b110110010 U
b110110010 l
b110110010 o
b100000000001000 .
b100000000001000 ]
b100000000001000 f
b100000000001000 P
b100000000001000 g
b100000000001000 j
b100000000001000 p
11
1/
1*
10
1+
#400
01
#405
bz Q
bz a
bz i
bz V
bz e
bz n
b0 E
bz (
bz T
bz y
bz ,
bz [
bz x
0"
b0 S
b0 w
0Y
b0 -
b0 \
b0 k
bz U
bz l
bz o
b0 .
b0 ]
b0 f
bz P
bz g
bz j
bz p
11
0/
0*
0$
00
0+
0&
#410
01
#415
b1 E
11
#420
01
#425
b10 (
b10 T
b10 y
1)
b110010 ,
b110010 [
b110010 x
1#
b1 S
b1 w
1Z
b10000000001000 P
b10000000001000 g
b10000000001000 j
b10000000001000 p
b1000110111 U
b1000110111 l
b1000110111 o
b10000000001000 R
b10000000001000 _
b10000000001000 h
b1000110111 W
b1000110111 c
b1000110111 m
b10 E
b1000110111 -
b1000110111 \
b1000110111 k
b10000000001000 .
b10000000001000 ]
b10000000001000 f
11
1/
1%
10
1'
#430
01
#435
bz (
bz T
bz y
bz ,
bz [
bz x
0#
b0 S
b0 w
0Z
bz U
bz l
bz o
bz P
bz g
bz j
bz p
b11 E
b110110010 V
b110110010 e
b110110010 n
bz W
bz c
bz m
b100000000001000 Q
b100000000001000 a
b100000000001000 i
bz R
bz _
bz h
b0 -
b0 \
b0 k
b0 .
b0 ]
b0 f
11
0/
1$
0%
00
1&
0'
#440
01
#445
b100 E
b11 (
b11 T
b11 y
0)
b0 ,
b0 [
b0 x
1"
b10 S
b10 w
1Y
b110110010 -
b110110010 \
b110110010 k
b110110010 U
b110110010 l
b110110010 o
b100000000001000 .
b100000000001000 ]
b100000000001000 f
b100000000001000 P
b100000000001000 g
b100000000001000 j
b100000000001000 p
11
1/
1*
10
1+
#450
01
