control_states.v
module control_states(sel1,sel2,clk,mux1,rst);
input clk,rst;
output reg sel1,sel2,mux1;

reg [2:0] state;
parameter s0=3'b000, s1=3'b001, s2=3'b010, s3=3'b011, s4=3'b100;

always @(posedge clk)
    begin
        case (state)
            s0: if (~rst) state <= s1;
            s1: state <= s2;
            s2: state <= s3;
            s3: state <= s4;
            s4: state <= s0;
            default: state <= s0;
        endcase
    end

always @(state)
    begin
        case (state)
            s0: begin #1 sel1=0; sel2 = 0; mux1 = 0;end
            s1: begin #1 sel1=1; sel2 = 0; mux1 = 0; end
            s2: begin #1 sel1=0; sel2 = 1; mux1 = 0; end
            s3: begin #1 mux1=1; sel2 = 0; sel1 = 0; end
            s4: begin #1 sel1 = 0; sel2 = 0; mux1=0; end
            default: begin #1 sel1=0; sel2 = 0; mux1 = 0; end
        
        endcase

    end

endmodule

decoder.v
module decoder( hsel_0, hsel_1, hsel_2, haddr,rst);

 input [15:0] haddr;  // Input address from the Address mux
 input rst;
 output reg hsel_0; // hSelect  slave0
 output reg hsel_1; //hSelect  slave1 
 output reg hsel_2; //hSelect  slave2 
 
  
 always @(*)
  if(rst)
    begin
        hsel_0 = 1'b0;
        hsel_1 = 1'b0;
        hsel_2 = 1'b0;
    end
  else
    begin
    case (haddr[15:13])
        3'b001:
            begin
              hsel_0 = 1'b1;
              hsel_1 = 1'b0;
              hsel_2 = 1'b0;
            end

        3'b010:
            begin
              hsel_0 = 1'b0;
              hsel_1 = 1'b1;
              hsel_2 = 1'b0;
            end

        3'b011:
            begin
              hsel_0 = 1'b0;
              hsel_1 = 1'b0;
              hsel_2 = 1'b1;
            end
        default:
            begin
              hsel_0 = 1'b0;
              hsel_1 = 1'b0;
              hsel_2 = 1'b0;
            end

    endcase
    end


endmodule

MUX.v
module MUX(out, in0, in1, sel);

input sel;
input [15:0]in0, in1;
output [15:0]out;

assign out = sel ? in1 : in0;

endmodule

PIPO.v
module PIPO(dout,din,ld,clk);
    input [15:0] din;
    input ld,clk;
    output reg [15:0] dout;

    always @(posedge clk)
        begin
            if (ld) 
                dout <= din;
            else
                dout <= 16'bz; 
        end
endmodule

data_path.v
module data_path(hsel_0,hsel_1,hsel_2,sel1,sel2,mux1,rst,data_in1,data_in2,clk);
    input sel1,sel2,mux1,clk,rst;
    input [15:0] data_in1, data_in2;

    output hsel_0,hsel_1,hsel_2;
    //output [15:0] z;
    wire [15:0] x,y,z;

    PIPO HADDR1 (x,data_in1,sel1,clk);
    PIPO HADDR2 (y,data_in2,sel2,clk);
    MUX addressmux (z,x,y,mux1);
    decoder dec1 (hsel_0,hsel_1,hsel_2,z,rst);
    
endmodule

test1_tb.v
`timescale 1ns/1ns
`include "control_states.v"
`include "data_path.v"
`include "MUX.v"
`include "PIPO.v"
`include "decoder.v"

module test1_tb;

reg [15:0] data_in1,data_in2;
reg clk,rst;



data_path dpt1 (hsel_0,hsel_1,hsel_2,sel1,sel2,mux1,rst,data_in1,data_in2,clk);
control_states cpt1(sel1,sel2,clk,mux1,rst);

initial
    begin
        clk = 1'b0;
        #1000 $finish;
    end

always #5 clk = ~clk;

initial
    begin

        #1
        rst = 1'b0; #1;

        data_in1 = 16'b0010000000001000; #200;
        data_in2 = 16'b0100000000001000; #200;
        data_in1 = 16'b0110000000001000; #200;
        rst = 1'b0;
        #200;
        rst = 1'b1;
        //data_in2 = 16'b1000000000001000; #50;
        //data_in1 = 16'b0000000000001000; #1;

       
    end

initial
    begin
    
        $dumpfile("test1_tb.vcd");
        $dumpvars(0,test1_tb);
        $display("End of test!!!");

    end

endmodule

test1_tb.vcd
$date
	Sat Dec 23 21:47:02 2023
$end
$version
	Icarus Verilog
$end
$timescale
	1ns
$end
$scope module test1_tb $end
$var wire 1 ! sel2 $end
$var wire 1 " sel1 $end
$var wire 1 # mux1 $end
$var wire 1 $ hsel_2 $end
$var wire 1 % hsel_1 $end
$var wire 1 & hsel_0 $end
$var reg 1 ' clk $end
$var reg 16 ( data_in1 [15:0] $end
$var reg 16 ) data_in2 [15:0] $end
$var reg 1 * rst $end
$scope module cpt1 $end
$var wire 1 ' clk $end
$var wire 1 * rst $end
$var parameter 3 + s0 $end
$var parameter 3 , s1 $end
$var parameter 3 - s2 $end
$var parameter 3 . s3 $end
$var parameter 3 / s4 $end
$var reg 1 # mux1 $end
$var reg 1 " sel1 $end
$var reg 1 ! sel2 $end
$var reg 3 0 state [2:0] $end
$upscope $end
$scope module dpt1 $end
$var wire 1 ' clk $end
$var wire 16 1 data_in1 [15:0] $end
$var wire 16 2 data_in2 [15:0] $end
$var wire 1 # mux1 $end
$var wire 1 * rst $end
$var wire 1 " sel1 $end
$var wire 1 ! sel2 $end
$var wire 16 3 z [15:0] $end
$var wire 16 4 y [15:0] $end
$var wire 16 5 x [15:0] $end
$var wire 1 $ hsel_2 $end
$var wire 1 % hsel_1 $end
$var wire 1 & hsel_0 $end
$scope module HADDR1 $end
$var wire 1 ' clk $end
$var wire 16 6 din [15:0] $end
$var wire 1 " ld $end
$var reg 16 7 dout [15:0] $end
$upscope $end
$scope module HADDR2 $end
$var wire 1 ' clk $end
$var wire 16 8 din [15:0] $end
$var wire 1 ! ld $end
$var reg 16 9 dout [15:0] $end
$upscope $end
$scope module addressmux $end
$var wire 16 : in0 [15:0] $end
$var wire 16 ; in1 [15:0] $end
$var wire 1 # sel $end
$var wire 16 < out [15:0] $end
$upscope $end
$scope module dec1 $end
$var wire 16 = haddr [15:0] $end
$var wire 1 * rst $end
$var reg 1 & hsel_0 $end
$var reg 1 % hsel_1 $end
$var reg 1 $ hsel_2 $end
$upscope $end
$upscope $end
$upscope $end
$enddefinitions $end
$comment Show the parameter values. $end
$dumpall
b100 /
b11 .
b10 -
b1 ,
b0 +
$end
#0
$dumpvars
bx =
bx <
bx ;
bx :
bx 9
bx 8
bx 7
bx 6
bx 5
bx 4
bx 3
bx 2
bx 1
bx 0
x*
bx )
bx (
0'
x&
x%
x$
x#
x"
x!
$end
#1
0$
0%
0&
0*
#2
b10000000001000 (
b10000000001000 1
b10000000001000 6
#5
b0 0
1'
#6
0#
0!
0"
#10
0'
#15
b1 0
1'
#16
1"
#20
0'
#25
1&
b10000000001000 3
b10000000001000 <
b10000000001000 =
b10000000001000 5
b10000000001000 7
b10000000001000 :
b10 0
1'
#26
1!
0"
#30
0'
#35
b11 0
1'
#36
0&
bx 3
bx <
bx =
0!
1#
#40
0'
#45
b100 0
1'
#46
1&
b10000000001000 3
b10000000001000 <
b10000000001000 =
0#
#50
0'
#55
b0 0
1'
#60
0'
#65
b1 0
1'
#66
1"
#70
0'
#75
b10 0
1'
#76
1!
0"
#80
0'
#85
b11 0
1'
#86
0&
bx 3
bx <
bx =
0!
1#
#90
0'
#95
b100 0
1'
#96
1&
b10000000001000 3
b10000000001000 <
b10000000001000 =
0#
#100
0'
#105
b0 0
1'
#110
0'
#115
b1 0
1'
#116
1"
#120
0'
#125
b10 0
1'
#126
1!
0"
#130
0'
#135
b11 0
1'
#136
0&
bx 3
bx <
bx =
0!
1#
#140
0'
#145
b100 0
1'
#146
1&
b10000000001000 3
b10000000001000 <
b10000000001000 =
0#
#150
0'
#155
b0 0
1'
#160
0'
#165
b1 0
1'
#166
1"
#170
0'
#175
b10 0
1'
#176
1!
0"
#180
0'
#185
b11 0
1'
#186
0&
bx 3
bx <
bx =
0!
1#
#190
0'
#195
b100 0
1'
#196
1&
b10000000001000 3
b10000000001000 <
b10000000001000 =
0#
#200
0'
#202
b100000000001000 )
b100000000001000 2
b100000000001000 8
#205
b0 0
1'
#210
0'
#215
b1 0
1'
#216
1"
#220
0'
#225
b10 0
1'
#226
1!
0"
#230
0'
#235
b11 0
b100000000001000 4
b100000000001000 9
b100000000001000 ;
1'
#236
1%
0&
b100000000001000 3
b100000000001000 <
b100000000001000 =
0!
1#
#240
0'
#245
b100 0
1'
#246
0%
1&
b10000000001000 3
b10000000001000 <
b10000000001000 =
0#
#250
0'
#255
b0 0
1'
#260
0'
#265
b1 0
1'
#266
1"
#270
0'
#275
b10 0
1'
#276
1!
0"
#280
0'
#285
b11 0
1'
#286
1%
0&
b100000000001000 3
b100000000001000 <
b100000000001000 =
0!
1#
#290
0'
#295
b100 0
1'
#296
0%
1&
b10000000001000 3
b10000000001000 <
b10000000001000 =
0#
#300
0'
#305
b0 0
1'
#310
0'
#315
b1 0
1'
#316
1"
#320
0'
#325
b10 0
1'
#326
1!
0"
#330
0'
#335
b11 0
1'
#336
1%
0&
b100000000001000 3
b100000000001000 <
b100000000001000 =
0!
1#
#340
0'
#345
b100 0
1'
#346
0%
1&
b10000000001000 3
b10000000001000 <
b10000000001000 =
0#
#350
0'
#355
b0 0
1'
#360
0'
#365
b1 0
1'
#366
1"
#370
0'
#375
b10 0
1'
#376
1!
0"
#380
0'
#385
b11 0
1'
#386
1%
0&
b100000000001000 3
b100000000001000 <
b100000000001000 =
0!
1#
#390
0'
#395
b100 0
1'
#396
0%
1&
b10000000001000 3
b10000000001000 <
b10000000001000 =
0#
#400
0'
#402
b110000000001000 (
b110000000001000 1
b110000000001000 6
#405
b0 0
1'
#410
0'
#415
b1 0
1'
#416
1"
#420
0'
#425
1$
0&
b110000000001000 3
b110000000001000 <
b110000000001000 =
b110000000001000 5
b110000000001000 7
b110000000001000 :
b10 0
1'
#426
1!
0"
#430
0'
#435
b11 0
1'
#436
0$
1%
b100000000001000 3
b100000000001000 <
b100000000001000 =
0!
1#
#440
0'
#445
b100 0
1'
#446
1$
0%
b110000000001000 3
b110000000001000 <
b110000000001000 =
0#
#450
0'
#455
b0 0
1'
#460
0'
#465
b1 0
1'
#466
1"
#470
0'
#475
b10 0
1'
#476
1!
0"
#480
0'
#485
b11 0
1'
#486
0$
1%
b100000000001000 3
b100000000001000 <
b100000000001000 =
0!
1#
#490
0'
#495
b100 0
1'
#496
1$
0%
b110000000001000 3
b110000000001000 <
b110000000001000 =
0#
#500
0'
#505
b0 0
1'
#510
0'
#515
b1 0
1'
#516
1"
#520
0'
#525
b10 0
1'
#526
1!
0"
#530
0'
#535
b11 0
1'
#536
0$
1%
b100000000001000 3
b100000000001000 <
b100000000001000 =
0!
1#
#540
0'
#545
b100 0
1'
#546
1$
0%
b110000000001000 3
b110000000001000 <
b110000000001000 =
0#
#550
0'
#555
b0 0
1'
#560
0'
#565
b1 0
1'
#566
1"
#570
0'
#575
b10 0
1'
#576
1!
0"
#580
0'
#585
b11 0
1'
#586
0$
1%
b100000000001000 3
b100000000001000 <
b100000000001000 =
0!
1#
#590
0'
#595
b100 0
1'
#596
1$
0%
b110000000001000 3
b110000000001000 <
b110000000001000 =
0#
#600
0'
#605
b0 0
1'
#610
0'
#615
b1 0
1'
#616
1"
#620
0'
#625
b10 0
1'
#626
1!
0"
#630
0'
#635
b11 0
1'
#636
0$
1%
b100000000001000 3
b100000000001000 <
b100000000001000 =
0!
1#
#640
0'
#645
b100 0
1'
#646
1$
0%
b110000000001000 3
b110000000001000 <
b110000000001000 =
0#
#650
0'
#655
b0 0
1'
#660
0'
#665
b1 0
1'
#666
1"
#670
0'
#675
b10 0
1'
#676
1!
0"
#680
0'
#685
b11 0
1'
#686
0$
1%
b100000000001000 3
b100000000001000 <
b100000000001000 =
0!
1#
#690
0'
#695
b100 0
1'
#696
1$
0%
b110000000001000 3
b110000000001000 <
b110000000001000 =
0#
#700
0'
#705
b0 0
1'
#710
0'
#715
b1 0
1'
#716
1"
#720
0'
#725
b10 0
1'
#726
1!
0"
#730
0'
#735
b11 0
1'
#736
0$
1%
b100000000001000 3
b100000000001000 <
b100000000001000 =
0!
1#
#740
0'
#745
b100 0
1'
#746
1$
0%
b110000000001000 3
b110000000001000 <
b110000000001000 =
0#
#750
0'
#755
b0 0
1'
#760
0'
#765
b1 0
1'
#766
1"
#770
0'
#775
b10 0
1'
#776
1!
0"
#780
0'
#785
b11 0
1'
#786
0$
1%
b100000000001000 3
b100000000001000 <
b100000000001000 =
0!
1#
#790
0'
#795
b100 0
1'
#796
1$
0%
b110000000001000 3
b110000000001000 <
b110000000001000 =
0#
#800
0'
#802
0$
1*
#805
b0 0
1'
