control_test_1.v
module control_test_1(sel1,sel2,sel3,sel4,start,done,clk,mux1,mux2);
input clk,start;
output reg sel1,sel2,sel3,sel4,mux1,mux2,done;

reg [2:0] state;
parameter s0=3'b000, s1=3'b001, s2=3'b010, s3=3'b011, s4=3'b100, s5 = 3'b101;

always @(posedge clk)
    begin
        case (state)
            s0: if (start) state <= s1;
            s1: state <= s2;
            s2: state <= s3;
            s3: state <= s4;
            s4: state <= s5;
            s5: state <= s0;
            default: state <= s0;
        endcase
    end

always @(state)
    begin
        case (state)
            s0: begin #1 sel1=0; sel2 = 0; mux1 = 0; sel3=0; sel4 = 0; mux2 = 0; done=0; end
            s1: begin #1 sel1=1; sel2 = 0; mux1 = 0; sel3=0; sel4 = 0; mux2 = 0; done=0; end
            s2: begin #1 sel1=0; sel2 = 1; mux1 = 1; sel3=0; sel4 = 0; mux2 = 0; done=0; end
            s3: begin #1 sel1=0; sel2 = 0; mux1 = 0; sel3=1; sel4 = 0; mux2 = 0; done=0; end
            s4: begin #1 sel1=0; sel2 = 0; mux1 = 0; sel3=0; sel4 = 1; mux2 = 1; done=0; end
            s5: begin #1 sel1=0; sel2 = 0; mux1 = 0; sel3=0; sel4 = 0; mux2 = 0; done=1; end
            default: begin #1 sel1=0; sel2 = 0; mux1 = 0;sel3=0; sel4 = 0; mux2 = 0; done=0; end
        
        endcase

    end

endmodule

MUXR.v
module MUXR(hrdata,hreadyout,hresponse,hrdata_1,hrdata_2,hrdata_3,hreadyout_1,hreadyout_2,hreadyout_3,hresp_1,hresp_2,hresp_3,sel);


input [31:0] hrdata_1;
input [31:0] hrdata_2;
input [31:0] hrdata_3;

input hreadyout_1;
input hreadyout_2;
input hreadyout_3;

input hresp_1;
input hresp_2;
input hresp_3;

input [2:0] sel;

output reg [31:0] hrdata;
output reg hreadyout;
output reg hresponse;


always @(*)
    case (sel)
        3'b000:
            begin

                hrdata = hrdata_1;
                hreadyout = hreadyout_1;
                hresponse = hresp_1;
                  
            end


        3'b001:
            begin

                hrdata = hrdata_2;
                hreadyout = hreadyout_2;
                hresponse = hresp_2;

            end

        3'b010:
            begin

                hrdata = hrdata_3;
                hreadyout = hreadyout_3;
                hresponse = hresp_3;

            end

       default:
            begin

                hrdata = 0;
                hreadyout = 1'b0;
                hresponse = 1'b0;

            end


    endcase


endmodule

decoder.v
module decoder(

hsel_0,// hSelect  slave0  
hsel_1,//hSelect  slave1  
hsel_2,//hSelect  slave2  
haddr,// Input address from the Address mux

//sel_slave//To read data response MUX

);

 input [15:0] haddr;
 output hsel_0;
 output hsel_1;
 output hsel_2;
 
 always @(*)
    case (haddr[15:14])
        2'b00:
            begin
              hsel_0 = 1'b1;
              hsel_1 = 1'b0;
              hsel_2 = 1'b0;
            end

        2'b01:
            begin
              hsel_0 = 1'b0;
              hsel_1 = 1'b1;
              hsel_2 = 1'b0;
            end

        2'b10:
            begin
              hsel_0 = 1'b0;
              hsel_1 = 1'b0;
              hsel_2 = 1'b1;
            end
        default:
            begin
              hsel_0 = 1'b0;
              hsel_1 = 1'b0;
              hsel_2 = 1'b0;
            end

    endcase
    


endmodule

MUXD.v
module MUXD(out, in0, in1, sel);

input sel;
input [31:0]in0, in1;
output [31:0]out;

assign out = sel ? in1 : in0;

endmodule

MUX.v
module MUX(out, in0, in1, sel);

input sel;
input [15:0]in0, in1;
output [15:0]out;

assign out = sel ? in1 : in0;

endmodule

PIPOD.v
module PIPOD(dout,din,ld,clk);
    input [31:0] din;
    input ld,clk;
    output reg [31:0] dout;

    always @(posedge clk)
        if (ld) 
            dout <= din;

endmodule

PIPO.v
module PIPO(dout,din,ld,clk);
    input [15:0] din;
    input ld,clk;
    output reg [15:0] dout;

    always @(posedge clk)
        begin
            if (ld) 
                dout <= din;
            else
                dout <= 16'bz; 
        end
endmodule

data_path_test_1.v
module data_path_test_1(sel1,sel2,sel3,sel4,mux1,mux2,data_in1,data_in2,data_in3,data_in4,clk,hsel_1,hsel_2,hsel_3,
                                hrdata,hreadyout,hresponse,hrdata_1,hrdata_2,hrdata_3,hreadyout_1,hreadyout_2,hreadyout_3,hresp_1,hresp_2,hresp_3,sel);

    input sel1,sel2,sel3,sel4,mux1,mux2,clk;
    input [15:0] data_in1, data_in2;
    input [31:0] data_in3, data_in4;


    input [31:0] hrdata_1,hrdata_2,hrdata_3;
    input hreadyout_1,hreadyout_2,hreadyout_3,hresp_1,hresp_2,hresp_3;
    input [2:0] sel;

    output [31:0] hrdata;
    output hreadyout,hresponse;


    output hsel_1,hsel_2,hsel_3;
    
    

    wire [15:0] z,x,y;
    wire [31:0] p,q,r;
    
//This part has some errors
    assign sel[0] = test1_dec(hsel_1);
    assign sel[1] = hsel_2;
    assign sel[2] = hsel_3;
   

    PIPO HADDR1 (x,data_in1,sel1,clk);
    PIPO HADDR2 (y,data_in2,sel2,clk);

    PIPOD HWDATA1 (p,data_in3,sel3,clk);
    PIPOD HWDATA2 (q,data_in4,sel4,clk);

    MUX addressmux (z,x,y,mux1);
    MUXD datamux (r,p,q,mux2);
    decoder test1_dec (hsel_1,hsel_2,hsel_3,z);

    MUXR readmux (hrdata,hreadyout,hresponse,hrdata_1,hrdata_2,hrdata_3,hreadyout_1,hreadyout_2,hreadyout_3,hresp_1,hresp_2,hresp_3,sel);

    
endmodule

test1_tb.v
`timescale 1ns/1ns
`include "control_test_1.v"
`include "data_path_test_1.v"
`include "MUX.v"
`include "MUXD.v"
`include "MUXR.v"
`include "PIPO.v"
`include "PIPOD.v"
`include "decoder.v"

module test1_tb;

reg [15:0] data_in1,data_in2;
reg [31:0] data_in3,data_in4;


reg [31:0] hrdata_1,hrdata_2,hrdata_3;
reg hreadyout_1,hreadyout_2,hreadyout_3,hresp_1,hresp_2,hresp_3;

reg clk, start;
wire done;

wire [31:0] hrdata;
wire hreadyout,hresponse;

data_path_test_1 dpt1 (sel1,sel2,sel3,sel4,mux1,mux2,data_in1,data_in2,data_in3,data_in4,clk,hsel_1,hsel_2,hsel_3,
                        hrdata,hreadyout,hresponse,hrdata_1,hrdata_2,hrdata_3,hreadyout_1,hreadyout_2,hreadyout_3,hresp_1,hresp_2,hresp_3,sel);
control_test_1 cpt1(sel1,sel2,sel3,sel4,start,done,clk,mux1,mux2);

initial
    begin
        clk = 1'b0;
        #3 start = 1'b1;
        #500 $finish;
    end

always #5 clk = ~clk;

initial
    begin

        #1
        data_in1 = 16'b0000000000001000; #1;
        data_in2 = 16'b0010000000001000; #1;
        data_in3 = 10; #1;
        data_in4 = 20; #1;

        hrdata_1  = 30;#1;
        hrdata_2  = 40;#1;
        hrdata_3  = 50;#1;

        hreadyout_1 = 1'b1;#1;
        hreadyout_2 = 1'b0;#1;
        hreadyout_3 = 1'b0;#1;

        hresp_1 = 1'b1;#1;
        hresp_2 = 1'b0;#1;
        hresp_3 = 1'b0;#1;

       
    end

initial
    begin
    
        $dumpfile("test1_tb.vcd");
        $dumpvars(0,test1_tb);
        $display("End of test!!!");

    end

endmodule

test1_tb.vcd
$date
	Sat Dec 23 06:47:52 2023
$end
$version
	Icarus Verilog
$end
$timescale
	1ns
$end
$scope module test1_tb $end
$var wire 1 ! sel $end
$var wire 1 " sel4 $end
$var wire 1 # sel3 $end
$var wire 1 $ sel2 $end
$var wire 1 % sel1 $end
$var wire 1 & mux2 $end
$var wire 1 ' mux1 $end
$var wire 1 ( hsel_3 $end
$var wire 1 ) hsel_2 $end
$var wire 1 * hsel_1 $end
$var wire 1 + hresponse $end
$var wire 1 , hreadyout $end
$var wire 32 - hrdata [31:0] $end
$var wire 1 . done $end
$var reg 1 / clk $end
$var reg 16 0 data_in1 [15:0] $end
$var reg 16 1 data_in2 [15:0] $end
$var reg 32 2 data_in3 [31:0] $end
$var reg 32 3 data_in4 [31:0] $end
$var reg 32 4 hrdata_1 [31:0] $end
$var reg 32 5 hrdata_2 [31:0] $end
$var reg 32 6 hrdata_3 [31:0] $end
$var reg 1 7 hreadyout_1 $end
$var reg 1 8 hreadyout_2 $end
$var reg 1 9 hreadyout_3 $end
$var reg 1 : hresp_1 $end
$var reg 1 ; hresp_2 $end
$var reg 1 < hresp_3 $end
$var reg 1 = start $end
$scope module cpt1 $end
$var wire 1 / clk $end
$var wire 1 = start $end
$var parameter 3 > s0 $end
$var parameter 3 ? s1 $end
$var parameter 3 @ s2 $end
$var parameter 3 A s3 $end
$var parameter 3 B s4 $end
$var parameter 3 C s5 $end
$var reg 1 . done $end
$var reg 1 ' mux1 $end
$var reg 1 & mux2 $end
$var reg 1 % sel1 $end
$var reg 1 $ sel2 $end
$var reg 1 # sel3 $end
$var reg 1 " sel4 $end
$var reg 3 D state [2:0] $end
$upscope $end
$scope module dpt1 $end
$var wire 1 / clk $end
$var wire 16 E data_in1 [15:0] $end
$var wire 16 F data_in2 [15:0] $end
$var wire 32 G data_in3 [31:0] $end
$var wire 32 H data_in4 [31:0] $end
$var wire 32 I hrdata_1 [31:0] $end
$var wire 32 J hrdata_2 [31:0] $end
$var wire 32 K hrdata_3 [31:0] $end
$var wire 1 7 hreadyout_1 $end
$var wire 1 8 hreadyout_2 $end
$var wire 1 9 hreadyout_3 $end
$var wire 1 : hresp_1 $end
$var wire 1 ; hresp_2 $end
$var wire 1 < hresp_3 $end
$var wire 1 ' mux1 $end
$var wire 1 & mux2 $end
$var wire 3 L sel [2:0] $end
$var wire 1 % sel1 $end
$var wire 1 $ sel2 $end
$var wire 1 # sel3 $end
$var wire 1 " sel4 $end
$var wire 16 M z [15:0] $end
$var wire 16 N y [15:0] $end
$var wire 16 O x [15:0] $end
$var wire 32 P r [31:0] $end
$var wire 32 Q q [31:0] $end
$var wire 32 R p [31:0] $end
$var wire 1 ( hsel_3 $end
$var wire 1 ) hsel_2 $end
$var wire 1 * hsel_1 $end
$var wire 1 + hresponse $end
$var wire 1 , hreadyout $end
$var wire 32 S hrdata [31:0] $end
$scope module HADDR1 $end
$var wire 1 / clk $end
$var wire 16 T din [15:0] $end
$var wire 1 % ld $end
$var reg 16 U dout [15:0] $end
$upscope $end
$scope module HADDR2 $end
$var wire 1 / clk $end
$var wire 16 V din [15:0] $end
$var wire 1 $ ld $end
$var reg 16 W dout [15:0] $end
$upscope $end
$scope module HWDATA1 $end
$var wire 1 / clk $end
$var wire 32 X din [31:0] $end
$var wire 1 # ld $end
$var reg 32 Y dout [31:0] $end
$upscope $end
$scope module HWDATA2 $end
$var wire 1 / clk $end
$var wire 32 Z din [31:0] $end
$var wire 1 " ld $end
$var reg 32 [ dout [31:0] $end
$upscope $end
$scope module addressmux $end
$var wire 16 \ in0 [15:0] $end
$var wire 16 ] in1 [15:0] $end
$var wire 1 ' sel $end
$var wire 16 ^ out [15:0] $end
$upscope $end
$scope module datamux $end
$var wire 32 _ in0 [31:0] $end
$var wire 32 ` in1 [31:0] $end
$var wire 1 & sel $end
$var wire 32 a out [31:0] $end
$upscope $end
$scope module readmux $end
$var wire 32 b hrdata_1 [31:0] $end
$var wire 32 c hrdata_2 [31:0] $end
$var wire 32 d hrdata_3 [31:0] $end
$var wire 1 7 hreadyout_1 $end
$var wire 1 8 hreadyout_2 $end
$var wire 1 9 hreadyout_3 $end
$var wire 1 : hresp_1 $end
$var wire 1 ; hresp_2 $end
$var wire 1 < hresp_3 $end
$var wire 3 e sel [2:0] $end
$var reg 32 f hrdata [31:0] $end
$var reg 1 , hreadyout $end
$var reg 1 + hresponse $end
$upscope $end
$scope module test1_dec $end
$var wire 16 g haddr [15:0] $end
$var reg 1 * hsel_0 $end
$var reg 1 ) hsel_1 $end
$var reg 1 ( hsel_2 $end
$upscope $end
$upscope $end
$upscope $end
$enddefinitions $end
$comment Show the parameter values. $end
$dumpall
b101 C
b100 B
b11 A
b10 @
b1 ?
b0 >
$end
#0
$dumpvars
bx g
bx f
bx e
bx d
bx c
bx b
bx a
bx `
bx _
bx ^
bx ]
bx \
bx [
bx Z
bx Y
bx X
bx W
bx V
bx U
bx T
bx S
bx R
bx Q
bx P
bx O
bx N
bx M
bx L
bx K
bx J
bx I
bx H
bx G
bx F
bx E
bx D
x=
x<
x;
x:
x9
x8
x7
bx 6
bx 5
bx 4
bx 3
bx 2
bx 1
bx 0
0/
x.
bx -
x,
x+
x*
x)
x(
x'
x&
x%
x$
x#
x"
x!
$end
#1
b1000 0
b1000 E
b1000 T
#2
b10000000001000 1
b10000000001000 F
b10000000001000 V
#3
b1010 2
b1010 G
b1010 X
1=
#4
b10100 3
b10100 H
b10100 Z
#5
b0 D
0+
0,
b0 -
b0 S
b0 f
b11110 4
b11110 I
b11110 b
1/
#6
0.
0&
0"
0#
0'
0$
0%
b101000 5
b101000 J
b101000 c
#7
b110010 6
b110010 K
b110010 d
#8
17
#9
08
#10
09
0/
#11
1:
#12
0;
#13
0<
#15
b1 D
1/
#16
1%
#20
0/
#25
b101000 -
b101000 S
b101000 f
1!
b1 L
b1 e
0(
0)
1*
b1000 M
b1000 ^
b1000 g
b1000 O
b1000 U
b1000 \
b10 D
1/
#26
1+
1,
b11110 -
b11110 S
b11110 f
0!
b0 L
b0 e
0*
bx M
bx ^
bx g
1'
1$
0%
#30
0/
#35
0+
0,
b101000 -
b101000 S
b101000 f
1!
b1 L
b1 e
1*
b10000000001000 M
b10000000001000 ^
b10000000001000 g
b11 D
b10000000001000 N
b10000000001000 W
b10000000001000 ]
1/
#36
b1000 M
b1000 ^
b1000 g
1#
0'
0$
#40
0/
#45
b1010 P
b1010 a
b1010 R
b1010 Y
b1010 _
b100 D
1/
#46
bx P
bx a
1&
1"
0#
#50
0/
#55
b10100 P
b10100 a
b101 D
b10100 Q
b10100 [
b10100 `
1/
#56
b1010 P
b1010 a
1.
0&
0"
#60
0/
#65
b0 D
1/
#66
0.
#70
0/
#75
b1 D
1/
#76
1%
#80
0/
#85
b10 D
1/
#86
b10000000001000 M
b10000000001000 ^
b10000000001000 g
1'
1$
0%
#90
0/
#95
b11 D
1/
#96
b1000 M
b1000 ^
b1000 g
1#
0'
0$
#100
0/
#105
b100 D
1/
#106
b10100 P
b10100 a
1&
1"
0#
#110
0/
#115
b101 D
1/
#116
b1010 P
b1010 a
1.
0&
0"
#120
0/
#125
b0 D
1/
#126
0.
#130
0/
#135
b1 D
1/
#136
1%
#140
0/
#145
b10 D
1/
#146
b10000000001000 M
b10000000001000 ^
b10000000001000 g
1'
1$
0%
#150
0/
#155
b11 D
1/
#156
b1000 M
b1000 ^
b1000 g
1#
0'
0$
#160
0/
#165
b100 D
1/
#166
b10100 P
b10100 a
1&
1"
0#
#170
0/
#175
b101 D
1/
#176
b1010 P
b1010 a
1.
0&
0"
#180
0/
#185
b0 D
1/
#186
0.
#190
0/
#195
b1 D
1/
#196
1%
#200
0/
#205
b10 D
1/
#206
b10000000001000 M
b10000000001000 ^
b10000000001000 g
1'
1$
0%
#210
0/
#215
b11 D
1/
#216
b1000 M
b1000 ^
b1000 g
1#
0'
0$
#220
0/
#225
b100 D
1/
#226
b10100 P
b10100 a
1&
1"
0#
#230
0/
#235
b101 D
1/
#236
b1010 P
b1010 a
1.
0&
0"
#240
0/
#245
b0 D
1/
#246
0.
#250
0/
#255
b1 D
1/
#256
1%
#260
0/
#265
b10 D
1/
#266
b10000000001000 M
b10000000001000 ^
b10000000001000 g
1'
1$
0%
#270
0/
#275
b11 D
1/
#276
b1000 M
b1000 ^
b1000 g
1#
0'
0$
#280
0/
#285
b100 D
1/
#286
b10100 P
b10100 a
1&
1"
0#
#290
0/
#295
b101 D
1/
#296
b1010 P
b1010 a
1.
0&
0"
#300
0/
#305
b0 D
1/
#306
0.
#310
0/
#315
b1 D
1/
#316
1%
#320
0/
#325
b10 D
1/
#326
b10000000001000 M
b10000000001000 ^
b10000000001000 g
1'
1$
0%
#330
0/
#335
b11 D
1/
#336
b1000 M
b1000 ^
b1000 g
1#
0'
0$
#340
0/
#345
b100 D
1/
#346
b10100 P
b10100 a
1&
1"
0#
#350
0/
#355
b101 D
1/
#356
b1010 P
b1010 a
1.
0&
0"
#360
0/
#365
b0 D
1/
#366
0.
#370
0/
#375
b1 D
1/
#376
1%
#380
0/
#385
b10 D
1/
#386
b10000000001000 M
b10000000001000 ^
b10000000001000 g
1'
1$
0%
#390
0/
#395
b11 D
1/
#396
b1000 M
b1000 ^
b1000 g
1#
0'
0$
#400
0/
#405
b100 D
1/
#406
b10100 P
b10100 a
1&
1"
0#
#410
0/
#415
b101 D
1/
#416
b1010 P
b1010 a
1.
0&
0"
#420
0/
#425
b0 D
1/
#426
0.
#430
0/
#435
b1 D
1/
#436
1%
#440
0/
#445
b10 D
1/
#446
b10000000001000 M
b10000000001000 ^
b10000000001000 g
1'
1$
0%
#450
0/
#455
b11 D
1/
#456
b1000 M
b1000 ^
b1000 g
1#
0'
0$
#460
0/
#465
b100 D
1/
#466
b10100 P
b10100 a
1&
1"
0#
#470
0/
#475
b101 D
1/
#476
b1010 P
b1010 a
1.
0&
0"
#480
0/
#485
b0 D
1/
#486
0.
#490
0/
#495
b1 D
1/
#496
1%
