control_test_1.v
module control_test_1(sel1,sel2,sel3,sel4,start,done,clk,mux1,mux2);
input clk,start;
output reg sel1,sel2,sel3,sel4,mux1,mux2,done;

reg [2:0] state;
parameter s0=3'b000, s1=3'b001, s2=3'b010, s3=3'b011, s4=3'b100, s5 = 3'b101;

always @(posedge clk)
    begin
        case (state)
            s0: if (start) state <= s1;
            s1: state <= s2;
            s2: state <= s3;
            s3: state <= s4;
            s4: state <= s5;
            s5: state <= s0;
            default: state <= s0;
        endcase
    end

always @(state)
    begin
        case (state)
            s0: begin #1 sel1=0; sel2 = 0; mux1 = 0; sel3=0; sel4 = 0; mux2 = 0; done=0; end
            s1: begin #1 sel1=1; sel2 = 0; mux1 = 0; sel3=0; sel4 = 0; mux2 = 0; done=0; end
            s2: begin #1 sel1=0; sel2 = 1; mux1 = 1; sel3=0; sel4 = 0; mux2 = 0; done=0; end
            s3: begin #1 sel1=0; sel2 = 0; mux1 = 0; sel3=1; sel4 = 0; mux2 = 0; done=0; end
            s4: begin #1 sel1=0; sel2 = 0; mux1 = 0; sel3=0; sel4 = 1; mux2 = 1; done=0; end
            s5: begin #1 sel1=0; sel2 = 0; mux1 = 0; sel3=0; sel4 = 0; mux2 = 0; done=1; end
            default: begin #1 sel1=0; sel2 = 0; mux1 = 0;sel3=0; sel4 = 0; mux2 = 0; done=0; end
        
        endcase

    end

endmodule

decoder.v
module decoder(

hsel_0,// hSelect  slave0  
hsel_1,//hSelect  slave1  
hsel_2,//hSelect  slave2  
haddr,// Input address from the Address mux

//sel_slave//To read data response MUX

);

 input [15:0] haddr;
 output hsel_0;
 output hsel_1;
 output hsel_2;
 
 always @(*)
    case (haddr[15:14])
        2'b00:
            begin
              hsel_0 = 1'b1;
              hsel_1 = 1'b0;
              hsel_2 = 1'b0;
            end

        2'b01:
            begin
              hsel_0 = 1'b0;
              hsel_1 = 1'b1;
              hsel_2 = 1'b0;
            end

        2'b10:
            begin
              hsel_0 = 1'b0;
              hsel_1 = 1'b0;
              hsel_2 = 1'b1;
            end
        default:
            begin
              hsel_0 = 1'b0;
              hsel_1 = 1'b0;
              hsel_2 = 1'b0;
            end

    endcase
    


endmodule

MUXD.v
module MUXD(out, in0, in1, sel);

input sel;
input [31:0]in0, in1;
output [31:0]out;

assign out = sel ? in1 : in0;

endmodule

MUX.v
module MUX(out, in0, in1, sel);

input sel;
input [15:0]in0, in1;
output [15:0]out;

assign out = sel ? in1 : in0;

endmodule

PIPOD.v
module PIPOD(dout,din,ld,clk);
    input [31:0] din;
    input ld,clk;
    output reg [31:0] dout;

    always @(posedge clk)
        if (ld) 
            dout <= din;

endmodule

PIPO.v
module PIPO(dout,din,ld,clk);
    input [15:0] din;
    input ld,clk;
    output reg [15:0] dout;

    always @(posedge clk)
        begin
            if (ld) 
                dout <= din;
            else
                dout <= 16'bz; 
        end
endmodule

data_path_test_1.v
module data_path_test_1(sel1,sel2,sel3,sel4,mux1,mux2,data_in1,data_in2,data_in3,data_in4,clk,hsel_1,hsel_2,hsel_3);

    input sel1,sel2,sel3,sel4,mux1,mux2,clk;
    input [15:0] data_in1, data_in2;
    input [31:0] data_in3, data_in4;
    output hsel_1,hsel_2,hsel_3;
    wire [15:0] z,x,y;
    wire [31:0] p,q,r;

    PIPO HADDR1 (x,data_in1,sel1,clk);
    PIPO HADDR2 (y,data_in2,sel2,clk);

    PIPOD HWDATA1 (p,data_in3,sel3,clk);
    PIPOD HWDATA2 (q,data_in4,sel4,clk);

    MUX addressmux (z,x,y,mux1);
    MUXD datamux (r,p,q,mux2);


    decoder test1_dec (hsel_1,hsel_2,hsel_3,z);
    
endmodule

test1_tb.v
`timescale 1ns/1ns
`include "control_test_1.v"
`include "data_path_test_1.v"
`include "MUX.v"
`include "MUXD.v"
`include "PIPO.v"
`include "PIPOD.v"
`include "decoder.v"

module test1_tb;

reg [15:0] data_in1,data_in2;
reg [31:0] data_in3,data_in4;

reg clk, start;
wire done;

data_path_test_1 dpt1 (sel1,sel2,sel3,sel4,mux1,mux2,data_in1,data_in2,data_in3,data_in4,clk,hsel_1,hsel_2,hsel_3);
control_test_1 cpt1(sel1,sel2,sel3,sel4,start,done,clk,mux1,mux2);

initial
    begin
        clk = 1'b0;
        #3 start = 1'b1;
        #500 $finish;
    end

always #5 clk = ~clk;

initial
    begin

        #1
        data_in1 = 16'b0000000000001000; #1;
        data_in2 = 16'b0100000000001000; #1;
        data_in3 = 10; #1;
        data_in4 = 20; #1;

       
    end

initial
    begin
    
        $dumpfile("test1_tb.vcd");
        $dumpvars(0,test1_tb);
        $display("End of test!!!");

    end

endmodule

test1_tb.vcd
$date
	Fri Dec 22 19:07:46 2023
$end
$version
	Icarus Verilog
$end
$timescale
	1ns
$end
$scope module test1_tb $end
$var wire 1 ! sel4 $end
$var wire 1 " sel3 $end
$var wire 1 # sel2 $end
$var wire 1 $ sel1 $end
$var wire 1 % mux2 $end
$var wire 1 & mux1 $end
$var wire 1 ' hsel_3 $end
$var wire 1 ( hsel_2 $end
$var wire 1 ) hsel_1 $end
$var wire 1 * done $end
$var reg 1 + clk $end
$var reg 16 , data_in1 [15:0] $end
$var reg 16 - data_in2 [15:0] $end
$var reg 32 . data_in3 [31:0] $end
$var reg 32 / data_in4 [31:0] $end
$var reg 1 0 start $end
$scope module cpt1 $end
$var wire 1 + clk $end
$var wire 1 0 start $end
$var parameter 3 1 s0 $end
$var parameter 3 2 s1 $end
$var parameter 3 3 s2 $end
$var parameter 3 4 s3 $end
$var parameter 3 5 s4 $end
$var parameter 3 6 s5 $end
$var reg 1 * done $end
$var reg 1 & mux1 $end
$var reg 1 % mux2 $end
$var reg 1 $ sel1 $end
$var reg 1 # sel2 $end
$var reg 1 " sel3 $end
$var reg 1 ! sel4 $end
$var reg 3 7 state [2:0] $end
$upscope $end
$scope module dpt1 $end
$var wire 1 + clk $end
$var wire 16 8 data_in1 [15:0] $end
$var wire 16 9 data_in2 [15:0] $end
$var wire 32 : data_in3 [31:0] $end
$var wire 32 ; data_in4 [31:0] $end
$var wire 1 & mux1 $end
$var wire 1 % mux2 $end
$var wire 1 $ sel1 $end
$var wire 1 # sel2 $end
$var wire 1 " sel3 $end
$var wire 1 ! sel4 $end
$var wire 16 < z [15:0] $end
$var wire 16 = y [15:0] $end
$var wire 16 > x [15:0] $end
$var wire 32 ? r [31:0] $end
$var wire 32 @ q [31:0] $end
$var wire 32 A p [31:0] $end
$var wire 1 ' hsel_3 $end
$var wire 1 ( hsel_2 $end
$var wire 1 ) hsel_1 $end
$scope module HADDR1 $end
$var wire 1 + clk $end
$var wire 16 B din [15:0] $end
$var wire 1 $ ld $end
$var reg 16 C dout [15:0] $end
$upscope $end
$scope module HADDR2 $end
$var wire 1 + clk $end
$var wire 16 D din [15:0] $end
$var wire 1 # ld $end
$var reg 16 E dout [15:0] $end
$upscope $end
$scope module HWDATA1 $end
$var wire 1 + clk $end
$var wire 32 F din [31:0] $end
$var wire 1 " ld $end
$var reg 32 G dout [31:0] $end
$upscope $end
$scope module HWDATA2 $end
$var wire 1 + clk $end
$var wire 32 H din [31:0] $end
$var wire 1 ! ld $end
$var reg 32 I dout [31:0] $end
$upscope $end
$scope module addressmux $end
$var wire 16 J in0 [15:0] $end
$var wire 16 K in1 [15:0] $end
$var wire 1 & sel $end
$var wire 16 L out [15:0] $end
$upscope $end
$scope module datamux $end
$var wire 32 M in0 [31:0] $end
$var wire 32 N in1 [31:0] $end
$var wire 1 % sel $end
$var wire 32 O out [31:0] $end
$upscope $end
$scope module test1_dec $end
$var wire 16 P haddr [15:0] $end
$var reg 1 ) hsel_0 $end
$var reg 1 ( hsel_1 $end
$var reg 1 ' hsel_2 $end
$upscope $end
$upscope $end
$upscope $end
$enddefinitions $end
$comment Show the parameter values. $end
$dumpall
b101 6
b100 5
b11 4
b10 3
b1 2
b0 1
$end
#0
$dumpvars
bx P
bx O
bx N
bx M
bx L
bx K
bx J
bx I
bx H
bx G
bx F
bx E
bx D
bx C
bx B
bx A
bx @
bx ?
bx >
bx =
bx <
bx ;
bx :
bx 9
bx 8
bx 7
x0
bx /
bx .
bx -
bx ,
0+
x*
x)
x(
x'
x&
x%
x$
x#
x"
x!
$end
#1
b1000 ,
b1000 8
b1000 B
#2
b100000000001000 -
b100000000001000 9
b100000000001000 D
#3
b1010 .
b1010 :
b1010 F
10
#4
b10100 /
b10100 ;
b10100 H
#5
b0 7
1+
#6
0*
0%
0!
0"
0&
0#
0$
#10
0+
#15
b1 7
1+
#16
1$
#20
0+
#25
0'
0(
1)
b1000 <
b1000 L
b1000 P
b1000 >
b1000 C
b1000 J
b10 7
1+
#26
0)
bx <
bx L
bx P
1&
1#
0$
#30
0+
#35
1(
b100000000001000 <
b100000000001000 L
b100000000001000 P
b11 7
b100000000001000 =
b100000000001000 E
b100000000001000 K
1+
#36
0(
1)
b1000 <
b1000 L
b1000 P
1"
0&
0#
#40
0+
#45
b1010 ?
b1010 O
b1010 A
b1010 G
b1010 M
b100 7
1+
#46
bx ?
bx O
1%
1!
0"
#50
0+
#55
b10100 ?
b10100 O
b101 7
b10100 @
b10100 I
b10100 N
1+
#56
b1010 ?
b1010 O
1*
0%
0!
#60
0+
#65
b0 7
1+
#66
0*
#70
0+
#75
b1 7
1+
#76
1$
#80
0+
#85
b10 7
1+
#86
1(
0)
b100000000001000 <
b100000000001000 L
b100000000001000 P
1&
1#
0$
#90
0+
#95
b11 7
1+
#96
0(
1)
b1000 <
b1000 L
b1000 P
1"
0&
0#
#100
0+
#105
b100 7
1+
#106
b10100 ?
b10100 O
1%
1!
0"
#110
0+
#115
b101 7
1+
#116
b1010 ?
b1010 O
1*
0%
0!
#120
0+
#125
b0 7
1+
#126
0*
#130
0+
#135
b1 7
1+
#136
1$
#140
0+
#145
b10 7
1+
#146
1(
0)
b100000000001000 <
b100000000001000 L
b100000000001000 P
1&
1#
0$
#150
0+
#155
b11 7
1+
#156
0(
1)
b1000 <
b1000 L
b1000 P
1"
0&
0#
#160
0+
#165
b100 7
1+
#166
b10100 ?
b10100 O
1%
1!
0"
#170
0+
#175
b101 7
1+
#176
b1010 ?
b1010 O
1*
0%
0!
#180
0+
#185
b0 7
1+
#186
0*
#190
0+
#195
b1 7
1+
#196
1$
#200
0+
#205
b10 7
1+
#206
1(
0)
b100000000001000 <
b100000000001000 L
b100000000001000 P
1&
1#
0$
#210
0+
#215
b11 7
1+
#216
0(
1)
b1000 <
b1000 L
b1000 P
1"
0&
0#
#220
0+
#225
b100 7
1+
#226
b10100 ?
b10100 O
1%
1!
0"
#230
0+
#235
b101 7
1+
#236
b1010 ?
b1010 O
1*
0%
0!
#240
0+
#245
b0 7
1+
#246
0*
#250
0+
#255
b1 7
1+
#256
1$
#260
0+
#265
b10 7
1+
#266
1(
0)
b100000000001000 <
b100000000001000 L
b100000000001000 P
1&
1#
0$
#270
0+
#275
b11 7
1+
#276
0(
1)
b1000 <
b1000 L
b1000 P
1"
0&
0#
#280
0+
#285
b100 7
1+
#286
b10100 ?
b10100 O
1%
1!
0"
#290
0+
#295
b101 7
1+
#296
b1010 ?
b1010 O
1*
0%
0!
#300
0+
#305
b0 7
1+
#306
0*
#310
0+
#315
b1 7
1+
#316
1$
#320
0+
#325
b10 7
1+
#326
1(
0)
b100000000001000 <
b100000000001000 L
b100000000001000 P
1&
1#
0$
#330
0+
#335
b11 7
1+
#336
0(
1)
b1000 <
b1000 L
b1000 P
1"
0&
0#
#340
0+
#345
b100 7
1+
#346
b10100 ?
b10100 O
1%
1!
0"
#350
0+
#355
b101 7
1+
#356
b1010 ?
b1010 O
1*
0%
0!
#360
0+
#365
b0 7
1+
#366
0*
#370
0+
#375
b1 7
1+
#376
1$
#380
0+
#385
b10 7
1+
#386
1(
0)
b100000000001000 <
b100000000001000 L
b100000000001000 P
1&
1#
0$
#390
0+
#395
b11 7
1+
#396
0(
1)
b1000 <
b1000 L
b1000 P
1"
0&
0#
#400
0+
#405
b100 7
1+
#406
b10100 ?
b10100 O
1%
1!
0"
#410
0+
#415
b101 7
1+
#416
b1010 ?
b1010 O
1*
0%
0!
#420
0+
#425
b0 7
1+
#426
0*
#430
0+
#435
b1 7
1+
#436
1$
#440
0+
#445
b10 7
1+
#446
1(
0)
b100000000001000 <
b100000000001000 L
b100000000001000 P
1&
1#
0$
#450
0+
#455
b11 7
1+
#456
0(
1)
b1000 <
b1000 L
b1000 P
1"
0&
0#
#460
0+
#465
b100 7
1+
#466
b10100 ?
b10100 O
1%
1!
0"
#470
0+
#475
b101 7
1+
#476
b1010 ?
b1010 O
1*
0%
0!
#480
0+
#485
b0 7
1+
#486
0*
#490
0+
#495
b1 7
1+
#496
1$
